Workbook
Name _10._AñO__DE_CONSTRUCCION_DEL_BIEN_INMUEBLE: #REF!
Name _10._AñO__DE_CONSTRUCCION_DEL_BIEN_INMUEBLE: #REF!
Name _10._AñO__DE_CONSTRUCCION_DEL_BIEN_INMUEBLE: #REF!
Name _10._AñO__DE_CONSTRUCCION_DEL_BIEN_INMUEBLE: #REF!
Name _10._AñO__DE_CONSTRUCCION_DEL_BIEN_INMUEBLE: #REF!
Name _10._AñO__DE_CONSTRUCCION_DEL_BIEN_INMUEBLE: #REF!
Name Altura: OFFSET(#REF!,0,0,COUNTA(#REF!)-1)
Name Altura: OFFSET(#REF!,0,0,COUNTA(#REF!)-1)
Name Altura: OFFSET(#REF!,0,0,COUNTA(#REF!)-1)
Name Altura: OFFSET(#REF!,0,0,COUNTA(#REF!)-1)
Name Altura: OFFSET(#REF!,0,0,COUNTA(#REF!)-1)
Name AREADE: #REF!
Name AREADE: #REF!
Name AREADE: #REF!
Name AREADE: #REF!
Name AREADE: #REF!
Name AREADE: #REF!
Name AREAOCUP: #REF!
Name AREAOCUP: #REF!
Name AREAOCUP: #REF!
Name AREAOCUP: #REF!
Name AREAOCUP: #REF!
Name ÁreaOcupadaPrincipal: '[1]MEM. DESC. II'!$AF$36
Name ÁreaOcupadaSecundaria: '[1]MEM. DESC. II'!$AF$46
Name ÁreaOcupadaTotal: '[1]MEM. DESC. II'!$AF$48
Name ÁreasComunes: OFFSET(#REF!,0,0,COUNTA(#REF!)-1)
Name ÁreasComunes: OFFSET(#REF!,0,0,COUNTA(#REF!)-1)
Name ÁreasComunes: OFFSET(#REF!,0,0,COUNTA(#REF!)-1)
Name ÁreasComunes: OFFSET(#REF!,0,0,COUNTA(#REF!)-1)
Name ÁreasComunes: OFFSET(#REF!,0,0,COUNTA(#REF!)-1)
Name ÁreaTechada: '[2]MD Áreas'!$K$40
Name ÁreaTechada: '[3]MD Áreas'!$K$40
Name ÁreaTechada: '[3]MD Áreas'!$K$40
Name ÁreaTechada: '[2]MD Áreas'!$K$40
Name ÁreaTechadaPrincipal: '[1]MEM. DESC. II'!$K$36
Name ÁreaTechadaTotal: '[1]MEM. DESC. II'!$AF$38
Name ÁreaTerreno: '[2]MD Áreas'!$S$30
Name ÁreaTerreno: '[1]MEM. DESC. II'!$S$23
Name ÁreaTerreno: '[3]MD Áreas'!$S$30
Name ÁreaTerreno: '[1]MEM. DESC. II'!$S$23
Name ÁreaTerreno: '[2]MD Áreas'!$S$30
Name Ascensor: OFFSET(#REF!,0,0,COUNTA(#REF!)-1)
Name Ascensor: OFFSET(#REF!,0,0,COUNTA(#REF!)-1)
Name Ascensor: OFFSET(#REF!,0,0,COUNTA(#REF!)-1)
Name Ascensor: OFFSET(#REF!,0,0,COUNTA(#REF!)-1)
Name Ascensor: OFFSET(#REF!,0,0,COUNTA(#REF!)-1)
Name BAÑO_COLOR: OFFSET('[1]Lista-Data'!$BB$4,0,0,COUNTA('[1]Lista-Data'!$BB:$BB)-1)
Name BAÑO_GRIFERÍA: OFFSET('[1]Lista-Data'!$BC$4,0,0,COUNTA('[1]Lista-Data'!$BC:$BC)-1)
Name BAÑO_TIPO: OFFSET('[1]Lista-Data'!$BA$4,0,0,COUNTA('[1]Lista-Data'!$BA:$BA)-1)
Name BañoColor: OFFSET(#REF!,0,0,COUNTA(#REF!)-1)
Name BañoColor: OFFSET(#REF!,0,0,COUNTA(#REF!)-1)
Name BañoColor: OFFSET(#REF!,0,0,COUNTA(#REF!)-1)
Name BañoColor: OFFSET(#REF!,0,0,COUNTA(#REF!)-1)
Name BañoColor: OFFSET(#REF!,0,0,COUNTA(#REF!)-1)
Name BañoGrifería: OFFSET(#REF!,0,0,COUNTA(#REF!)-1)
Name BañoGrifería: OFFSET(#REF!,0,0,COUNTA(#REF!)-1)
Name BañoGrifería: OFFSET(#REF!,0,0,COUNTA(#REF!)-1)
Name BañoGrifería: OFFSET(#REF!,0,0,COUNTA(#REF!)-1)
Name BañoGrifería: OFFSET(#REF!,0,0,COUNTA(#REF!)-1)
Name BañoTipo: OFFSET(#REF!,0,0,COUNTA(#REF!)-2)

Sheet HR-EXCLUSIVO TERMINADO
A1: HOJA RESUMEN - TASACIONES
A2: HIPOTECA (INMUEBLE)
G17: PLANO DE UBICACIÓN | S17: FACHADA DEL INMUEBLE
B18: DATOS DEL CLIENTE
B20: CLIENTE | F20: =+'MEM. DESC. I'!J42 -> 0 | U20: CÓD CLIENTE
B22: N° GARANTÍA | M22: Ejm: G193 00110958 | U22: (09 Dígitos)
B24: PROPIETARIO | F24: =+'MEM. DESC. I'!J44 -> 0
B26: FECHA INSPECCIÓN | J26: TIPO DE TASACIÓN | N26: Hipotecaria
B28: DATOS DEL INMUEBLE
B30: DIRECCIÓN RRPP | F30: ='MEM. DESC. I'!J48 -> 0
B32: DISTRITO | L32: PROVINCIA | U32: DEPARTAMENTO
B34: GEOREFERENCIA | F34: (-) Latitud | L34: (-) Longitud | R34: (*) Datos obtenidos de Google Maps
B36: OCUPANTE | K36: TIPO DE PREDIO
F39: Uso | L39: %
B40: USO DEL INMUEBLE | F40: ='MEM. DESC. I'!J92 -> Departamento Flat | L40: =+'MEM. DESC. I'!Q92 -> 100 | O40: INMUEBLE CERCADO | V40: DECLARATORIA DE FÁBRICA
F41: ='MEM. DESC. I'!J93 -> 0 | L41: =+'MEM. DESC. I'!Q93 -> 0
B44: ZONIFICACIÓN | L44: DESCRIPCIÓN ZONIFICACIÓN
B46: ÁREA DE TRATAMIENTO CON FINES DE RENOVACIÓN URBANA | N46: Sí
B47: Según OPINIÓN del suscrito
B48: ZONA DE TRATAMIENTO ESPECIAL | N48: Sí | Q48: BIEN CULTURAL
B49: Según OPINIÓN del suscrito | Q49: Según OPINIÓN del suscrito
B51: AÑO DE CONSTRUCCIÓN | G51: 2 | J51: ESTADO DE CONSERVACIÓN | P51: Muy Bueno
B53: DISEÑADA PARA N° DE PISOS | H53: 2 | K53: Nº DE SÓTANOS | O53: 0 | R53: Nº DE PISOS | U53: 2
B55: MATERIAL DE CONSTRUCCIÓN | H55: Concreto - Ladrillo | M55: % | N55: 20 | Q55: ESPECIFICAR OTRO | U55: Concreto | Z55: % | AA55: 20
B57: CARGAS | D57: No | G57: GRAVÁMENES | J57: No | M57: COMENTARIOS/ADVERTENCIAS SOBRE LA CARGA
B60: OBSERVACIONES GENERALES
B64: EN CASO DE PREDIOS AGRICOLAS
B66: TIPO DE SUELO | K66: ACCESO DIRECTO DESDE ALGUNA VIA DE COMUNICACIÓN
B68: POZOS Y RESERVORIOS
B70: Número de Registro de Pozos (IRHS) | I70: Caudal(Litros/Seg) | M70: Conductividad Eléctrica del Agua (mmhos/cm) | V70: Permiso Vigente
AE73: .
B76: Notas: Para Predios Agrícolas el Valor Comercial y de Realización solo debe considerar el Valor de Terreno de la Propiedad, además de las Obras Civiles / Infraestructura, Pozos con licencia y Reservorios con los que cuente el inmueble. NO se debe considerar el Valor de los Cultivos, los Equipos de Riego, la Cosecha ni las inversiones en Packing. Asimismo es importante considerar en el cálculo del Valor de Terreno la disponibilidad suficiente de Recurso Hídrico para la Actividad Agrícola que se demande.
B79: RESULTADOS DE VALORIZACIÓN
B81: VALORES INSCRITOS EN RRPP | J81: MONEDA | M81: VALOR TOTAL | T81: VALOR DE TERRENO | Y81: VALOR DE EDIFICACION
B82: VALOR COMERCIAL | J82: US$ | M82: =T82+Y82 -> 0 | T82: =+REPOSICIÓN!X25 -> 0 | Y82: 0
J83: S/. | M83: =SUM(T83:AC83) -> 0 | T83: =+T82*$J$104 -> 0 | Y83: =+Y82*$J$104 -> 0
B84: VALOR DE REALIZACIÓN | J84: US$ | M84: =SUM(T84:AC84) -> 0 | T84: =+T82*(1-RESULTADOS!$R$54) -> 0 | Y84: =+Y82*(1-RESULTADOS!$R$54) -> 0
J85: S/. | M85: =SUM(T85:AC85) -> 0 | T85: =+T84*J104 -> 0 | Y85: =+Y84*J104 -> 0
B87: VALORES NO INSCRITOS EN RRPP | J87: MONEDA | M87: VALOR TOTAL | Y87: VALOR DE EDIFICACION
B88: VALOR COMERCIAL | J88: US$ | M88: =SUM(T88:AC88) -> 0 | T88: 0
J89: S/. | M89: =SUM(T89:AC89) -> 0 | T89: =+T88*J104 -> 0 | Y89: =+Y88*J104 -> 0
B90: VALOR DE REALIZACIÓN | J90: US$ | M90: =SUM(T90:AC90) -> 0 | T90: =+T88*(1-RESULTADOS!$R$54) -> 0 | Y90: =+Y88*(1-RESULTADOS!$R$54) -> 0
J91: S/. | M91: =SUM(T91:AC91) -> 0 | T91: =+T90*J104 -> 0 | Y91: =+Y90*J104 -> 0
B93: VALOR TOTAL DEL PREDIO | J93: MONEDA | M93: VALOR TOTAL | T93: INSCRITO EN RRPP | Y93: NO INSCRITO EN RRPP
B94: VALOR TOTAL COMERCIAL (INCL. CONSTRUCCIÓN DECLAR. Y NO DECLAR.) | J94: US$ | M94: =SUM(T94:AC94) -> 0 | T94: =M82 -> 0 | Y94: =M88 -> 0
J95: S/. | M95: =SUM(T95:AC95) -> 0 | T95: =+M83 -> 0 | Y95: =+M89 -> 0
B96: VALOR DE REALIZACIÓN | J96: US$ | M96: =SUM(T96:AC96) -> 0 | T96: =+M84 -> 0 | Y96: =+M90 -> 0
J97: S/. | M97: =SUM(T97:AC97) -> 0 | T97: =+M85 -> 0 | Y97: =+M91 -> 0
B99: VALOR DE RECONSTRUCCIÓN | J99: MONEDA | M99: VALOR TOTAL | T99: VSN EDIFICACION | Y99: VSN OBRAS COMPLEMENT.
B100: VALOR DE RECONSTRUCCIÓN (INCL. CONSTRUCCIONES DECLAR. Y NO DECLAR.) | J100: US$ | M100: =SUM(T100:AC100) -> 0 | T100: =+REPOSICIÓN!M61 -> 0 | Y100: =+REPOSICIÓN!O85 -> 0
J101: S/. | M101: =SUM(T101:AC101) -> 0 | T101: =+T100*J104 -> 0 | Y101: =+Y100*J104 -> 0
B102: NOTA: LOS VALORES CONSIGNADOS EN LA PRESENTE TASACION, CONSIDERAN LOS VALORES DE MERCADO Y CORRESPONDEN A TODOS LOS BIENES QUE EL BANCO HA INDICADO VALUAR.
B104: TIPO DE CAMBIO APLICADO | I104: : | J104: 3.58 | M104: Nuevos Soles / Dólar
B106: CUADRO COMPARATIVO DE ÁREAS
F108: Unidad de Medida | J108: Según Registros Públicos | O108: Según Autoavalúo | S108: Diferencia | V108: Según Inspección Ocular | AA108: Observaciones
B109: ÁREA TERRENO | F109: m2 | S109: =+J109-O109 -> 0
B110: ÁREA OCUPADA | F110: m3 | S110: =+J110-O110 -> 0
B111: ÁREA CONSTRUIDA | F111: m4 | S111: =+J111-O111 -> 0
B112: USO
T117: PERITO: | V117: VANET S.A.C.
T118: REPEV: | V118: 561-2001

Sheet RESUMEN
BH1: AREA OCUPADA | BI1: USO | BJ1: AREADE | BK1: MATERIAL | BL1: AÑO DE CONSTRUCCION/ Fecha de Fabricación | BM1: PISOS | BN1: SOTANOS | BO1: kilometros/hora | BP1: Estado de conservación del Bien | BQ1: operatividad del Bien
BH3: INQUILINO | BI3: ALMACEN | BJ3: BIEN CULTURAL | BK3: ADOBE | BL3: 1950 | BM3: 1 | BN3: 1 | BO3: 1000 | BP3: Muy Bueno | BQ3: 0.1
BH4: INVASOR | BI4: COMERCIAL | BJ4: OTROS | BK4: CONCRETO ARMADO | BL4: 1951 | BM4: 2 | BN4: 2 | BO4: 2000 | BP4: Bueno | BQ4: 0.2
BH5: PROPIETARIO | BI5: INDUSTRIAL | BJ5: TRATAMIENTO PARA RENOVACION URBANA | BK5: CONCRETO ARMADO CON PLACAS | BL5: 1952 | BM5: 3 | BN5: 3 | BO5: 3000 | BP5: Regular | BQ5: 0.3
BH6: INQUILINO/PROPIETARIO | BI6: OFICINA | BJ6: ZONA DE TRATAMIENTO ESPECIAL | BK6: MAMPOSTERIA | BL6: 1953 | BM6: 4 | BN6: 4 | BO6: 4000 | BP6: Malo | BQ6: 0.4
BH7: NO OCUPADO | BI7: OTROS | BK7: OTROS | BL7: 1954 | BM7: 5 | BN7: 5 | BO7: 5000 | BQ7: 0.5
BH8: SE DESCONOCE | BI8: VIVIENDA | BK8: QUINCHA Y/O MADERA | BL8: 1955 | BM8: 6 | BN8: 6 | BO8: 6000 | BQ8: 0.6
BK9: LADRILLO Y CEMENTO | BL9: 1956 | BM9: 7 | BN9: 7 | BO9: 7000 | BQ9: 0.7
BL10: 1957 | BM10: 8 | BN10: 8 | BO10: 8000 | BQ10: 0.8
B11: VALUACIÓN Nº 20 | AI11: =+'MEM. DESC. I'!Z13 -> XXXX-26 | BL11: 1958 | BM11: 9 | BN11: 9 | BO11: 9000 | BQ11: 0.9
B12: HOJA RESUMEN -TASACIONES HIPOTECA (INMUEBLE) | BL12: 1959 | BM12: 10 | BN12: 10 | BO12: 10000 | BQ12: 1
B13: DATOS DEL CLIENTE | BO13: 96000
B14: CLIENTE | K14: =+'HR-COMÚN TERMINADO'!F35 -> 0 | AQ14: CODIGO - | BL14: 1961 | BM14: 12 | BO14: 12000
B15: Nº GARANTIA | K15: =+'HR-COMÚN TERMINADO'!F37 -> 0 | O15: - | P15: =+'HR-COMÚN TERMINADO'!I37 -> 0 | BL15: 1962 | BM15: 13 | BO15: 13000
B16: PROPIETARIO | K16: =+'HR-COMÚN TERMINADO'!F39 -> 0 | BL16: 1963 | BM16: 14 | BO16: 14000
B17: FECHA TASACION | K17: =+'HR-COMÚN TERMINADO'!F41 -> 0 | BH17: TIPO DEL TERRENO | BI17: I.CERCAD | BJ17: INMUEBLE CERCADO | BK17: ACCESO A VIA | BL17: 1964 | BM17: 15 | BO17: 15000
BH18: LIMOSO | BL18: 1968 | BM18: 19 | BO18: 19000
B19: DATOS DEL INMUEBLE | BO19: 96000
B20: DIRECCION | K20: =+'HR-COMÚN TERMINADO'!F45 -> 0 | BH20: FRANCO ARCILLOSO | BI20: SI | BL20: 1970 | BM20: 21 | BO20: 21000
B21: DISTRITO | K21: =+'HR-COMÚN TERMINADO'!F47 -> 0 | BH21: FRANCO LIMOSO | BI21: NO | BJ21: DECLARATORIA DE FABRICA | BL21: 1971 | BM21: 22 | BO21: 22000
B22: DEPARTAMENTO | K22: =+'HR-COMÚN TERMINADO'!Y47 -> 0 | AC22: PROVINCIA | AN22: =+'HR-COMÚN TERMINADO'!O47 -> 0 | BL22: 1972 | BM22: 23 | BO22: 23000
B23: INMUEBLE OCUPADO POR | BJ23: TOTAL | BL23: 1973 | BM23: 24 | BO23: 24000
BJ24: PARCIAL | BL24: 1974 | BM24: 25 | BO24: 25000
B25: USO DEL LOCAL | K25: TIPO | T25: % | BJ25: NO TIENE | BL25: 1975 | BM25: 26 | BO25: 26000
K26: ALMACEN | BL26: 1976 | BM26: 27 | BO26: 27000
K27: COMERCIAL | BL27: 1977 | BM27: 28 | BO27: 28000
K28: INDUSTRIAL | BL28: 1978 | BM28: 29 | BO28: 29000
K29: OFICINA | BL29: 1979 | BM29: 30 | BO29: 30000
K30: VIVIENDA | BL30: 1980 | BM30: 31 | BO30: 31000
K31: TERRENO AGRICOLA | BL31: 1981 | BM31: 32 | BO31: 32000
K32: ……………….. | BL32: 1982 | BM32: 33 | BO32: 33000
BL33: 1983 | BM33: 34 | BO33: 34000
B34: INMUEBLE CERCADO | K34: =+'HR-COMÚN TERMINADO'!S55 -> Sí | AB34: DECLARATORIA DE FABRICA | BL34: 1984
B35: PARAMETRO DE ZONIFICACION | K35: =+'HR-COMÚN TERMINADO'!F59 -> 0 | AB35: DESCRIPCION DE ZONIFICACION | AS35: =+'HR-COMÚN TERMINADO'!R59 -> 0 | BL35: 1985 | BM35: 36 | BO35: 36000
B36: AREA DE: | K36: OTROS | BL36: 1986 | BM36: 38 | BO36: 38000
B37: AÑO CONSTRUC. | K37: =2020-'[9]MEMORIA Y VAL'!C171 -> 2020 | AB37: ESTADO-CONSERVAC. | AN37: =+'MEM. DESC. I'!X99 -> 0 | BL37: 1987 | BM37: 39 | BO37: 39000
B38: MATERIAL DE CONSTRUCCION | AJ38: ESPECIFICAR OTROS | BL38: 1988 | BM38: 40 | BO38: 40000
B39: DISEÑADA PARA | W39: N° DE SOTANOS | AN39: N° DE PISOS | BL39: 1989 | BM39: 41 | BO39: 41000
BL40: 1990 | BM40: 42 | BO40: 42000
B41: OBSERVACIONES | K41: La fábrica del inmueble se encuentra declarada al …….%. DETALLAR MAS DE SER NECESARIO. | BL41: 1991 | BM41: 46 | BO41: 46000
K42: El inmueble (SI/NO) cuenta con carga técnica inscrita en el asiento ………… correspondiente a …………, lo cual que (SI/NO) afecta el valor del inmueble. | BL42: 1991 | BM42: 46 | BO42: 46000
K43: =+'HR-COMÚN TERMINADO'!F75 -> 0 | BL43: 1992 | BM43: 46 | BO43: 46000
BL44: 1993 | BM44: 47 | BO44: 47000
BL45: 1994 | BM45: 48 | BO45: 48000
B46: TERRENO Y EDIFICACIONES | BL46: 1995 | BM46: 49 | BO46: 49000
BL47: 1996 | BM47: 50 | BO47: 50000
B48: NOTA: PARA TERRENOS AGRICOLAS EL VALOR COMERCIAL Y DE REALIZACION SOLO DEBE INCLUIR EL VALOR DE LA TIERRA, OBRAS CIVILES/INFRAESTRUCTURA, POZOS (CON LICENCIA) Y RESERVORIOS. NO DEBE INCLUIR CULTIVOS, EQUIPO DE RIEGO, COSECHA NI PACKING. ES IMPORTANTE AL MOMENTO DE ESTABLECER EL VALOR DE LA HECTAREA TENER EN CUENTA SI LAS TIERRAS TIENEN SUFICIENTE AGUA O NO PARA LA ACTIVIDAD AGRICOLA. | BL48: 1997 | BO48: 51000
BL49: 1998 | BO49: 52000
BL50: 1999 | BO50: 53000
BL51: 2000 | BO51: 54000
B52: VALOR DEL TERRENO | L52: US$ | O52: =+REPOSICIÓN!X25 -> 0 | AG52: S/ | AL52: =+O52*O66 -> 0 | BL52: 2001 | BO52: 55000
BL53: 2002 | BO53: 56000
B54: VALOR DE LAS EDIFICACIONES | L54: US$ | O54: =+BA64 -> 0 | AG54: S/ | AL54: =+BA64*O66 -> 0 | BL54: 2003 | BO54: 57000
BL55: 2004 | BO55: 58000
B56: DESCRIPCIÓN (*) Ejm: 1er Piso, 2do Piso, Obra Complementaria | S56: ÁREA Ejm: M2, HA | Z56: VALOR US$ / Unidad 2 Ejm: US$ /M2 , US$ /HA | AK56: % Depreciación | AT56: Factor Reajuste Comercial | BA56: US$ | BL56: 2005 | BO56: 59000
B57: Área techada | AT57: 1 | BL57: 2006 | BO57: 60000
B58: Área sin techar | AT58: 1 | BL58: 2007 | BO58: 60000
B59: VALOR DE LAS ÁREAS COMUNES | BA59: =+'[9]MEMORIA Y VAL'!AO356 -> 0 | BL59: 2008 | BO59: 60000
B60: VALOR DE LAS OBRAS COMPLEMENTARIAS | BA60: =+'[9]MEMORIA Y VAL'!AO365 -> 0 | BL60: 2009 | BO60: 60000
BL61: 2010 | BO61: 60000
B62: =+'[9]MEMORIA Y VAL'!$C$366 -> VALOR DEL ESTACIONAMIENTO Nº | BA62: =+'[9]MEMORIA Y VAL'!AO368 -> 0 | BL62: 2011 | BO62: 60000
B63: =+'[9]MEMORIA Y VAL'!$C$369 -> VALOR DEL DEPOSITO Nº | BA63: =+'[9]MEMORIA Y VAL'!AO371 -> 0 | BL63: 2012 | BO63: 60000
AK64: Valor de las Edificaciones | BA64: =SUM(BA57:BF63) -> 0 | BL64: 2016 | BO64: 63000
BL65: 2017 | BO65: 68000
B66: Tipo de cambio US$ 1.00 = S/ | O66: =+'HR-COMÚN TERMINADO'!J104 -> 3.48 | BL66: 2018 | BO66: 69000
BL67: 2019 | BO67: 70000
B68: TOTAL VALOR COMERCIAL | O68: US$ | S68: =+RESULTADOS!X39 -> 0 | AH68: S/ | AM68: =+S68*O66 -> 0 | BL68: 2020 | BO68: 55000
BL69: 2021 | BO69: 56000
B70: TOTAL VALOR DE REALIZACION | O70: US$ | S70: =+RESULTADOS!X58 -> 0 | AH70: S/ | AM70: =+S70*O66 -> 0 | BL70: 2022 | BO70: 57000
BL71: 2023 | BO71: 78000
B72: RECONSTRUCCIÓN | BO72: 96000
BL73: 2025 | BO73: 80000
B74: VALOR DE RECONSTRUCCIÓN | O74: US$ | S74: =+AT84 -> 0 | AH74: S/ | AM74: =+S74*O66 -> 0 | BL74: 2026 | BO74: 55000
BL75: 2027 | BO75: 82000
B76: DESCRIPCIÓN (*) Ejm: 1er Piso, 2do Piso, Obra Complementaria | S76: ÁREA Ejm: M2, HA | Z76: VALOR US$ / Unidad 2 Ejm: US$ /M2, US$ /HA | AK76: % Depreciación | AT76: US$ | BL76: 2028 | BO76: 59000
B77: =+B57 -> Área techada | S77: =+'[9]MEMORIA Y VAL'!C305 -> 0 | Z77: =+'[9]MEMORIA Y VAL'!N305 -> 0 | AK77: =+'[9]MEMORIA Y VAL'!AA305 -> 1 | AT77: =+'[9]MEMORIA Y VAL'!AO305 -> 0 | BO77: 84000
B78: =+B58 -> Área sin techar | S78: =+'[9]MEMORIA Y VAL'!C307 -> 0 | Z78: =+'[9]MEMORIA Y VAL'!N307 -> 200 | AK78: =+'[9]MEMORIA Y VAL'!AA307 -> 1 | AT78: =+'[9]MEMORIA Y VAL'!AO307 -> 0 | BO78: 84000
B79: =+B59 -> VALOR DE LAS ÁREAS COMUNES | AT79: =+'[9]MEMORIA Y VAL'!AO311 -> 0 | BO79: 84000
B80: =+B60 -> VALOR DE LAS OBRAS COMPLEMENTARIAS | AT80: =+'[9]MEMORIA Y VAL'!AO320 -> 0 | BO80: 84000
BO81: 84000
B82: =+'[9]MEMORIA Y VAL'!$C$330 -> VALOR DE RECONSTRUCCION DEL ESTACIONAMIENTO Nº | AT82: =+'[9]MEMORIA Y VAL'!AO330 -> 0 | BO82: 84000
B83: =+'[9]MEMORIA Y VAL'!$C$330 -> VALOR DE RECONSTRUCCION DEL ESTACIONAMIENTO Nº | AT83: =+'[9]MEMORIA Y VAL'!AO340 -> 0 | BO83: 84000
Z84: Valor de Reconstrucción de las Edificaciones | AT84: =SUM(AT77:BF83) -> 0 | BO84: 87000
BO85: 92000
B86: (*) Detallar todos los pisos con los que cuente la garantía | BO86: 93000
BO87: 94000
B88: Factor de depreciacion | O88: =1-'[9]MEMORIA Y VAL'!C200 -> 1 | Y88: %
B90: SI ES TERRENO AGRICOLA,INDICAR: TIPO DE TERRENO:
B91: TIENE ACCESO DIRECTO A ALGUNA VIA DE COMUNICACIÓN
B92: POZOS Y RESERVORIOS (PARA TERRENOS AGRICOLAS | BO92: 96000
BO93: 104000
B94: Número de registro de cada pozo (IRHS) | S94: Caudal (Litros/Seg) | AG94: Conductividad eléctrica del agua (mmhos/cm) | AT94: Indicar si los pozos cuentan con permiso vigente | BO94: 105000
BO95: 106000
BO96: 107000
BO97: 107000
BO98: 108000
BO99: 109000
B100: DOCUMENTACION REGISTRAL | BO100: 96000
BO101: 110000
N102: Unidad M2/HA | T102: FICHA RRPP | Z102: AUTOVALUO | AG102: DIFERENCIA | AN102: INSPECCION OCULAR DEL TASADOR | AX102: OBSERVACIONES DEL TASADOR
...

Sheet C2
C2: HOJA RESUMEN TASACIÓN DE INMUEBLES - FONDO MIVIVIENDA S.A. - C.02
A4: FECHA DE VALUACIÓN | I4: DE | T4: DE | V4: 2026
A6: ENTIDAD FINANCIERA | G6: BANCO DE CRÉDITO DEL PERÚ | Z6: PROPIETARIO | AA6: =+'MEM. DESC. I'!J44 -> 0
A8: BENEFICIARIO | G8: =+'MEM. DESC. I'!J42 -> 0 | AE8: DNI / LE / CIP / CE
A10: PERITO TASADOR | G10: VANET S.A.C. | AF10: REPEV. SBS | AK10: 561 2001
A12: UBICACIÓN DEL INMUEBLE | G12: Carrt. | I12: Av. | K12: Jr. | M12: Calle | O12: Psje | S12: =+'MEM. DESC. I'!J48 -> 0
A14: N° / Mza./Lt | F14: Dpto./Int. | N14: Urb./Loc
A16: Departamento | D16: =+'HR-COMÚN TERMINADO'!Y47 -> 0 | M16: Provincia | P16: =+'HR-COMÚN TERMINADO'!O47 -> 0 | Z16: Distrito | AG16: =+'HR-COMÚN TERMINADO'!F47 -> 0
A18: CLASIFICACIÓN | F18: BIEN FUTURO | M18: a) En Proyecto | T18: b) En Construcción | AC18: c) En acabados | AL18: d) Culminado
G19: *Bien futuro: inmueble en proyecto, en construcción o en acabados sin declaratoria de fábrica inscrita en RR.PP.
F20: BIEN TERMINADO | M20: Registro: RPI | T20: RPU | W20: Zona | AA20: Ficha | AF20: Partida | AL20: N° | AM20: =+'MEM. DESC. I'!S34 -> 0
F21: *Bien terminado: Inmueble con construcción terminada, con declaratoria de fábrica y de ser el caso independización inscritas en los RR.PP.
A23: DESCRIPCIÓN DEL INMUEBLE
A25: TIPO DE INMUEBLE | L25: CASA | W25: DEPARTAMENTO | AA25: X | AD25: Si vive en un departamento, indicar el piso
A27: AREAS | P27: AREA DEL TERRENO | R27: =+'MEM. DESC. II'!S44 -> 0 | U27: M2 | AG27: AREA CONSTRUIDA | AL27: =+'MEM. DESC. II'!K56 -> 0 | AO27: M2
A30: ESTADO DE CONSERVACIÓN | J30: Bueno | O30: Regular | S30: Malo | AA30: ANTIGÜEDAD CONSTRUCCIÓN | AL30: =+'MEM. DESC. I'!Q99 -> 0 | AO30: años
A34: Sala-Comedor | F34: SI | H34: NO | L34: Dormitorios (Cantidad) | Y34: Cochera (Cantidad)
A35: Cocina | F35: SI | H35: NO | L35: Dormitorio de Servicio | S35: SI | U35: NO | Y35: Jardín | AF35: SI | AJ35: NO
A36: Baños (Cantidad) | L36: Cuarto de Estudio | S36: SI | U36: NO | Y36: Terraza | AF36: SI | AJ36: NO
A37: Baño de Servicio | F37: SI | H37: NO | L37: Lavandería | S37: SI | U37: NO | Y37: Parque de uso común | AF37: SI | AJ37: NO
L38: Instalaciones de gas natural | S38: SI | U38: NO | Y38: Sala común | AF38: SI | AJ38: NO
Y39: Canchas/Gimnasios | AF39: SI | AJ39: NO
Y40: Piscina común | AF40: SI | AJ40: NO
A43: ESPECIFICACIONES TECNICAS
A45: ESTRUCTURAS
A46: CIMENTACIÓN | J46: COLUMNAS | Q46: VIGAS | X46: TECHOS | AE46: MUROS
A47: Platea de cimentación | J47: a) Concreto | Q47: a) Concreto | X47: Aligerado | AE47: Concreto | AM47: Tipos de albañilería
A48: Cimientos corridos | J48: b) Acero | Q48: b) Acero | X48: Maciso | AE48: Albañilería | AK48: Arcilla | AO48: Concreto
A49: Viga de cimentación | J49: a) y b) | Q49: a) y b) | AK49: Calcáreo | AO49: Adobe
A51: ACABADOS
B54: PUERTAS | E54: TIPO | I54: a) Apanelada | O54: b) Maciza | T54: c) Contraplacada | AB54: VENTANAS | AH54: Madera | AL54: Aluminio
E55: MATERIAL | I55: a) Fierro | O55: b) Madera | T55: c) Otros | AH55: Fierro | AL55: Otros
A58: MUEBLES DE COCINA | AB58: APARATOS SANITARIOS
A59: AMOBLADA | J59: NO AMOBLADA | AF59: BLANCO | AK59: COLOR
A61: PISOS
B62: AMBIENTE | H62: Vinílico | M62: Parquet | R62: Machimbrado | W62: Cemento | AB62: Cerámica | AH62: Otro
B63: Sala-Comedor
B64: Baños
B65: Dormitorios
A67: PRECIOS REFERENCIALES
A69: N° | B69: UBICACIÓN | P69: AT (m2) | U69: AC (m2) | Z69: PRECIO (US$) | AH69: FUENTE
A70: 1 | B70: =+'EST. MERCADO TERRENOS'!B22 -> Área Construida: 156.00/m2 Valor de venta total = US$ 640,000.00 Para determinar el valor de terreno se ha descontado el valor de la construcción = US$ 60,000.00 | P70: =+'EST. MERCADO TERRENOS'!BA22 -> 0 | U70: =+'EST. MERCADO TERRENOS'!BD22 -> 0 | Z70: =+'EST. MERCADO TERRENOS'!BV22 -> #DIV/0! | AH70: =+'EST. MERCADO TERRENOS'!I22 -> 0
A71: 2 | B71: =+'EST. MERCADO TERRENOS'!B23 -> 0 | P71: =+'EST. MERCADO TERRENOS'!BA23 -> 0 | U71: =+'EST. MERCADO TERRENOS'!BD23 -> 0 | Z71: =+'EST. MERCADO TERRENOS'!BV23 -> #DIV/0! | AH71: =+'EST. MERCADO TERRENOS'!I23 -> 0
A72: 3 | B72: =+'EST. MERCADO TERRENOS'!B24 -> 0 | P72: =+'EST. MERCADO TERRENOS'!BA24 -> 0 | U72: =+'EST. MERCADO TERRENOS'!BD24 -> 0 | Z72: =+'EST. MERCADO TERRENOS'!BV24 -> #DIV/0! | AH72: =+'EST. MERCADO TERRENOS'!I24 -> 0
A73: 4 | B73: =+COMPARACIÓN!B20 -> 0 | P73: =+COMPARACIÓN!BA20 -> 0 | U73: =+COMPARACIÓN!BD20 -> 0 | Z73: =+COMPARACIÓN!BV20 -> #DIV/0! | AH73: =+COMPARACIÓN!I20 -> 0
A74: 5 | B74: =+COMPARACIÓN!B21 -> 0 | P74: =+COMPARACIÓN!BA21 -> 0 | U74: =+COMPARACIÓN!BD21 -> 0 | Z74: =+COMPARACIÓN!BV21 -> #DIV/0! | AH74: =+COMPARACIÓN!I21 -> 0
A75: 6 | B75: =+COMPARACIÓN!B22 -> 0 | P75: =+COMPARACIÓN!BA22 -> 0 | U75: =+COMPARACIÓN!BD22 -> 0 | Z75: =+COMPARACIÓN!BV22 -> #DIV/0! | AH75: =+COMPARACIÓN!I22 -> 0
A77: VALORIZACIONES
A79: VALOR DEL TERRENO (En S/.) | N79: =+REPOSICIÓN!X25*'HR-COMÚN TERMINADO'!J104 -> 0 | AC79: (*) SEGÚN LA RESOLUCIÓN SBS N° 808-2003 EL VALOR DE REALIZACIÓN SE ENTIENDE COMO EL VALOR NETO QUE LA EMPRESA ESPERA RECUPERAR COMO CONSECUENCIA DE LA EVENTUAL VENTA O EJECUCIÓN DEL BIEN, EN LA SITUACIÓN COMO Y DONDE ESTÉ. POR TANTO, ESTE VALOR DEBE CONSIDERAR LOS CASTIGOS Y CARGOS POR CONCEPTO DE IMPUESTOS EN LAS VENTAS, COMISIONES, FLETES, MERMAS, ETC.
A81: VALOR DEL CASCO HABITABLE (En S/.) | N81: =+REPOSICIÓN!AH47*'HR-COMÚN TERMINADO'!J104 -> 0
A83: VALOR DEL ESTACIONAMIENTO (En S/.) | N83: =+'HR-COMÚN TERMINADO'!V89 -> 0
A85: VALOR DEL DEPÓSITO (En S/.) | N85: =+'HR-COMÚN TERMINADO'!Z89 -> 0
A87: VALOR COMERCIAL DEL INMUEBLE (En S/.) | N87: =+'HR-COMÚN TERMINADO'!M95 -> 0
A89: VALOR DE REALIZACIÓN (*) (En S/.) | N89: =+'HR-COMÚN TERMINADO'!M97 -> 0
A91: COMENTARIOS / OBSERVACIONES
AC96: FIRMA DEL PERITO VALUADOR
A98: 1. En caso los datos de la valorización se hayan obtenido en nuevos soles, se deberá utilizar el tipo
A99: de cambio promedio compra SBS, al cierre del día hábil anterior, a la fecha de realizada la tasación
A100: 2. En caso de Bien Futuro, firmará preliminarmente, el ingeniero supervisor de la EF que financie el
A101: proyecto inmobiliario.
AC104: NOMBRES Y APELLIDOS
AC105: REPEV S.B.S
AC106: C.I.P.

Sheet PORTADA

Sheet HR-BIEN FUTURO
T12: N° de Solicitud BCP | Y12: : | Z12: =+'MEM. DESC. I'!Z12 -> 0
T13: N° de Servicio Tasadora | Y13: : | Z13: =+'MEM. DESC. I'!Z13 -> XXXX-26
T14: Fecha de Expedición | Y14: : | Z14: =+'MEM. DESC. I'!Z14 -> 0
T15: Fecha última de Vigencia | Y15: : | Z15: =+'MEM. DESC. I'!Z15 -> 365
A16: HOJA RESUMEN N° XX-26 - VALUACIÓN
A17: HIPOTECA (INMUEBLE)
G32: PLANO DE UBICACIÓN | S32: FACHADA DEL INMUEBLE
B33: DATOS DEL CLIENTE
B35: CLIENTE | F35: =+'MEM. DESC. I'!J42 -> 0 | U35: CÓD CLIENTE
B37: N° GARANTÍA | M37: Ejm: G193 00110958 | U37: (09 Dígitos)
B39: PROPIETARIO | F39: =+'MEM. DESC. I'!J44 -> 0
B41: FECHA INSPECCIÓN
B43: DATOS DEL INMUEBLE
B45: DIRECCIÓN SEGÚN MINUTA | F45: =+'MEM. DESC. I'!J48 -> 0
B47: DISTRITO | F47: =+'HR-COMÚN TERMINADO'!F47 -> 0 | L47: PROVINCIA | O47: =+'HR-COMÚN TERMINADO'!O47 -> 0 | U47: DEPARTAMENTO | Y47: =+'HR-COMÚN TERMINADO'!Y47 -> 0
B49: GEOREFERENCIA | F49: (-) Latitud | H49: =+'HR-COMÚN TERMINADO'!H49 -> 0 | L49: (-) Longitud | O49: =+'HR-COMÚN TERMINADO'!O49 -> 0 | R49: (*) Datos obtenidos de Google Maps
B51: OCUPANTE | K51: TIPO DE PREDIO
F54: Uso | L54: %
B55: USO DEL INMUEBLE | O55: INMUEBLE CERCADO | V55: DECLARATORIA DE FÁBRICA
B59: ZONIFICACIÓN | L59: DESCRIPCIÓN ZONIFICACIÓN
B61: ÁREA DE TRATAMIENTO CON FINES DE RENOVACIÓN URBANA
B62: Según OPINIÓN del suscrito
B63: ZONA DE TRATAMIENTO ESPECIAL | Q63: BIEN CULTURAL
B64: Según OPINIÓN del suscrito | Q64: Según OPINIÓN del suscrito
B66: AÑO DE CONSTRUCCIÓN | J66: ESTADO DE CONSERVACIÓN
B68: DISEÑADA PARA N° DE PISOS | K68: Nº DE SÓTANOS | R68: Nº DE PISOS
B70: MATERIAL DE CONSTRUCCIÓN | H70: Concreto - Ladrillo | M70: % | N70: 20 | Q70: ESPECIFICAR OTRO | U70: Concreto | Z70: % | AA70: 20
B72: CARGAS | G72: GRAVÁMENES | M72: COMENTARIOS / ADVERTENCIAS SOBRE LA CARGA
B75: OBSERVACIONES GENERALES
B79: RESULTADOS DE VALORIZACIÓN
B81: VALORES DE INMUEBLES A FUTURO EN PROYECTO NO INSCRITOS EN RRPP | J81: MONEDA | M81: VALOR TOTAL | R81: DEPARTAMENTO | V81: ESTACIONAMIENTO | Z81: DEPÓSITO
B82: VALOR COMERCIAL | J82: US$ | M82: =SUM(R82:AC82) -> 0 | R82: 0 | V82: 0 | Z82: 0
J83: S/. | M83: =SUM(R83:AC83) -> 0 | R83: =+R82*$J$93 -> 0 | V83: =+V82*$J$93 -> 0 | Z83: =+Z82*$J$93 -> 0
B84: VALOR DE REALIZACIÓN | J84: US$ | M84: =SUM(R84:AC84) -> 0 | R84: =+R82*(100%-RESULTADOS!$R$54) -> 0 | V84: =+V82*(100%-RESULTADOS!$R$54) -> 0 | Z84: =+Z82*(100%-RESULTADOS!$R$54) -> 0
J85: S/. | M85: =SUM(R85:AC85) -> 0 | R85: =+R84*$J$93 -> 0 | V85: =+V84*$J$930 -> 0 | Z85: =+Z84*$J$93 -> 0
B87: VALOR DE RECONSTRUCCIÓN | J87: MONEDA | M87: VALOR TOTAL | R87: EDIFICACIONES | V87: ÁREAS COMUNES | Z87: INSTALACIONES Y OBRAS COMPLEM.
B88: VALOR DE RECONSTRUCCIÓN (INCL. CONSTRUCCIONES DECLAR. Y NO DECLAR.) | J88: US$ | M88: =SUM(R88:AC88) -> 0 | R88: =+REPOSICIÓN!M61 -> 0 | V88: =+REPOSICIÓN!R75 -> 0 | Z88: =+REPOSICIÓN!R96 -> 0
J89: S/. | M89: =SUM(R89:AC89) -> 0 | R89: =+R88*J93 -> 0 | V89: =+V88*J93 -> 0 | Z89: =+Z88*J93 -> 0
B91: NOTA: LOS VALORES CONSIGNADOS EN LA PRESENTE TASACION, CONSIDERAN LOS VALORES DE MERCADO Y CORRESPONDEN A TODOS LOS BIENES QUE EL BANCO HA INDICADO VALUAR.
B93: TIPO DE CAMBIO APLICADO | I93: : | J93: =+'HR-COMÚN TERMINADO'!$J$104 -> 3.48 | M93: Nuevos Soles / Dólar
B95: CUADRO COMPARATIVO DE ÁREAS
B97: =+R81 -> DEPARTAMENTO | F97: Unidad de Medida | J97: Según Registros Públicos | O97: Según Autoavalúo | S97: Diferencia | V97: Según Inspección Ocular | AA97: Observaciones
B98: ÁREA TERRENO
B99: ÁREA OCUPADA
B100: ÁREA CONSTRUIDA
B101: USO
B102: =+V81 -> ESTACIONAMIENTO | F102: Unidad de Medida | J102: Según Registros Públicos | O102: Según Autoavalúo | S102: Diferencia | V102: Según Inspección Ocular | AA102: Observaciones
B103: ÁREA TERRENO | F103: m2 | O103: 0
B104: ÁREA OCUPADA | F104: m2 | O104: 0
B105: ÁREA CONSTRUIDA | F105: m2 | O105: 0
B106: USO
B107: =+Z81 -> DEPÓSITO | F107: Unidad de Medida | J107: Según Registros Públicos | O107: Según Autoavalúo | S107: Diferencia | V107: Según Inspección Ocular | AA107: Observaciones
B108: ÁREA TERRENO | F108: m2 | O108: 0
B109: ÁREA OCUPADA | F109: m2 | O109: 0
B110: ÁREA CONSTRUIDA | F110: m2 | O110: 0
B111: USO
T116: Control interno | V116: =+'HR-COMÚN TERMINADO'!$V$128:$AD$128 -> / / JT
T117: PERITO:
T118: REPEV:

Sheet HR-COMÚN TERMINADO
T12: N° de Solicitud BCP | Y12: : | Z12: =+'MEM. DESC. I'!Z12 -> 0
T13: N° de Servicio Tasadora | Y13: : | Z13: =+'MEM. DESC. I'!Z13:AD13 -> XXXX-26
T14: Fecha de Expedición | Y14: : | Z14: =+'MEM. DESC. I'!Z14:AD14 -> 0
T15: Fecha última de Vigencia | Y15: : | Z15: =+'MEM. DESC. I'!Z15:AD15 -> 365
A16: HOJA RESUMEN N° XX-26 - VALUACIÓN
A17: HIPOTECA (INMUEBLE)
G32: PLANO DE UBICACIÓN | S32: FACHADA DEL INMUEBLE
B33: DATOS DEL CLIENTE
B35: CLIENTE | F35: =+'MEM. DESC. I'!J42 -> 0 | U35: CÓD CLIENTE
B37: N° GARANTÍA | M37: Ejm: G193 00110958 | U37: (09 Dígitos)
B39: PROPIETARIO | F39: =+'MEM. DESC. I'!J44 -> 0
B41: FECHA INSPECCIÓN
B43: DATOS DEL INMUEBLE
B45: DIRECCIÓN RRPP | F45: =+'MEM. DESC. I'!J48 -> 0
B47: DISTRITO | L47: PROVINCIA | U47: DEPARTAMENTO
B49: GEOREFERENCIA | F49: (-) Latitud | L49: (-) Longitud | R49: (*) Datos obtenidos de Google Maps
B51: OCUPANTE | F51: =+'MEM. DESC. I'!J46 -> 0 | K51: TIPO DE PREDIO | O51: =+'MEM. DESC. I'!J60 -> 0
F54: Uso | L54: %
B55: USO DEL INMUEBLE | F55: =+'MEM. DESC. I'!J92 -> Departamento Flat | L55: =+'MEM. DESC. I'!Q92 -> 100 | O55: INMUEBLE CERCADO | S55: Sí | V55: DECLARATORIA DE FÁBRICA
F56: =+'MEM. DESC. I'!U92 -> 0 | L56: =+'MEM. DESC. I'!AB92 -> 0
F57: =+'MEM. DESC. I'!J93 -> 0 | L57: =+'MEM. DESC. I'!Q93 -> 0
B59: ZONIFICACIÓN | F59: =+'MEM. DESC. I'!Y61 -> 0 | L59: DESCRIPCIÓN ZONIFICACIÓN
B61: ÁREA DE TRATAMIENTO CON FINES DE RENOVACIÓN URBANA | N61: No
B62: Según OPINIÓN del suscrito
B63: ZONA DE TRATAMIENTO ESPECIAL | N63: No | Q63: BIEN CULTURAL | W63: No
B64: Según OPINIÓN del suscrito | Q64: Según OPINIÓN del suscrito
B66: AÑO DE CONSTRUCCIÓN | G66: =2026-'MEM. DESC. I'!Q99 -> 2026 | J66: ESTADO DE CONSERVACIÓN | P66: =+'MEM. DESC. I'!X99 -> 0
B68: DISEÑADA PARA N° DE PISOS | H68: =+U68 -> 0 | K68: Nº DE SÓTANOS | O68: =+'MEM. DESC. I'!Q102 -> 0 | R68: Nº DE PISOS | U68: =+'MEM. DESC. I'!J102 -> 0
B70: MATERIAL DE CONSTRUCCIÓN | H70: =+'MEM. DESC. I'!J99 -> 0 | M70: % | N70: 100 | Q70: ESPECIFICAR OTRO | Z70: %
B72: CARGAS | D72: No | G72: GRAVÁMENES | J72: No | M72: COMENTARIOS / ADVERTENCIAS SOBRE LA CARGA | S72: Ninguna.
B75: OBSERVACIONES GENERALES
B79: RESULTADOS DE VALORIZACIÓN
B81: VALORES INSCRITOS EN RRPP | J81: MONEDA | M81: VALOR TOTAL | R81: DEPARTAMENTO | V81: ESTACIONAMIENTO | Z81: DEPÓSITO
B82: VALOR COMERCIAL | J82: US$ | M82: =SUM(R82:AC82) -> 0 | R82: =+COMPARACIÓN!V90 -> 0 | V82: =+COMPARACIÓN!V91 -> 0 | Z82: =+COMPARACIÓN!V92 -> 0
J83: S/ | M83: =SUM(R83:AC83) -> 0 | R83: =+R82*$J$104 -> 0 | V83: =+V82*$J$104 -> 0 | Z83: =+Z82*$J$104 -> 0
B84: VALOR DE REALIZACION | J84: US$ | M84: =SUM(R84:AC84) -> 0 | R84: =+R82*(100%-RESULTADOS!$R$54) -> 0 | V84: =+V82*(100%-RESULTADOS!$R$54) -> 0 | Z84: =+Z82*(100%-RESULTADOS!$R$54) -> 0
J85: S/ | M85: =SUM(R85:AC85) -> 0 | R85: =+R84*$J$104 -> 0 | V85: =+V84*J104 -> 0 | Z85: =+Z84*$J$104 -> 0
B87: VALORES NO INSCRITOS EN RRPP | J87: MONEDA | M87: VALOR TOTAL | R87: =R81 -> DEPARTAMENTO | V87: =V81 -> ESTACIONAMIENTO | Z87: =Z81 -> DEPÓSITO
B88: VALOR COMERCIAL | J88: US$ | M88: =SUM(R88:AC88) -> 0 | V88: 0 | Z88: 0
J89: S/ | M89: =SUM(R89:AC89) -> 0 | R89: =+R88*$J$104 -> 0 | V89: =+V88*$J$104 -> 0 | Z89: =+Z88*$J$104 -> 0
B90: VALOR DE REALIZACIÓN | J90: US$ | M90: =SUM(R90:AC90) -> 0 | R90: =+R88*(100%-RESULTADOS!$R$54) -> 0 | V90: =+V88*(100%-RESULTADOS!$R$54) -> 0 | Z90: =+Z88*(100%-RESULTADOS!$R$54) -> 0
J91: S/ | M91: =SUM(R91:AC91) -> 0 | R91: =+R90*$J$104 -> 0 | V91: =+V90*$J$104 -> 0 | Z91: =+Z90*$J$104 -> 0
B93: VALOR TOTAL DEL PREDIO | J93: MONEDA | M93: VALOR TOTAL | R93: INSCRITO EN RRPP | V93: NO INSCRITO EN RRPP
B94: VALOR TOTAL COMERCIAL (INCL. CONSTRUCCIÓN DECLAR. Y NO DECLAR.) | J94: US$ | M94: =SUM(R94:AC94) -> 0 | R94: =M82 -> 0 | V94: =M88 -> 0
J95: S/ | M95: =SUM(R95:AC95) -> 0 | R95: =+M83 -> 0 | V95: =+M89 -> 0
B96: VALOR DE REALIZACIÓN | J96: US$ | M96: =SUM(R96:AC96) -> 0 | R96: =+M84 -> 0 | V96: =+M90 -> 0
J97: S/ | M97: =SUM(R97:AC97) -> 0 | R97: =+M85 -> 0 | V97: =+M91 -> 0
B99: VALOR DE RECONSTRUCCIÓN | J99: MONEDA | M99: VALOR TOTAL | R99: EDIFICACIONES | V99: ÁREAS COMUNES | Z99: INSTALACIONES Y OBRAS COMPLEM.
B100: VALOR DE RECONSTRUCCIÓN (INCL. CONSTRUCCIONES DECLAR. Y NO DECLAR.) | J100: US$ | M100: =SUM(R100:AC100) -> 0 | R100: =+REPOSICIÓN!M61 -> 0 | V100: =+REPOSICIÓN!R75 -> 0 | Z100: =+REPOSICIÓN!R96 -> 0
J101: S/ | M101: =SUM(R101:AC101) -> 0 | R101: =+R100*$J$104 -> 0 | V101: =+V100*$J$104 -> 0 | Z101: =+Z100*$J$104 -> 0
B102: NOTA: LOS VALORES CONSIGNADOS EN LA PRESENTE TASACION, CONSIDERAN LOS VALORES DE MERCADO Y CORRESPONDEN A TODOS LOS BIENES QUE EL BANCO HA INDICADO VALUAR.
B104: TIPO DE CAMBIO APLICADO | I104: : | J104: 3.48 | M104: Soles / Dólar
B106: CUADRO COMPARATIVO DE ÁREAS
B108: =+R81 -> DEPARTAMENTO | F108: Unidad de Medida | J108: Según Registros Públicos | O108: Según Autoavalúo | S108: Diferencia | V108: Según Inspección Ocular | AA108: Observaciones
B109: ÁREA TERRENO | F109: m2 | O109: 0
B110: ÁREA OCUPADA | F110: m2 | O110: 0
B111: ÁREA CONSTRUIDA | F111: m2 | O111: 0
B112: USO
B113: =+V81 -> ESTACIONAMIENTO | F113: Unidad de Medida | J113: Según Registros Públicos | O113: Según Autoavalúo | S113: Diferencia | V113: Según Inspección Ocular | AA113: Observaciones
B114: ÁREA TERRENO | F114: m2 | O114: 0
B115: ÁREA OCUPADA | F115: m2 | O115: 0
B116: ÁREA CONSTRUIDA | F116: m2 | O116: 0
B117: USO
B118: =+Z81 -> DEPÓSITO | F118: Unidad de Medida | J118: Según Registros Públicos | O118: Según Autoavalúo | S118: Diferencia | V118: Según Inspección Ocular | AA118: Observaciones
B119: ÁREA TERRENO | F119: m2 | O119: 0
B120: ÁREA OCUPADA | F120: m2 | O120: 0
B121: ÁREA CONSTRUIDA | F121: m2 | O121: 0
B122: USO
T128: Control interno | V128: / / JT
T129: PERITO: | V129: VANET S.A.C.
T130: REPEV: | V130: 561-2001

Sheet MEM. DESC. I
T12: N° de Solicitud BCP | Y12: :
T13: N° de Servicio Tasadora | Y13: : | Z13: XXXX-26
T14: Fecha de Expedición | Y14: :
T15: Fecha última de Vigencia | Y15: : | Z15: =Z14+365 -> 365
A16: MEMORIA DESCRIPTIVA
A17: NORMATIVIDAD
B19: OBJETO DE LA TASACIÓN | I19: : | J19: Determinar el Valor Comercial del inmueble para fines de Garantía Hipotecaria
B21: ALCANCES Y LIMITACIÓN | I21: : | J21: Durante la visita se dieron las facilidades para la inspección ocular y toma de registro fotográfico al interior del Inmueble:
B22: (Marcar con (X) la opción que corresponda)
J23: Sí | M23: No
B25: REGLAMENTACIÓN | I25: : | J25: Reglamento Nacional de Tasaciones del Perú - R.M. Nº 172 - 2016 - VIVIENDA y su modificatoria la R.M. N° 424 - 2017-VIVIENDA. Además se emplea la Resolución S.B.S N° 11356 - 2008 para la determinación del Valor de Realización en el Mercado.
B27: METODOLOGÍA | I27: : | J27: Se utilizan los Métodos Directos (Comparación y/o Costos) así como los Indirectas cuando correspondan, establecidos en el Artículo 3, Inciso 3.1.5 del Título I del Reglamento Nacional de Tasaciones del Perú.
B29: FUENTE Y PROCEDENCIA DE LA | I29: : | K29: Partida Registral | P29: Predio Urbano/Rural | U29: Planos | AA29: CRI
B30: INFORMACIÓN | K30: Parámetros Urb. | P30: Tasación Anterior | U30: Cuadro de acabados | AA30: Memoria Des.
B31: (Marcar con (X) la opción que corresponda)
K32: Otros | P32: Especificar
B34: SITUACIÓN REGISTRAL DEL PREDIO | G34: Principal | I34: : | J34: Partida Electrónica | R34: Nº: | X34: Fecha Documento:
G35: Secund. I | I35: : | R35: Nº: | X35: Fecha Documento:
G36: Secund. II | I36: : | R36: Nº: | X36: Fecha Documento:
G37: Secund. III | I37: : | R37: Nº: | X37: Fecha Documento:
G38: Otras Und. | I38: :
A40: DATOS GENERALES
B42: CLIENTE | I42: :
B44: PROPIETARIO (S) | I44: :
B46: OCUPANTE | I46: :
B48: UBICACIÓN | I48: :
B49: SEGÚN PARTIDA ELECTRÓNICA
B51: UBICACIÓN | I51: : | J51: No se contó con la documentación correspondiente.
B52: SEGÚN PREDIO URBANO
B54: UBICACIÓN | I54: :
B55: SEGÚN INSPECCIÓN OCULAR
A57: CARACTERÍSTICAS URBANAS
B59: CARACTERÍSTICAS DEL ENTORNO
B60: Tipo de Zona | I60: : | Q60: Demanda / Interés | X60: :
B61: Uso Predominante | I61: : | Q61: Zonificación | X61: :
B62: Desarrollo | I62: : | Q62: Altura de Edificación | X62: :
B63: Nivel Socioeconómico | I63: : | Q63: Velocidad de Cambio | X63: :
B64: Tendencia del Desarrollo Urbano | I64: : | Q64: Estado de Conservación | X64: :
B66: EQUIPAMIENTO DEL ENTORNO | J66: Nivel de Equipamiento | Y66: Nivel de Equipamiento
B67: Comercial | I67: : | Q67: Estacionamiento | X67: :
B68: Escolar | I68: : | Q68: Áreas Verdes | X68: :
B69: Asistencial | I69: : | Q69: Zonas Recreativas | X69: :
B71: INFRAESTRUCTURA DE SERVICIO | J71: Tiene | Q71: Calidad | Y71: Estado de Conservación
B72: Vías Asfaltadas | I72: : | J72: Completas | Q72: Medio | Y72: Bueno
B73: Veredas | I73: : | J73: Completas | Q73: Medio | Y73: Bueno
B74: Alcantarillado | I74: : | J74: Completas | Q74: Medio | Y74: Bueno
B75: Agua Potable | I75: : | J75: Completas | Q75: Medio | Y75: Bueno
B76: Alumbrado | I76: : | J76: Completas | Q76: Medio | Y76: Bueno
B78: VIAS PRINCIPALES DE ACCESO | I78: :
B80: CERCANIA A RIOS /MAR / LAGOS /
B81: ACANTILADOS / QUEBRADAS | I81: : | J81: Sí | M81: No | Q81: DISTANCIA | S81: :
A83: CARACTERÍSTICAS DEL INMUEBLE
B85: REGIMEN DE LA PROPIEDAD | I85: : | J85: Exclusivo y Común
B87: TIPO DE INMUEBLE | I87: : | J87: Vivienda
B89: SERVIDUMBRES | I89: : | L89: Detalle:
J91: Uso | Q91: % | U91: Uso | AB91: %
B92: USO DE LA PROPIEDAD | I92: : | J92: Departamento Flat | Q92: 100
B95: TERRENO | I95: : | J95: Forma | Q95: Topografía | X95: Ubicación
B96: (Marcar con (X) la opción que corresponda) | J96: Regular | M96: Irregular | Q96: Plana | T96: Pendiente
B98: EDIFICACIONES | I98: : | J98: Material de la Estructura | Q98: Edad Efectiva (años) | X98: Estado de Conservación
B101: DESCRIPCIÓN GENERAL | I101: : | J101: N° de Pisos | Q101: N° de Sótanos y/o Semisótanos | X101: N° de Unidades del Conjunto
Q102: 0
J103: Piso(s) que ocupa el Inmueble | Q103: Ascensor | X103: Áreas Comunes
J105: Vista del Inmueble | Q105: Mantenimiento | X105: Servicios
B108: DESCRIPCIÓN Y DISTRIBUCIÓN DEL INMUEBLE | I108: : | J108: Descripción Distribución: Primer piso: Segundo piso: Tercer piso:

Sheet MEM. DESC. II
T12: N° de Solicitud BCP | Y12: : | Z12: =+'MEM. DESC. I'!Z12:AD12 -> 0
T13: N° de Servicio Tasadora | Y13: : | Z13: =+'MEM. DESC. I'!Z13:AD13 -> XXXX-26
T14: Fecha de Expedición | Y14: : | Z14: =+'MEM. DESC. I'!Z14:AD14 -> 0
T15: Fecha última de Vigencia | Y15: : | Z15: =+'MEM. DESC. I'!Z15:AD15 -> 365
A16: LINDEROS
B17: Orientación | E17: Descripción | Z17: Longitud (ml)
B18: =+B39 -> Departamento N°
B19: Por el Frente:
B20: Por la Derecha:
B21: Por la Izquierda:
B22: Por el Fondo:
W23: Perímetro: | Z23: =SUM(Z19:AC22) -> 0
B24: =+B40 -> Estacionamiento N°
B25: Por el Frente:
B26: Por la Derecha:
B27: Por la Izquierda:
B28: Por el Fondo:
W29: Perímetro: | Z29: =SUM(Z25:AC28) -> 0
B30: =+B41 -> Depósito N°
B31: Por el Frente:
B32: Por la Derecha:
B33: Por la Izquierda:
B34: Por el Fondo:
W35: Perímetro: | Z35: =SUM(Z31:AC34) -> 0
A37: TERRENO
B38: Unidad Inmobiliaria | H38: Unidad Métrica | K38: Área Matriz (Prop. Horiz. o Vert.) | O38: % Participación | S38: Área Privativa | V38: Obtención del Área | Z38: Observación
A39: 1 | B39: Departamento N° | H39: m2
A40: 2 | B40: Estacionamiento N° | H40: m2
A41: 3 | B41: Depósito N° | H41: m2
A42: 4
A43: 5
B44: Total Área de Terreno | S44: =SUM(S39:U43) -> 0
A46: Nota:
A48: CONSTRUCCIONES
B49: Inmueble / Unidad Principal
B50: Descripción | H50: Unidad Métrica | K50: Área Techada | O50: Área sin Techar | S50: Obtención del Área | Z50: Edificación Declarada
A51: 1 | B51: Primer piso | H51: m2
A52: 2 | B52: Segundo piso | H52: m2
A53: 3 | B53: Tercer piso (Azotea) | H53: m2
A54: 4 | H54: m2
A55: 5 | H55: m2
B56: Total Áreas Construidas | K56: =SUM(K51:N55) -> 0 | O56: =SUM(O51:R55) -> 0
B58: Inmueble / Unidad Secundaria | H58: Ejem: Estacionamientos, Depósitos, etc
B59: Descripción | H59: Unidad Métrica | K59: Área Techada | O59: Área sin Techar | S59: Obtención del Área | Z59: Edificación Declarada
A60: 1 | B60: =+B40 -> Estacionamiento N° | H60: m2
A61: 2 | B61: =+B41 -> Depósito N° | H61: m2
A62: 3 | H62: m2
A63: 4 | H63: m2
A64: 5 | H64: m2
B65: Total Áreas Construidas | K65: =SUM(K60:N64) -> 0 | O65: =SUM(O60:R64) -> 0
A67: INSTALACIONES Y OBRAS COMPLEMENTARIAS
B68: Descripción | H68: Unidad Métrica | K68: Cantidad | O68: Material Predominante | S68: Antigüedad | V68: Obtención del Área | Z68: Edificación Declarada
A69: 1 | H69: m3
A70: 2 | H70: m2
A71: 3 | H71: Und
A72: 4 | H72: m2
A74: CARACTERÍSTICAS PRINCIPALES DE LA CONSTRUCCIÓN
C76: Tipo de construcción : | I76: Definitiva | R76: Origen de la construcción* : | X76: Const. Profesional
C77: (Marcar con (X) la opción que corresponda) | I77: Provisional | R77: (Marcar con (X) la opción que corresponda) | X77: Autoconstrucción
R78: * Opinión del Suscrito
B80: ESTRUCTURA GENERAL | H80: : | I80: Cimentación
I81: Estructura
I82: Muros
I83: Techos
I84: Cobertura
I85: Inst. Eléctricas
I86: Inst. Gas
I87: Inst. Sanitarias
A89: ACABADOS | B89: ACABADOS
B90: Puertas | H90: : | I90: Tipo
I91: Material
I92: Sistema
B94: Ventanas | H94: : | I94: Marco
I95: Vidrio
I96: Sistema
B98: Mamparas | H98: : | I98: Marco
I99: Vidrio
I100: Sistema
B102: Muebles de cocina | H102: : | I102: Tipo
I103: Material
I104: Tableros
I105: Lavaderos
B107: Baños | H107: : | I107: Tipo
I108: Color
I109: Grifería
B111: Closets | H111: : | I111: Tipo
B113: Pisos | H113: :
B115: Revestimientos | H115: :
B117: Cerrajería | H117: :
B119: Obras Complementarias e Instalaciones Fijas | H119: : | I119: Aire Acondicionado | P119: Parrilla | W119: Cerco
I120: Alarma | P120: Sistema Hidroneumático | W120: Cisterna
C121: (Marcar con (X) la opción que corresponda) | I121: Ascensor | P121: Sistema Contra Incendio | W121: Iluminación Especial
I122: Intercomunicador | P122: Tanque Elevado | W122: Piscina
B124: Otros y Comentarios | H124: : | I124: Ninguna.

Sheet EST. MERCADO TERRENOS
T12: N° de Solicitud BCP | Y12: : | Z12: =+'MEM. DESC. II'!Z12:AD12 -> 0
T13: N° de Servicio Tasadora | Y13: : | Z13: =+'MEM. DESC. II'!Z13:AD13 -> XXXX-26
T14: Fecha de Expedición | Y14: : | Z14: =+'MEM. DESC. II'!Z14:AD14 -> 0
T15: Fecha última de Vigencia | Y15: : | Z15: =+'MEM. DESC. II'!Z15:AD15 -> 365
A16: ANALISIS METODOLOGICO
A17: MÉTODO DE COSTOS O REPOSICIÓN (OFERTA DE TERRENOS EN EL MERCADO) | AF17: VALOR DEL TERRENO
B19: DATOS GENERALES DE LOS COMPARABLES | K19: (Evidenciar como mínimo tres (03) muestras) | AF19: CUADRO COMPARATIVO
B20: Descripción | F20: Ubicación | I20: Fuente (In situ, correo, página web, periódicos, etc) | N20: Teléfono | P20: Nombre de Contacto | S20: Forma / Topografía | V20: Zonificación | Y20: Distancia al Inmueble (m) | AB20: Fecha | AF20: UBICACIÓN | AU20: Zonificación | AX20: Antigüedad | BA20: Área de terreno m2 | BD20: Área construida m2 | BG20: V. Tot. Inm. US$ | BL20: V. Const. US$ | BQ20: Valor de Terr.US$ | BV20: V. U. US$/m2
B21: "OFERTA EN EL MERCADO" | AF21: =+B21 -> "OFERTA EN EL MERCADO"
A22: 1 | B22: Área Construida: 156.00/m2 Valor de venta total = US$ 640,000.00 Para determinar el valor de terreno se ha descontado el valor de la construcción = US$ 60,000.00 | S22: Regular / Plana | BQ22: =+BG22-BL22 -> 0 | BV22: =+BQ22/BA22 -> #DIV/0!
A23: 2 | B23: =+AF23 -> 0 | S23: Regular / Plana | BQ23: =+BG23-BL23 -> 0 | BV23: =+BQ23/BA23 -> #DIV/0!
A24: 3 | B24: =+AF24 -> 0 | S24: Regular / Plana | BQ24: =+BG24-BL24 -> 0 | BV24: =+BQ24/BA24 -> #DIV/0!
A25: 4 | B25: =+AF25 -> 0 | S25: Regular / Plana | BQ25: =+BG25-BL25 -> 0 | BV25: =+BQ25/BA25 -> #DIV/0!
B26: "INMUEBLES VENDIDOS - VENTAS CERRADAS" Tomado del aplicativo Vanetmap
A27: 5 | S27: Regular / Plana | BQ27: =+BG27-BL27 -> 0 | BV27: =+BQ27/BA27 -> #DIV/0!
B29: HOMOLOGACIÓN DE LOS COMPARABLES | AF29: Del estudio realizado, observamos que el valor unitario de los terrenos están entre US$605.00/m2. a US$ 950.00/m2, dependiendo de la ubicación de los inmuebles. Como se observa en el setudio de mercado la referencia N°1, tiene expectativas econimicas muy altas. Las referencias N° 2, 3 y 4, presentan similitud urbanistica con el inmueble tasado, por lo que se ha procedido a promediar estas referencias, lo que nos da un valor promedio de US$761.00/m2 a este resultado le multiplicamos por un factor de 0.95, por negociacion, lo que nos da un valor unitario de terreno redondeado de :
B30: Valor del Inmueble Referencial (US$) | H30: Área (m2) | L30: Valor Unitario Terreno (US$/m2) | P30: Factores de HOMOLOGACIÓN | V30: Factor Resultante | X30: Valor Unit. Terreno Homologado (US$/m2)
P31: Ub. | Q31: Top. | R31: Sup | S31: Ser. | T31: Zon | U31: F.N.
B32: "OFERTA EN EL MERCADO"
A33: 1 | B33: =+BQ22 -> 0 | H33: =+BA22 -> 0 | L33: =IFERROR(B33/H33,0) -> 0 | P33: 1 | Q33: 1 | R33: 1 | S33: 1 | T33: 1 | U33: 1.05 | V33: =PRODUCT(P33:U33) -> 1.05 | X33: =IFERROR(ROUND(L33^2*V33/L33,2)," ")
A34: 2 | B34: =+BQ23 -> 0 | H34: =+BA23 -> 0 | L34: =IFERROR(B34/H34,0) -> 0 | P34: 1 | Q34: 1 | R34: 1 | S34: 1 | T34: 1 | U34: 1.05 | V34: =PRODUCT(P34:U34) -> 1.05 | X34: =IFERROR(ROUND(L34^2*V34/L34,2)," ") | BF34: / m2
A35: 3 | B35: =+BQ24 -> 0 | H35: =+BA24 -> 0 | L35: =IFERROR(B35/H35,0) -> 0 | P35: 1 | Q35: 1 | R35: 1 | S35: 1 | T35: 1 | U35: 1 | V35: =PRODUCT(P35:U35) -> 1 | X35: =IFERROR(ROUND(L35^2*V35/L35,2)," ")
A36: 4 | B36: =+BQ25 -> 0 | H36: =+BA25 -> 0 | L36: =IFERROR(B36/H36,0) -> 0 | P36: 1 | Q36: 1 | R36: 1 | S36: 1 | T36: 1 | U36: 1 | V36: =PRODUCT(P36:U36) -> 1 | X36: =IFERROR(ROUND(L36^2*V36/L36,2)," ")
B37: "INMUEBLES VENDIDOS - VENTAS CERRADAS" Tomado del aplicativo Vanetmap
A38: 5 | B38: =+BQ27 -> 0 | H38: =+BA27 -> 0 | L38: =IFERROR(B38/H38,0) -> 0 | P38: 1 | Q38: 1 | R38: 1 | S38: 1 | T38: 1 | U38: 1 | V38: =PRODUCT(P38:U38) -> 1 | X38: =IFERROR(ROUND(L38^2*V38/L38,2)," ")
B39: Valor Unitario Terreno Homologado Promedio [$/m²]: | J39: =IFERROR(AVERAGEIF(X33:AC38,">0"),0) -> 0 | O39: VUT Promedio Homologado ajustado por redondeo [$/m²]: | X39: =ROUND(J39,-1) -> 0
B41: *Notas: | E41: 1. - Los Valores Unitarios de Mercado han sido afectados por un Factor de Negociación reconociendo que se tratan de comparables de carácter ofertable aún sin realizar.
E42: 2. - Los comparables identificados han sido ponderados reconociendo la variación en cuanto a criterios de Ubicación, Topografía, Superficie, Servicios y Zonificación
A44: PLANO DE UBICACIÓN Y REFERENCIAS DE TERRENO
B74: RESUMEN VALORES UNITARIOS
B76: COMPARABLES | C76: Referencias | G76: Ofertado | J76: Homologado
C77: =A33 -> 1 | G77: =IF(L33=0," ",L33) | J77: =X33
C78: =A34 -> 2 | G78: =IF(L34=0," ",L34) | J78: =X34
C79: =A35 -> 3 | G79: =IF(L35=0," ",L35) | J79: =X35
C80: =A36 -> 4 | G80: =IF(L36=0," ",L36) | J80: =X36
C81: =A38 -> 5 | G81: =IF(L38=0," ",L38) | J81: =X38
C82: Promedio: | G82: =IFERROR(AVERAGE(G77:G81),"") | J82: =IFERROR(AVERAGE(J77:J81),"")
C83: Máximo | G83: =MAX(G77:G81) -> 0 | J83: =MAX(J77:J81) -> 0
C84: Mínimo | G84: =MIN(G77:G81) -> 0 | J84: =MIN(J77:J81) -> 0
C85: Difer. Max Min | G85: =G83-G84 -> 0 | J85: =J83-J84 -> 0

Sheet REPOSICIÓN
T12: N° de Solicitud BCP | Y12: : | Z12: =+'EST. MERCADO TERRENOS'!Z12:AD12 -> 0
T13: N° de Servicio Tasadora | Y13: : | Z13: =+'EST. MERCADO TERRENOS'!Z13:AD13 -> XXXX-26
T14: Fecha de Expedición | Y14: : | Z14: =+'EST. MERCADO TERRENOS'!Z14:AD14 -> 0
T15: Fecha última de Vigencia | Y15: : | Z15: =+'EST. MERCADO TERRENOS'!Z15:AD15 -> 365
A16: VALOR DE TERRENO (VT)
B18: De acuerdo a la Investigación de Mercado de Terrenos con características similares al inmueble tasado se tiene:
B19: Unidad Inmobiliaria | H19: Área de terreno (m2) | M19: % de Participación | Q19: Valor Unitario de Terreno (US$/m2) | U19: Factor de Ajuste* | X19: Valor de Terreno (US$)
A20: 1 | B20: =+'MEM. DESC. II'!B39:G39 -> Departamento N° | H20: =+'MEM. DESC. II'!S39 -> 0 | M20: =IF(B20=0,"",+'MEM. DESC. II'!O39) -> 0 | Q20: =IF(B20=0,"",+'EST. MERCADO TERRENOS'!$X$39) -> 0 | U20: 1 | X20: =+H20*Q20*U20 -> 0
A21: 2 | B21: =+'MEM. DESC. II'!B40:G40 -> Estacionamiento N° | H21: =+'MEM. DESC. II'!S40 -> 0 | M21: =IF(B21=0,"",+'MEM. DESC. II'!O40) -> 0 | Q21: =IF(B21=0,"",+'EST. MERCADO TERRENOS'!$X$39) -> 0 | U21: 1 | X21: =+H21*Q21*U21 -> 0
A22: 3 | B22: =+'MEM. DESC. II'!B41:G41 -> Depósito N° | H22: =+'MEM. DESC. II'!S41 -> 0 | M22: =IF(B22=0,"",+'MEM. DESC. II'!O41) -> 0 | Q22: =IF(B22=0,"",+'EST. MERCADO TERRENOS'!$X$39) -> 0 | U22: 1 | X22: =+H22*Q22*U22 -> 0
A23: 4 | B23: =+'MEM. DESC. II'!B42:G42 -> 0 | H23: =+'MEM. DESC. II'!S42 -> 0 | M23: =IF(B23=0,"",+'MEM. DESC. II'!O42) | Q23: =+Q22 -> 0 | U23: 1 | X23: =+H23*Q23*U23 -> 0
A24: 5 | B24: =+'MEM. DESC. II'!B43:G43 -> 0 | H24: =+'MEM. DESC. II'!S43 -> 0 | M24: =IF(B24=0,"",+'MEM. DESC. II'!O43) | Q24: =+Q23 -> 0 | U24: 1 | X24: =+H24*Q24*U24 -> 0
B25: Subtotal Terreno (VT) | H25: =SUM(H20:L24) -> 0 | X25: =SUM(X20:AC24) -> 0
B27: *Motivo del Factor | F27: :
A29: VALOR DE LAS EDIFICACIONES [VALOR SIMILAR A NUEVO (VSNE) Y VALOR DE EDIFICACIÓN (VE)]
W31: Región de la Edificación:
B32: De acuerdo a las características constructivas y a los acabados del inmueble observados en la inspección realizada se estima el costo de construcción para: | W32: Lima Metropolitana y Callao
B34: Código | E34: Partida | L34: VUE1 Depa. | O34: VUE2 Estac. | R34: VUE3 Depó. | U34: VUE4 | X34: VUE5 | AA34: VUE6
L35: Clas. | M35: Costo/m2 | O35: Clas. | P35: Costo/m2 | R35: Clas. | S35: Costo/m2 | U35: Clas. | V35: Costo/m2 | X35: Clas. | Y35: Costo/m2 | AA35: Clas. | AB35: Costo/m2
B36: 1 | E36: Muros y Columnas
B37: 2 | E37: Techos
B38: 3 | E38: Pisos
B39: 4 | E39: Puertas y Ventanas
B40: 5 | E40: Revestimientos
B41: 6 | E41: Baños
B42: 7 | E42: Instalaciones Eléctricas y Sanitarias
B43: Costo Unitario de Edificación (US$): | L43: =SUM(M36:N42) -> 0 | O43: =SUM(P36:Q42) -> 0 | R43: =SUM(S36:T42) -> 0 | U43: =SUM(V36:W42) -> 0 | X43: =SUM(Y36:Z42) -> 0 | AA43: =SUM(AB36:AC42) -> 0 | AH43: =SUM(AH36:AK42) -> 0
B44: Gastos Generales: | F44: 0 | G44: (Obra Mediana) | U44: =IF(U43=0,"",ROUND($F$44*U43,2)) | X44: =IF(X43=0,"",ROUND($F$44*X43,2)) | AA44: =IF(AA43=0,"",ROUND($F$44*AA43,2))
B45: Utilidad: | F45: 0 | G45: Tipo de Cambio: | J45: =+'HR-COMÚN TERMINADO'!J104 -> 3.48 | U45: =IF(U43=0,"",ROUND($F$45*U43,2)) | X45: =IF(X43=0,"",ROUND($F$45*X43,2)) | AA45: =IF(AA43=0,"",ROUND($F$45*AA43,2))
B46: Valor Unitario de Edificación (S/.): | L46: =+L43*$J$45 -> 0 | O46: =+O43*$J$45 -> 0 | R46: =+R43*$J$45 -> 0 | U46: =+U43*$J$45 -> 0 | X46: =+X43*$J$45 -> 0 | AA46: =+AA43*$J$45 -> 0
B47: Valor Unitario de Edificación redondeado (US$): | L47: =L46/$J$45 -> 0 | O47: =O46/$J$45 -> 0 | R47: =R46/$J$45 -> 0 | U47: =U46/$J$45 -> 0 | X47: =X46/$J$45 -> 0 | AA47: =AA46/$J$45 -> 0 | AH47: =+H52*AH43*Y52 -> 0 | AO47: CALCULO CASCO HABITABLE
B48: Los valores mostrados ya incluyen GG y Utilidad
B50: Cálculo del Valor Similar a Nuevo o Valor de Reconstrucción de las Edificaciones (VSNE) y el Valor de las Edificaciones (VE)
B51: Descripción | H51: Área (m2) | J51: VUE (US$/m2) | M51: Valor Similar a Nuevo (US$) | P51: Material Predominante | T51: Edad (años) | V51: Estado de Conservación | Y51: FD (*) | Z51: Valor de Edificación (US$)
A52: 1 | B52: =+'MEM. DESC. II'!B51:G51 -> Primer piso | H52: =+'MEM. DESC. II'!K51 -> 0 | J52: =+L47 -> 0 | M52: =+H52*J52 -> 0 | P52: =+'MEM. DESC. I'!J99 -> 0 | T52: =+'MEM. DESC. I'!Q99 -> 0 | V52: =+'MEM. DESC. I'!X99 -> 0 | Y52: 0.95 | Z52: =+M52*Y52 -> 0
A53: 2 | B53: =+'MEM. DESC. II'!B60 -> Estacionamiento N° | H53: =+'MEM. DESC. II'!K60 -> 0 | J53: =+O47 -> 0 | M53: =+H53*J53 -> 0 | P53: =+P52 -> 0 | T53: =+T52 -> 0 | V53: =+V52 -> 0 | Y53: =+Y52 -> 0.95 | Z53: =+M53*Y53 -> 0
A54: 3 | B54: =+'MEM. DESC. II'!B61 -> Depósito N° | H54: =+'MEM. DESC. II'!K61 -> 0 | J54: =+R47 -> 0 | M54: =+H54*J54 -> 0 | P54: =+P53 -> 0 | T54: =+T53 -> 0 | V54: =+V53 -> 0 | Y54: =+Y53 -> 0.95 | Z54: =+M54*Y54 -> 0
A55: 4 | M55: =+H55*J55 -> 0 | P55: =+P54 -> 0 | Y55: =+Y54 -> 0.95 | Z55: =+M55*Y55 -> 0
A56: 5 | M56: =+H56*J56 -> 0 | Z56: =+M56*Y56 -> 0
A57: 6 | M57: =+H57*J57 -> 0 | Z57: =+M57*Y57 -> 0
A58: 7 | B58: 0 | H58: 0 | M58: =+H58*J58 -> 0 | Z58: =+M58*Y58 -> 0
A59: 8 | B59: 0 | H59: 0 | M59: =+H59*J59 -> 0 | Z59: =+M59*Y59 -> 0
A60: 9 | B60: 0 | H60: 0 | M60: =+H60*J60 -> 0 | Z60: =+M60*Y60 -> 0
B61: Subtotal Edificaciones (VSNE) | H61: =SUM(H52:H60) -> 0 | L61: US$ | M61: =SUM(M52:O60) -> 0 | Q61: Subtotal Edificaciones (VE) | X61: US$ | Y61: =SUM(Z52:Z60) -> 0
A63: VALOR DE EDIFICACIÓN DE LAS AREAS COMUNES (VAC)
B65: Según el Reglamento General de Tasaciones del Perú, para el valor de las Áreas Comunes en los regímenes que corresponda, se asigna un % del valor de la edificación:
B67: Descripción | H67: % de Áreas Comunes | M67: Valor Unitario de Áreas Comunes (US$/m2) | R67: Valor de Reconstrucción Áreas Comunes (US$) | W67: FD (*) | Y67: Valor de Áreas Comunes (US$)
B69: =+B20 -> Departamento N°
B70: Áreas Comunes | H70: 0.15 | M70: =+R70/'MEM. DESC. II'!K51 -> #DIV/0! | R70: =ROUND(PorcentajeÁreasComunes*M52,2) -> 0 | W70: =+Y52 -> 0.95 | Y70: =+R70*W70 -> 0
B71: =+B21 -> Estacionamiento N°
B72: Áreas Comunes | H72: 0.15 | M72: =+R72/'MEM. DESC. II'!K60 -> #DIV/0! | R72: =ROUND(PorcentajeÁreasComunes*M53,2) -> 0 | W72: =+Y54 -> 0.95 | Y72: =+R72*W72 -> 0
B73: =+B22 -> Depósito N°
B74: Áreas Comunes | H74: 0.15 | M74: =+R74/'MEM. DESC. II'!K61 -> #DIV/0! | R74: =ROUND(PorcentajeÁreasComunes*M54,2) -> 0 | W74: =+W72 -> 0.95 | Y74: =+R74*W74 -> 0
B75: Subtotal Áreas Comunes (VAC) | Q75: US$ | R75: =+R70+R72+R74 -> 0 | X75: US$ | Y75: =+Y70+Y72+Y74 -> 0
A77: VALOR DE LAS INSTALACIONES FIJAS Y OBRAS COMPLEMENTARIAS (VI + VOC)
B79: Descripción | G79: Cantidad | J79: Unidad (Und.) | L79: Valor Unitario (US$/Und.) | O79: Valor de Reconstrucción (US$) | R79: Edad (años) | T79: Estado de Conservación | W79: FD (*) | Y79: Valor de Inst. y Obras Complem. (US$)
A81: 1 | B81: =+'MEM. DESC. II'!B69 -> 0 | G81: =+'MEM. DESC. II'!K69 -> 0 | J81: =+'MEM. DESC. II'!H69 -> m3 | O81: =+G81*L81 -> 0 | R81: =+T52 -> 0 | T81: =+V52 -> 0 | W81: =+Y52 -> 0.95 | Y81: =+O81*W81 -> 0
A82: 2 | B82: =+'MEM. DESC. II'!B70 -> 0 | G82: =+'MEM. DESC. II'!K70 -> 0 | J82: =+'MEM. DESC. II'!H70 -> m2 | O82: =+G82*L82 -> 0 | R82: =+R81 -> 0 | T82: =+T81 -> 0 | W82: =+W81 -> 0.95 | Y82: =+O82*W82 -> 0
A83: 3 | B83: =+'MEM. DESC. II'!B71 -> 0 | G83: =+'MEM. DESC. II'!K71 -> 0 | J83: =+'MEM. DESC. II'!H71 -> Und | O83: =+G83*L83 -> 0 | R83: =+R82 -> 0 | T83: =+T82 -> 0 | W83: =+W82 -> 0.95 | Y83: =+O83*W83 -> 0
A84: 4 | B84: =+'MEM. DESC. II'!B72 -> 0 | G84: =+'MEM. DESC. II'!K72 -> 0 | J84: =+'MEM. DESC. II'!H72 -> m2 | O84: =+G84*L84 -> 0 | R84: =+R83 -> 0 | T84: =+T83 -> 0 | W84: =+W83 -> 0.95 | Y84: =+O84*W84 -> 0
B85: Subtotal Instalaciones y Obras Complementarias (VI + VOC) | N85: US$ | O85: =SUM(O81:Q84) -> 0 | X85: US$ | Y85: =SUM(Y81:AC84) -> 0
B86: =+B52 -> Primer piso
B87: Porcentaje de Áreas Comunes al inmueble % | Y87: =+M20 -> 0
B88: Total de Obras Complementarias (VI + VOC) | J88: =+B86 -> Primer piso | R88: =+$O$85*Y87 -> 0 | W88: US$ | Y88: =+$Y$85*Y87 -> 0
B89: =+B21 -> Estacionamiento N°
B90: Porcentaje de Áreas Comunes al estacionamiento % | Y90: =+M21 -> 0
B91: Total de Obras Complementarias (VI + VOC) | J91: =+B89 -> Estacionamiento N° | R91: =+$O$85*Y90 -> 0 | W91: US$ | Y91: =+$Y$85*Y90 -> 0
B92: =+B22 -> Depósito N°
B93: Porcentaje de Áreas Comunes al depósito % | Y93: =+M22 -> 0
B94: Total de Obras Complementarias (VI + VOC) | J94: =+B92 -> Depósito N° | R94: =+$O$85*Y93 -> 0 | W94: US$ | Y94: =+$Y$85*Y93 -> 0
B96: TOTAL | M96: US$ | R96: =+R88+R91+R94 -> 0 | W96: US$ | Y96: =+Y88+Y91+Y94 -> 0
B97: (*) Factor de Depreciación
B101: VALOR TOTAL DE LAS EDIFICACIONES (VTE1) [Mediante el Método de Costos Directos = VE + VAC + VI + VOC] | X101: US$ | Y101: =Y61+Y75+Y96 -> 0
B103: VALOR TOTAL DEL PREDIO (VTP1) [Mediante el Método de Costos Directos = VT + VE + VAC + VI + VOC] | X103: US$ | Y103: =+X25+Y61+Y75+Y96 -> 0
B105: VALOR DE RECONSTRUCCIÓN DEL INMUEBLE TASADO (VSN) [VSNE + VSNAC + VSNVI + VSNVOC] | X105: US$ | Y105: =+M61+R75+R96 -> 0

Sheet CASO EN QUINTA (SI CORRESPONDE)
T1: N° de Solicitud BCP | Y1: :
T2: N° de Servicio Tasadora | Y2: :
T3: Fecha de Expedición | Y3: :
T4: Fecha última de Vigencia | Y4: :
A5: VALOR DE TERRENO (VT)
B7: Cálculo del Supuesto Valor Comercial Urbano (SVCU) de la vía de Dominio Privado
S8: VCTU | T8: = | U8: Valor Comercial de Terreno Urbano de la vía de dominio privado.
E9: (US$/m2) | H9: m | L9: m | S9: a | T9: = | U9: Ancho de la vía de dominio privado expresado en metros con aproximación al centésimo, medida en el lindero de ésta con la vía pública
B10: SVCU | D10: = | E10: VCTU | G10: x | H10: (a* | I10: / | J10: 3) | K10: x | L10: (1.00 | M10: - | N10: 0.01 | O10: d)
B11: SVCU | D11: = | E11: 1650 | G11: x | H11: 1 | I11: / | J11: 3) | K11: x | L11: (1.00 | M11: - | N11: 0.01 | O11: 56
S12: d | T12: = | U12: Distancia de la vía pública hasta el vértice más cercano del terreno materia de tasación, expresado en metros con aproximación al centésimo, medida sobre las líneas de propiedad colindantes con la vía de dominio privado.
B13: SVCU* | D13: = | E13: US$ | F13: =+E11*0.5 -> 825
B14: *Nota 1: Si la relación a/3.00 resulta mayor de 1.00 se asume una unidad (1.00) como valor de la misma
B15: *Nota 2: El Supuesto Valor Comercial Urbano (SVCU) no debe ser menor a 0.5 VCTU de lo contrario se descarta considerándose como mínimo 0.5 VCTU
B16: Artículos 21/23 del RNT: Tasación comercial de un lote de terreno urbano frente a un pasadizo común o vía de dominio privado en condominio.
B18: Luego se tiene:
B19: Unidad Inmobiliaria | H19: Área de terreno (m2) | M19: % de Participación | Q19: Supuesto Valor Comercial Urbano (SVCU) US$/m2 | X19: Valor de Terreno (US$)
H20: 679.5 | Q20: =F13 -> 825 | X20: =+H20*Q20 -> 560587.5
B21: Subtotal Terreno (VT) | H21: =SUM(H20:L20) -> 679.5 | X21: =SUM(X20:AC20) -> 560587.5
B23: Cálculo del Valor Correspondiente al Terreno del Pasadizo Común | AI23: =7+56+56 -> 119
AI24: =15/AI23 -> 0.12605042
B25: Unidad Inmobiliaria | M25: Área de terreno (m2) | Q25: Valor Comercial de Terreno Urbano (VCTU) | V25: Factor | X25: Valor de Terreno (US$) | AE25: =+X21+X28 -> 1005262.5
B26: 3(frente)^2 del pasillo | M26: =7*7*3 -> 147 | Q26: 1650 | V26: 1 | X26: =+M26*Q26 -> 242550 | AE26: =+X28*AI24 -> 56051.471
B27: Terreno restante del pasillo | M27: =392-M26 -> 245 | Q27: 1650 | V27: 0.5 | X27: =+M27*Q27*V27 -> 202125 | AE27: =+AE26+X21 -> 616638.97
B28: Subtotal Terreno (VT) | M28: =SUM(M26:P27) -> 392 | X28: =SUM(X26:AC27) -> 444675 | AH28: =+AE27/H21 -> 907.48929
P29: Considerando el área proporcional: | X29: =+X28*V29 -> 0
B31: VALOR TOTAL DEL TERRENO* | W31: = | X31: =X21+X29 -> 560587.5
B32: *Suma del Valor del Área del Dominio Privado y el Valor que le corresponde del Pasadizo Común
A34: VALOR DE LAS EDIFICACIONES [VALOR SIMILAR A NUEVO (VSNE) Y VALOR DE EDIFICACIÓN (VE)]
W36: Región de la Edificación:
B37: De acuerdo a las características constructivas y a los acabados del inmueble observados en la inspección realizada se estima el costo de construcción para: | W37: Costa
B39: Código | E39: Partida | L39: VUE1 | O39: VUE2 | R39: VUE3 | U39: VUE4 | X39: VUE5 | AA39: VUE6
L40: Clas. | M40: Costo/m2 | O40: Clas. | P40: Costo/m2 | R40: Clas. | S40: Costo/m2 | U40: Clas. | V40: Costo/m2 | X40: Clas. | Y40: Costo/m2 | AA40: Clas. | AB40: Costo/m2
B41: 1 | E41: Muros y Columnas | L41: C
B42: 2 | E42: Techos
B43: 3 | E43: Pisos
B44: 4 | E44: Puertas y Ventanas | L44: C
B45: 5 | E45: Revestimientos
B46: 6 | E46: Baños
B47: 7 | E47: Instalaciones Eléctricas y Sanitarias
B48: Costo Unitario de Edificación (S/.): | L48: =SUM(M41:N47) -> 0 | O48: =SUM(P41:Q47) -> 0 | R48: =SUM(S41:T47) -> 0 | U48: =SUM(V41:W47) -> 0 | X48: =SUM(Y41:Z47) -> 0 | AA48: =SUM(AB41:AC47) -> 0
B49: Gastos Generales: | F49: =CHOOSE(MATCH(G49,'Lista-Data'!BJ3:BJ5,0),14%,7%,4%) -> 0.04 | G49: (Obra Grande) | L49: =IF(L48=0,"",ROUND(GastosGenerales*L48,2)) | O49: =IF(O48=0,"",ROUND(GastosGenerales*O48,2)) | R49: =IF(R48=0,"",ROUND(GastosGenerales*R48,2)) | U49: =IF(U48=0,"",ROUND(GastosGenerales*U48,2)) | X49: =IF(X48=0,"",ROUND(GastosGenerales*X48,2)) | AA49: =IF(AA48=0,"",ROUND(GastosGenerales*AA48,2))
B50: Utilidad: | F50: 0.1 | G50: Tipo de Cambio: | J50: 3.49 | L50: =IF(L48=0,"",ROUND(Utilidad*L48,2)) | O50: =IF(O48=0,"",ROUND(Utilidad*O48,2)) | R50: =IF(R48=0,"",ROUND(Utilidad*R48,2)) | U50: =IF(U48=0,"",ROUND(Utilidad*U48,2)) | X50: =IF(X48=0,"",ROUND(Utilidad*X48,2)) | AA50: =IF(AA48=0,"",ROUND(Utilidad*AA48,2))
B51: Valor Unitario de Edificación (S/.): | L51: =SUM(L48:L50) -> 0 | O51: =SUM(O48:O50) -> 0 | R51: =SUM(R48:R50) -> 0 | U51: =SUM(U48:U50) -> 0 | X51: =SUM(X48:X50) -> 0 | AA51: =SUM(AA48:AA50) -> 0
B52: Valor Unitario de Edificación redondeado (US$): | L52: 0 | O52: 0 | R52: 0 | U52: 0 | X52: 0 | AA52: 0
B54: Cálculo del Valor Similar a Nuevo o Valor de Reconstrucción de las Edificaciones (VSNE) y el Valor de las Edificaciones (VE)
B55: Descripción | H55: Área (m2) | J55: VUE (US$/m2) | M55: Valor Similar a Nuevo (US$) | P55: Material Predominante | T55: Edad (años) | V55: Estado de Conservación | Y55: FD (*) | Z55: Valor de Edificación (US$)
A56: 1 | B56: 0 | H56: 0 | M56: =ROUND(J56*H56,2) -> 0 | Z56: =ROUND(M56*Y56,2) -> 0
A57: 2 | B57: 0 | H57: 0 | M57: =ROUND(J57*H57,2) -> 0 | Z57: =ROUND(M57*Y57,2) -> 0
A58: 3 | B58: 0 | H58: 0 | M58: =ROUND(J58*H58,2) -> 0 | Z58: =ROUND(M58*Y58,2) -> 0
A59: 4 | B59: 0 | H59: 0 | M59: =ROUND(J59*H59,2) -> 0 | Z59: =ROUND(M59*Y59,2) -> 0
A60: 5 | B60: 0 | H60: 0 | M60: =ROUND(J60*H60,2) -> 0 | Z60: =ROUND(M60*Y60,2) -> 0
A61: 6 | B61: 0 | H61: 0 | M61: =ROUND(J61*H61,2) -> 0 | Z61: =ROUND(M61*Y61,2) -> 0
A62: 7 | B62: 0 | H62: 0 | M62: =ROUND(J62*H62,2) -> 0 | Z62: =ROUND(M62*Y62,2) -> 0
A63: 8 | B63: 0 | H63: 0 | M63: =ROUND(J63*H63,2) -> 0 | Z63: =ROUND(M63*Y63,2) -> 0
A64: 9 | B64: 0 | H64: 0 | M64: =ROUND(J64*H64,2) -> 0 | Z64: =ROUND(M64*Y64,2) -> 0
B65: Subtotal Edificaciones (VSNE) | H65: =SUM(H56:H64) -> 0 | L65: US$ | M65: =SUM(M56:OM64) -> 0 | Q65: Subtotal Edificaciones (VE) | X65: US$ | Y65: =SUM(Z56:Z64) -> 0
A67: VALOR DE EDIFICACIÓN DE LAS AREAS COMUNES (VAC)
B69: Según el Reglamento General de Tasaciones del Perú, para el valor de las Áreas Comunes en los regímenes que corresponda, se asigna un % del valor de la edificación:
B70: Descripción | H70: % de Áreas Comunes | M70: Valor Unitario de Áreas Comunes (US$/m2) | R70: Valor de Reconstrucción Áreas Comunes (US$) | W70: FD (*) | Y70: Valor de Áreas Comunes (US$)
B72: Áreas Comunes | H72: 0.15 | R72: 0 | Y72: =ROUND(R72*W72,2) -> 0
B73: Subtotal Áreas Comunes (VAC) | Q73: US$ | R73: =SUM(R72:R72) -> 0 | X73: US$ | Y73: =SUM(Y72:Y72) -> 0
A75: VALOR DE LAS INSTALACIONES FIJAS Y OBRAS COMPLEMENTARIAS (VI + VOC)
B77: Descripción | G77: Cantidad | J77: Unidad (Und.) | L77: Valor Unitario (US$/Und.) | O77: Valor de Reconstrucción (US$) | R77: Edad (años) | T77: Estado de Conservación | W77: FD (*) | Y77: Valor de Inst. y Obras Complem. (US$)
A79: 1 | R79: =ROUND(M79*H79,2) -> 0 | Y79: =ROUND(R79*W79,2) -> 0
A80: 2 | R80: =ROUND(M80*H80,2) -> 0 | Y80: =ROUND(R80*W80,2) -> 0
A81: 3 | R81: =ROUND(M81*H81,2) -> 0 | Y81: =ROUND(R81*W81,2) -> 0
A82: 4 | R82: =ROUND(M82*H82,2) -> 0 | Y82: =ROUND(R82*W82,2) -> 0
B83: Subtotal Instalaciones y Obras Complementarias (VI + VOC) | N83: US$ | O83: =SUM(O79:Q82) -> 0 | X83: US$ | Y83: =SUM(Y79:AC82) -> 0
B84: (*) Factor de Depreciación
B88: VALOR TOTAL DE LAS EDIFICACIONES (VTE1) [Mediante el Método de Costos Directos = VE + VAC + VI + VOC] | X88: US$ | Y88: =Y65+Y73+Y83 -> 0
B90: VALOR TOTAL DEL PREDIO (VTP1) [Mediante el Método de Costos Directos = VT + VE + VAC + VI + VOC] | X90: US$ | Y90: =+X21+Y65+Y73+Y83 -> 560587.5
B92: VALOR DE RECONSTRUCCIÓN DEL INMUEBLE TASADO (VSN) [VSNE + VSNAC + VSNVI + VSNVOC] | X92: US$ | Y92: =+M65+R73+O83 -> 0

Sheet COMPARACIÓN
T12: N° de Solicitud BCP | Y12: : | Z12: =+REPOSICIÓN!Z12 -> 0
T13: N° de Servicio Tasadora | Y13: : | Z13: =+REPOSICIÓN!Z13 -> XXXX-26
T14: Fecha de Expedición | Y14: : | Z14: =+REPOSICIÓN!Z14 -> 0 | AF14: VALOR DEL ÁREA UTIL VENDIBLE
T15: Fecha última de Vigencia | Y15: : | Z15: =+REPOSICIÓN!Z15 -> 365 | AF15: CUADRO COMPARATIVO
A16: MÉTODO DE MERCADO O COMPARACIÓN (OFERTA DE INMUEBLES SIMILARES EN EL MERCADO) | AF16: UBICACIÓN | AU16: Zonificación | AX16: Antigüedad | BA16: Área de terreno m2 | BD16: Área construida m2 | BG16: V. Tot. Inm. US$ | BL16: V. Const. US$ | BQ16: Valor de Terr.US$ | BV16: V.U.A. U.V. US$/m2
B17: DATOS GENERALES DE LOS COMPARABLES | K17: (Evidenciar como mínimo tres (03) muestras)
B18: Descripción | I18: Fuente (In situ, correo, página web, periódicos, etc) | R18: Teléfono | U18: Contacto | X18: Comparación | AA18: Fecha
B19: "OFERTA EN EL MERCADO" | AF19: =+B19 -> "OFERTA EN EL MERCADO"
A20: 1 | B20: =+AF20 -> 0 | BV20: =+BG20/BD20 -> #DIV/0!
A21: 2 | B21: =+AF21 -> 0 | BV21: =+BG21/BD21 -> #DIV/0!
A22: 3 | B22: =+AF22 -> 0 | BV22: =+BG22/BD22 -> #DIV/0!
A23: 4 | B23: =+AF23 -> 0 | BV23: =+BG23/BD23 -> #DIV/0!
B24: "INMUEBLES VENDIDOS - VENTAS CERRADAS" Tomado del aplicativo Vanetmap
A25: 5 | B25: =+AF25 -> 0 | BV25: =+BG25/BD25 -> #DIV/0!
B26: Características de los Comparables
B27: Características | H27: Planificación | Q27: Valor de la Oferta US$ | U27: Descuentos (US$)
B28: Vistas | D28: Ubicación | F28: Tipo | H28: Nivel | I28: Asc. | J28: Dor. | K28: Baño | L28: Est. | M28: Dep | N28: Edad | O28: Conser. | U28: Estacion. | X28: Depósito | AA28: Área Libre
B29: "OFERTA EN EL MERCADO" | AF29: =+B29 -> "OFERTA EN EL MERCADO"
A30: 1 | Q30: =+BG20 -> 0
A31: 2 | Q31: =+BG21 -> 0
A32: 3 | Q32: =+BG22 -> 0
A33: 4 | Q33: =+BG23 -> 0
B34: "INMUEBLES VENDIDOS - VENTAS CERRADAS" Tomado del aplicativo Vanetmap
A35: 5 | Q35: =+BG25 -> 0
B36: HOMOLOGACIÓN DE LOS COMPARABLES
B37: Valor Neto del Inmueble (US$) | H37: Área (m2) | N37: VCU/AC (US$/m2) | Q37: Factores de Homologación | W37: Factor Resultante | Z37: VCU/AC Homolog. (US$/m2)
H38: Terreno | K38: Construida | Q38: Ub. | R38: Ent. | S38: Sup | T38: Ed. | U38: T/C | V38: F.N.
B39: "OFERTA EN EL MERCADO" | AF39: =+B39 -> "OFERTA EN EL MERCADO"
A40: 1 | B40: =IF(Q30-SUM(U30:AC30)=0,"",ROUND(Q30-SUM(U30:AC30),2)) | K40: =+BD20 -> 0 | N40: =+B40/K40 -> #VALUE! | Q40: 1 | R40: 1 | S40: 1 | T40: 1 | U40: 1 | V40: 1 | W40: =PRODUCT(Q40:V40) -> 1 | Z40: =IFERROR(ROUND(N40^2*W40/N40,2)," ")
A41: 2 | B41: =IF(Q31-SUM(U31:AC31)=0,"",ROUND(Q31-SUM(U31:AC31),2)) | K41: =+BD21 -> 0 | N41: =+B41/K41 -> #VALUE! | Q41: 1 | R41: 1 | S41: 1 | T41: 1 | U41: 1 | V41: 1 | W41: =PRODUCT(Q41:V41) -> 1 | Z41: =IFERROR(ROUND(N41^2*W41/N41,2)," ")
A42: 3 | B42: =IF(Q32-SUM(U32:AC32)=0,"",ROUND(Q32-SUM(U32:AC32),2)) | K42: =+BD22 -> 0 | N42: =+B42/K42 -> #VALUE! | Q42: 1 | R42: 1 | S42: 1 | T42: 1 | U42: 1 | V42: 1 | W42: =PRODUCT(Q42:V42) -> 1 | Z42: =IFERROR(ROUND(N42^2*W42/N42,2)," ")
A43: 4 | B43: =IF(Q33-SUM(U33:AC33)=0,"",ROUND(Q33-SUM(U33:AC33),2)) | K43: =+BD23 -> 0 | N43: =+B43/K43 -> #VALUE! | Q43: 1 | R43: 1 | S43: 1 | T43: 1 | U43: 1 | V43: 1 | W43: =PRODUCT(Q43:V43) -> 1 | Z43: =IFERROR(ROUND(N43^2*W43/N43,2)," ")
B44: "INMUEBLES VENDIDOS - VENTAS CERRADAS" Tomado del aplicativo Vanetmap
A45: 5 | K45: =+BD25 -> 0 | N45: =+B45/K45 -> #DIV/0! | Q45: 1 | R45: 1 | S45: 1 | T45: 1 | U45: 1 | V45: 1 | W45: =PRODUCT(Q45:V45) -> 1 | Z45: =IFERROR(ROUND(N45^2*W45/N45,2)," ")
B46: Valor Comercial Unitario Homologado Promedio [$/m²]: | K46: =IFERROR(AVERAGEIF(Z40:Z45,">0"),0) -> 0 | Q46: VCU Homologado Promedio ajustado por redondeo [$/m²]: | Z46: =ROUND(K46,-1) -> 0
B48: *Notas: | E48: 1. - Los Valores Unitarios de Mercado han sido afectados por un Factor de Negociación reconociendo que se tratan de comparables de carácter ofertable aún sin realizar.
E49: 2. - Los comparables identificados han sido ponderados reconociendo la variación en cuanto a criterios de Ubicación, Entorno, Superficie y Edad.
A51: PLANO DE UBICACIÓN Y REFERENCIAS DE INMUEBLES SIMILARES
B73: RESUMEN VALORES UNITARIOS
B74: COMPARABLES | C74: Referencias | G74: Ofertado | J74: Homologado
C75: =+A40 -> 1 | G75: =IF(N40>0,N40," ") -> #VALUE! | H75: =IF(O40>0,O40," ") | I75: =IF(P40>0,P40," ") | J75: =Z40
C76: =A31 -> 2 | G76: =IF(N41>0,N41," ") -> #VALUE! | H76: =IF(O41>0,O41," ") | I76: =IF(P41>0,P41," ") | J76: =Z41
C77: =A32 -> 3 | G77: =IF(N42>0,N42," ") -> #VALUE! | H77: =IF(O42>0,O42," ") | I77: =IF(P42>0,P42," ") | J77: =Z42
C78: =A33 -> 4 | G78: =IF(N43>0,N43," ") -> #VALUE! | H78: =IF(O43>0,O43," ") | I78: =IF(P43>0,P43," ") | J78: =Z43
C79: =A35 -> 5 | G79: =IF(N45>0,N45," ") -> #DIV/0! | H79: =IF(O45>0,O45," ") | I79: =IF(P45>0,P45," ") | J79: =Z45
C80: Promedio: | G80: =IFERROR(AVERAGE(G75:G79),"") | J80: =IFERROR(AVERAGE(J75:J79),"")
C81: Máximo | G81: =IF(MAX(G75:G79)=0,"",MAX(G75:G79)) -> #VALUE! | J81: =IF(MAX(J75:J79)=0,"",MAX(J75:J79))
C82: Mínimo | G82: =IF(MIN(G75:G79)=0,"",MIN(G75:G79)) -> #VALUE! | J82: =IF(MIN(J75:J79)=0,"",MIN(J75:J79))
C83: Difer. Max Min | G83: =IFERROR(G81-G82,"") | J83: =IFERROR(J81-J82,"")
A85: VALOR TOTAL DEL PREDIO MEDIANTE EL MÉTODO DE COMPARACIÓN
B87: De acuerdo a la Investigación de Mercado de Inmuebles con características similares al inmueble tasado se tiene:
B88: Descripción | K88: Área (m2) | N88: V. C. Unit. Mercado (US$/m2) | R88: Factor de Ajuste 1 | T88: Factor de Ajuste 2 | V88: Valor de Mercado (US$) | AF88: factor de ajuste 2
AF89: motivo de los factores
A90: 1 | B90: =REPOSICIÓN!B52 -> Primer piso | K90: =REPOSICIÓN!H52 -> 0 | N90: =+$Z$46 -> 0 | R90: 1 | V90: =ROUND(PRODUCT(K90:U90),2) -> 0
A91: 2 | B91: =REPOSICIÓN!B53 -> Estacionamiento N° | K91: =REPOSICIÓN!H53 -> 0 | N91: =IF(K91=0,0,Z46) -> 0 | R91: 1 | V91: =ROUND(PRODUCT(K91:U91),2) -> 0
A92: 3 | B92: =REPOSICIÓN!B54 -> Depósito N° | K92: =REPOSICIÓN!H54 -> 0 | N92: =IF(K92=0,0,$Z$46) -> 0 | R92: 1 | V92: =ROUND(PRODUCT(K92:U92),2) -> 0
A93: 4 | B93: =REPOSICIÓN!B55 -> 0 | K93: =REPOSICIÓN!H55 -> 0 | N93: =IF(K93=0,0,$Z$46) -> 0 | R93: 1 | V93: =ROUND(PRODUCT(K93:U93),2) -> 0
A94: 5 | B94: =REPOSICIÓN!B56 -> 0 | K94: =REPOSICIÓN!H56 -> 0 | N94: =IF(K94=0,0,$Z$46) -> 0 | R94: 1 | V94: =ROUND(PRODUCT(K94:U94),2) -> 0
A95: 6 | B95: =REPOSICIÓN!B57 -> 0 | K95: =REPOSICIÓN!H57 -> 0 | N95: =IF(K95=0,0,$Z$46) -> 0 | V95: =ROUND(PRODUCT(K95:U95),2) -> 0
A96: 7 | B96: =REPOSICIÓN!B58 -> 0 | K96: =REPOSICIÓN!H58 -> 0 | N96: =IF(K96=0,0,$Z$46) -> 0 | V96: =ROUND(PRODUCT(K96:U96),2) -> 0
A97: 8 | B97: =REPOSICIÓN!B59 -> 0 | K97: =REPOSICIÓN!H59 -> 0 | N97: =IF(K97=0,0,$Z$46) -> 0 | V97: =ROUND(PRODUCT(K97:U97),2) -> 0
A98: 9 | B98: =REPOSICIÓN!B60 -> 0 | K98: =REPOSICIÓN!H60 -> 0 | N98: =IF(K98=0,0,$Z$46) -> 0 | V98: =ROUND(PRODUCT(K98:U98),2) -> 0
B99: Total del Valor de Mercado | U99: US$ | V99: =SUM(V90:AC98) -> 0
B101: VALOR TOTAL DEL PREDIO (VTP2) [Mediante el Método de Mercado] | U101: US$ | V101: =+V99 -> 0

Sheet RESULTADOS
T12: N° de Solicitud BCP | Y12: : | Z12: =+COMPARACIÓN!Z12 -> 0
T13: N° de Servicio Tasadora | Y13: : | Z13: =+COMPARACIÓN!Z13 -> XXXX-26
T14: Fecha de Expedición | Y14: : | Z14: =+COMPARACIÓN!Z14 -> 0
T15: Fecha última de Vigencia | Y15: : | Z15: =+COMPARACIÓN!Z15 -> 365
A16: RESULTADOS
A17: RESUMEN GENERAL DE TASACIÓN
B19: Mediante los métodos aplicados se han obtenido los siguientes resultados:
B21: RESULTADOS DE LOS MÉTODOS DIRECTOS: | O21: VTP (US$) | T21: VU (US$/m2) | Y21: VTP (S/.)
B23: Método de Costos o Reposición | O23: =+REPOSICIÓN!Y103 -> 0 | T23: =+O23/'MEM. DESC. II'!$K$56 -> #DIV/0! | Y23: =+O23*REPOSICIÓN!$J$45 -> 0
B24: Método de Comparación o de Mercado | O24: =IFERROR(+COMPARACIÓN!V101,"") -> 0 | T24: =+O24/'MEM. DESC. II'!$K$56 -> #DIV/0! | Y24: =+O24*REPOSICIÓN!$J$45 -> 0
A26: VALOR COMERCIAL DEL INMUEBLE
B28: Para determinar la conclusión del Valor Comercial del inmueble, se han tenido en cuenta las siguientes consideraciones:
B30: a. | C30: Estado y conservacion del inmueble.
B32: b. | C32: Estudio del mercado de la referencia de inmuebles.
B34: c. | C34: Entorno y ubicación del inmueble.
B36: d. | C36: El método que mejor refleja el Valor Comercial es el: | M36: Método de Comparación (O de Mercado)
X37: Valor Comercial
B38: Valor Comercial en Dólares (Moneda Extranjera)
B39: SON: | D39: =+CONCATENATE(" ",[10]!NumeLetras(X39,"con","dolares americanos",1)) -> #NAME? | X39: =+IF(M36="Método de Comparación (O de Mercado)",O24,O23) -> 0
B40: Valor Comercial en Soles (Moneda Local)
B41: SON: | D41: =+CONCATENATE(" ",[10]!NumeLetras(X41,"con","sOLES",1)) -> #NAME? | X41: =+X39*REPOSICIÓN!J45 -> 0
A43: VALOR DE REALIZACIÓN INMEDIATA
B45: El Valor de Realización Inmediata, es el Valor Neto del inmueble que se esperaría recuperar como consecuencia de la eventual venta del bien en el menor tiempo posible y en las condiciones actuales del inmueble y el mercado. Se obtiene descontando los castigos y cargos por los conceptos indicados a continuación:
C47: Concepto de la Deducción | R47: % de la Deducción | X47: Importe (US$)
C48: a. | D48: Gastos de Publicidad. | R48: 0.02 | X48: =+$X$39*R48 -> 0
C49: b. | D49: Gastos de tasación del inmueble para la Realizacion. | R49: 0.002 | X49: =+$X$39*R49 -> 0
C50: c. | D50: Comisiones de Ventas. | R50: 0.05 | X50: =+$X$39*R50 -> 0
C51: d. | D51: Mantenimiento. | R51: 0.02 | X51: =+$X$39*R51 -> 0
C52: e. | D52: Factor por la venta del inmueble (Realización) en un plazo de 60 dias. | R52: =+R54-R48-R49-R50-R51-R53 -> 0.108 | X52: =+$X$39*R52 -> 0
C53: f. | D53: Otras Deducciones (Sólo casos especiales). | R53: 0 | X53: =+$X$39*R53 -> 0
C54: Total Deducciones | R54: 0.2 | X54: =SUM(X48:AA53) -> 0
X56: Valor Realización Inmediata
B57: Valor de Realización En Dólares (Moneda Extranjera)
B58: SON: | D58: =+CONCATENATE(" ",[10]!NumeLetras(X58,"con","dolares americanos",1)) -> #NAME? | X58: =+X39-X54 -> 0
B60: Valor de Realización en Soles (Moneda Local)
B61: SON: | D61: =+CONCATENATE(" ",[10]!NumeLetras(X61,"con","sOLES",1)) -> #NAME? | X61: =+X58*REPOSICIÓN!J45 -> 0
A63: RESPONSABLES
B65: EMPRESA TASADORA: | J65: VANET SAC
B67: REGISTRO REPEV: | J67: 561-2001
B69: PERITO RESPONSABLE DE INSPECCIÓN: | J69: RICARDO BARTHELLMES SACO
Q74: PERITO: | T74: RICARDO BARTHELMESS SACO
Q75: PROFESION: | T75: INGENIERO
Q76: REPEV: | T76: 561-2001
A78: OBSERVACIONES DEL PERITO
B80: Ninguna
A90: CONDICIONANTES Y ADVERTENCIAS
B92: Ninguna

Sheet ALQUILER
B2: VALOR DE ALQUILER
B4: Conforme a lo solicitado se estimará, como un segundo enfoque, el valor que la propiedad tendría según el poder de ganancia neta de la propiedad basado en la capitalización del ingreso neto.
B5: CUADRO DE ALQUILERES O ARRENDAMIENTOS
B6: Según sondeo de alquiler o arrendamiento de inmuebles similares al inmueble materia de valuación, se obtuvo lo siguiente :
B7: CUADRO COMPARATIVO
B9: UBICACIÓN | R9: Zonificación | U9: Antigüedad | X9: Distanc. Al Inm. Mt. | AA9: Área de terreno m2 | AD9: Área Techada m2 | AG9: Renta Mensual | AK9: Renta Anual Bruta | AO9: Renta Anual Neta | AS9: Valor Unit. Renta por m2 techado
AK10: =+AG10*12 -> 0 | AO10: =+AG10*10 -> 0 | AS10: =+ROUND(AG10/AD10,0) -> #DIV/0!
AK11: =+AG11*12 -> 0 | AO11: =+AG11*10 -> 0 | AS11: =+ROUND(AG11/AD11,0) -> #DIV/0!
AK12: =+AG12*12 -> 0 | AO12: =+AG12*10 -> 0 | AS12: =+ROUND(AG12/AD12,0) -> #DIV/0!
AK13: =+AG13*12 -> 0 | AO13: =+AG13*10 -> 0 | AS13: =+ROUND(AG13/AD13,0) -> #DIV/0!
B28: Del estudio de mercado se puede determinar que el valor de los alquileres de locales comerciales en la zona oscila entre US$17.00/m2 a US$ 22.00/m2, dependiendo de su área, ubicación y movimiento comercial. La referencia N° 1, se encuentra ubicada en calle, con igual zonificación al valuado y de menor área. La referencia N°2, se encuentra ubicado en avenida con igual zonificación que el valuado y de menor área construida. La referencia N° 3, se encuentra ubicada en avenida, con zonificación CM a diferencia del valuado que cuenta con zonificación CZ, y menor área construida. La referencia N°4, se encuentra ubicado en avenida, con igual zonificación y menor área que el valuado. De lo anterior se puede apreciar, que la referencia N° 3, es la más cercana al valuado, el cual se encuentra ubicado en esquina, por lo que al valor unitario de alquiler de US$ 26.00/m2, se le aplica un factor de 1.15 y se estima un valor unitario de US$ 30.00/m2, adicionalmente el valuado se encuentra ubicado frente a parque frente a parque Mariscal Cáceres y cerca de la Av. Salaverry zona de alto tránsito, por lo que al valor unitario de US$30.00/m2 se le bonifica con un factor de 1.15 y se estima un valor unitario redondeado de:
AB29: /m2
B30: =+REPOSICIÓN!H52 -> 0 | K30: X | P30: =+V29 -> 0 | AL30: = | AM30: =+B30*P30 -> 0
B31: TOTAL VALOR COMERCIAL DE ALQUILER DEL INMUEBLE | AL31: = | AM31: =+AM30 -> 0
A33: -.&&&&&&&.-
C39: Lima, | F39: =+RESULTADOS!Z14 -> 0

Sheet Lista-Data
A1: LISTAS | BN1: TIPO DE FACTOR DE HOMOLOGACIÓN | BT1: LISTAS NO UTILIZADAS
B2: TIPO DE TASACIÓN | D2: TIPO DE INMUEBLE | E2: TIPO DE USO | F2: OBJETO Y PROPÓSITO | G2: TITULACIÓN E INSCRIPCIÓN | H2: OCUPANTE | I2: TIPO DE ZONA | J2: USO PREDOMINANTE | K2: DESARROLLO | L2: NIVEL SOCIOECONÓMICO | M2: TENDENCIA DE DESARROLLO URBANO | N2: DEMANDA / INTERÉS | O2: ZONIFICACIÓN | P2: ALTURA DE EDIFICACIÓN | Q2: VELOCIDAD DE CAMBIO | R2: ESTADO DE CONSERVACIÓN | S2: NIVEL DE EQUIPAMIENTO | T2: INFRAESTRUCTURA | U2: CALIDAD | V2: MATERIAL PREDOMINANTE | W2: ESTADO DE CONSERVACIÓN | X2: CUENTA CON ASCENSOR | Y2: ÁREAS COMUNES | Z2: OBRAS COMPLEMENTARIAS | AA2: MANTENIMIENTO | AB2: SERVICIOS | AC2: UNIDAD | AD2: OBTENCIÓN DEL ÁREA | AE2: CIMENTACIÓN | AF2: ESTRUCTURA | AG2: MUROS | AH2: TECHOS | AI2: COBERTURA | AJ2: INST. ELÉCTRICAS | AK2: INST. GAS | AL2: INST. SANITARIAS | AM2: PUERTAS | AP2: VENTANAS | AS2: MAMPARAS | AV2: MUEBLES DE COCINA | AZ2: BAÑOS | BC2: CLOSETS | BD2: PISOS | BE2: REVESTIMIENTOS | BF2: CERRAJERÍA | BG2: COMPARACIÓN GENERAL | BH2: REGIÓN DE EDIFICACIÓN | BI2: CLASE | BJ2: OBRA | BK2: VISTA | BL2: UBICACIÓN | BM2: TIPO INMUEBLE | BN2: FACTOR | BO2: CONCEPTO DEL FACTOR | BP2: SÍ / NO | BQ2: MÉTODO | BR2: CÓDIGO | BS2: DECLARATORIA DE FÁBRICA | BT2: OFICINAS REGISTRALES | BU2: IDENTIF | BV2: DISTRIBUCIÓN | BX2: Tipo de oferta | BZ2: TIPO DE SUELO
B3: Comercial | D3: Terreno | E3: Casa Habitación | F3: Determinar el Valor Comercial del inmueble para fines de Garantía Hipotecaria | G3: Partida Electrónica | H3: Propietario | I3: Urbana | J3: Vivienda | K3: Creciente | L3: Estrato Alto | M3: Consolidado Homogéneo | N3: Nula | O3: RDMB | P3: Alta | Q3: Rápida | R3: Muy Bueno | S3: Muy Abundante | T3: Completas | U3: Muy Alto | V3: Ladrillo | W3: Nuevo - Estreno | X3: Sí | Y3: Sí, especificadas en cuadro detalle | Z3: Sí, especificadas en cuadro detalle | AA3: Constante | AB3: Sí, todos | AC3: m2 | AD3: F. Reg/Part. Elect | AE3: Platea de Cimentación | AF3: Laminares Curvadas | AG3: Adobe | AH3: Losa Aligerada de C°A° Unidireccional | AI3: Tejas Cerámicas | AJ3: Sin Instalación | AK3: Sin Instalación | AL3: Sin Instalación | AM3: Tipo | AN3: Material | AO3: Sistema | AP3: Marco | AQ3: Vidrio | AR3: Sistema | AS3: Marco | AT3: Vidrio | AU3: Sistema | AV3: Tipo | AW3: Material | AX3: Tableros | AY3: Lavadero | AZ3: Tipo | BA3: Color | BB3: Grifería | BC3: Vestidos de Madera con Cajonería de Cedro | BD3: Alfombra | BE3: Tarrajeo | BF3: Cerradura tipo Yale o Similar | BG3: Peor | BH3: Lima Metropolitana y Callao | BI3: A | BJ3: (Obra Pequeña) | BK3: Al mar | BL3: Interior | BM3: Flat | BN3: C/T | BO3: AC / Terreno | BP3: Sí | BQ3: Método Directo de Costos (O de Reposición) | BR3: 1 | BS3: Tiene | BT3: Abancay | BU3: Calle: | BV3: Almacén | BW3: C°A° | BX3: Transac. | BY3: UNIDAD INMOBILIARIA | BZ3: Arenoso
B4: Hipotecaria | D4: Vivienda | E4: Departamento Flat | F4: Determinar el Valor Comercial del inmueble para fines Judiciales | G4: Ficha Registral | H4: Inquilino | I4: Rural | J4: Comercio | K4: En Renovación | L4: Medio Alto | M4: Consolidado Heterogéneo | N4: Débil | O4: RDB | P4: Media | Q4: Lenta | R4: Bueno | S4: Abundante | T4: Incompletas | U4: Alto | V4: Concreto | W4: Muy Bueno | X4: No | Y4: Escalera de acceso, recepción | Z4: No | AA4: Regularmente | AB4: Solo servicio eléctrico | AC4: ha | AD4: Copia Literal | AE4: Vigas de Cimentación | AF4: Pórticos de Concreto Armado | AG4: Pircado con mezcla de barro | AH4: Losa Aligerada de C°A° Bidireccional | AI4: Tejas de Madera | AJ4: Corriente Monofásica sin empotrar | AK4: Cocina | AL4: Tuberías de agua fría y desagüe | AM4: Apanelada | AN4: Fierro | AO4: Corrediza | AP4: Madera | AQ4: Crudo | AR4: Corrediza | AS4: Madera | AT4: Crudo | AU4: Corrediza | AV4: Bajos | AW4: Concreto | AX4: Madera | AY4: Acero | AZ4: Sifón Top Piece y/o Rapid Jet | BA4: Blanco | BB4: Importada | BC4: Con persianas o paneles | BD4: Bambú | BE4: Pintura | BF4: Alpha Vaivén | BG4: Inferior | BH4: Costa | BI4: B | BJ4: (Obra Mediana) | BK4: Al parque | BL4: Exterior | BM4: Dúplex | BN4: Vis | BO4: Vista (Exterior o Interior) | BP4: No | BQ4: Método de Comparación (O de Mercado) | BR4: 2 | BS4: No Tiene | BT4: Andahuaylas | BU4: Jirón: | BV4: Azotea | BW4: C°A°-Ladrillo | BX4: Oferta | BY4: DEPARTAMENTO | BZ4: Arcilloso
B5: Judicial | D5: Comercio | E5: Departamento Dúplex | G5: Copia Literal | H5: Inquilino Precario | J5: Industria | K5: Estacionario | L5: Estrato Medio | M5: En Proceso de Consolidación | N5: Media | O5: RDM | P5: Baja | Q5: Media | R5: Regular | S5: Suficiente | T5: No tiene | U5: Medio | V5: Concreto - Ladrillo | W5: Bueno | X5: Directo a unidad inmobiliaria | Y5: No corresponde | AA5: No cuenta con mantenimiento | AB5: Solo agua y servicio eléctrico, no desagüe | AC5: varas2 | AD5: Minuta | AE5: Platea y Viga de Cimentación | AF5: Albañilería Confinada | AG5: Drywall / Material liviano | AH5: Losas de C°A° inclinadas | AI5: Ladrillo Pastelero hecho a mano | AJ5: Corriente Monofásica empotrada | AK5: Agua Caliente | AL5: Tuberías de agua fría, caliente y desagüe | AM5: Maciza | AN5: Madera | AO5: Batiente | AP5: Aluminio | AQ5: Templado | AR5: Batiente | AS5: Aluminio | AT5: Templado | AU5: Batiente | AV5: Altos | AW5: Melamine | AX5: Granito | AY5: Fierro Enlozado | AZ5: Flux | BA5: Color | BB5: Nacional | BC5: Con repisas y tubos | BD5: Cemento Bruñado | BE5: Tarrajeo y Pintura | BF5: Bisagras de bronce | BG5: Similar | BH5: Sierra | BI5: C | BJ5: (Obra Grande) | BK5: A basurero | BL5: Esquina | BM5: Tríplex | BN5: Niv | BO5: Nivel (En caso no hubiera Ascensor) | BQ5: Método de la Renta (O de Capitalización) | BR5: 3 | BS5: Parcial | BT5: Arequipa | BU5: Avenida: | BV5: Balcón | BW5: Ladrillo | BY5: ESTACIONAMIENTO | BZ5: Limoso
D6: Local industrial | E6: Departamento Tríplex | G6: No se encuentran inscritos | H6: Terceros | J6: Otro | K6: Decreciente | L6: Medio Bajo | M6: No Consolidado | N6: Fuerte | O6: RDA | P6: Nula | Q6: Nula | R6: Malo | S6: Escaso | T6: En construcción | U6: Bajo | V6: Adobe | W6: Bueno - Regular | AA6: Se desconoce (Visita por exteriores) | AB6: No cuenta con conexión a servicios | AC6: m3 | AD6: Predio Urbano | AE6: Muros de Contención, Platea y Viga de Cimentación | AF6: Albañilería sin Confinar | AG6: Albañilería (Ladrillo) | AH6: Calamina Metálica | AI6: Ladrillo Pastelero hecho a máquina | AJ6: Corriente Trifásica | AK6: Cocina y Agua Caliente | AL6: Sist. de Bombeo de agua potable y desagüe | AM6: Contraplacada | AN6: Otros | AO6: Levadiza | AP6: Fierro | AQ6: Semitemplado | AR6: Otros | AS6: Fierro | AT6: Semitemplado | AU6: Otros | AV6: Altos y Bajos | AW6: MDF | AX6: Mármol | AY6: Otros | AZ6: One Piece | BB6: Estándar | BC6: Con puertas contraplacadas con cajonería | BD6: Cemento Pulido | BE6: Cerámico | BF6: Tipo LGO dos golpes y picaporte | BG6: Mejor | BH6: Selva | BI6: D | BK6: A un cerro | BL6: 02 Frentes | BM6: Loft | BN6: AC | BO6: Áreas Comunes | BR6: 4 | BT6: Ayacucho | BU6: Pasaje: | BV6: Baños | BW6: Est. De Acero | BY6: DEPOSITO | BZ6: Franco Arenoso
D7: Oficina | E7: Departamento Loft | H7: Se desconoce | J7: Mixto | K7: Nulo | L7: Estrato Bajo | O7: RDMA | S7: Muy Escaso | T7: En implementación | U7: Muy Bajo | V7: Ligero / Desmontable | W7: Regular | AB7: Se especifica en cuadro detalle | AC7: Glb | AD7: Inspección Ocular | AE7: Zapatas de Concreto Armado | AF7: Sistema Mixto, Placas y Pórticos de C°A° | AG7: Albañilería (Concreto) | AH7: Fibrocemento sobre viguería metálica | AI7: Torta de Barro | AJ7: Otros | AK7: Otros | AL7: Sist. de Bombeo de agua potable y desagüe por bombeo | AM7: Otros | AO7: Otros | AP7: Otros | AQ7: Otros | AS7: Otros | AT7: Otros | AV7: No Posee | AW7: Madera | AX7: Albañilería | AZ7: Otros | BC7: Con puertas contraplacadas sin cajonería | BD7: Cerámica | BE7: Mayólica | BF7: Tipo LGO dos golpes sin picaporte | BG7: Superior | BI7: E | BK7: Interior | BL7: 03 Frentes | BN7: Eq | BO7: Equipamiento | BR7: 5 | BT7: Bagua | BU7: Carretera: | BV7: Car-port | BW7: Metálico | BY7: OFICINA | BZ7: Franco Arcilloso
D8: Taller | E8: Estacionamiento | H8: Desocupado | L8: Mixto | O8: VT | S8: No Existe | U8: Otros | V8: Noble | W8: Regular - Malo | AC8: ml | AD8: Tasación anterior | AE8: Zapatas de Concreto Simple | AF8: Adobe | AG8: Albañilería (Calcáreo) | AH8: De Madera | AI8: Sin Cobertura | AL8: Otros | AV8: Otros | AW8: Otros | AX8: Postformado | BC8: Con tubos metálicos | BD8: Cerámica Importada | BE8: Porcelanato | BI8: F | BK8: Exterior | BL8: 04 Frentes | BR8: 6 | BT8: Barranca | BU8: AA.HH.: | BV8: Cocina | BW8: Adobe/Quincha | BY8: CASA | BZ8: Franco Limoso
D9: Almacén | E9: Depósito | H9: Familiar | L9: No Aplica | O9: CV | W9: Malo | AC9: Und | AD9: Planos | AE9: Cimientos Corridos de Concreto Ciclópeo | AF9: De Madera | AG9: Placas de Concreto | AH9: Caña o Torta de Barro | AI9: Otros | AX9: Otros | BC9: De melamine con cajonería | BD9: Ladrillo Pastelero | BE9: Otros | BI9: G | BK9: No Corresponde | BL9: Pasaje | BR9: 7 | BT9: Cajamarca | BU9: Alameda: | BV9: Comedor | BW9: Madera
D10: Depósito | E10: Inmueble a Futuro | O10: CZ | W10: En Construcción | AD10: Cálculo de Alícuota | AE10: Cimientos Corridos de Concreto Simple con Zapatas | AF10: Metálica | AG10: De Piedra | AH10: Sin Techo | BC10: Solo con puertas | BD10: Lajas | BI10: H | BL10: Cerro | BT10: Callao | BU10: Asociación: | BV10: Comedor de diario | BW10: Otros
D11: Clínica | E11: Oficinas Administrativas | O11: CM | W11: En Proyecto | AD11: AT Mat.*AC U.I/AC Total | AE11: Otros | AF11: Vigas y columnas de concreto armado | AG11: Otros | AH11: Losa Aligerada y Madera Machihem. | BC11: Sin puertas | BD11: Laminado | BI11: I | BL11: Frente a Parque | BT11: Camana Casma | BU11: Autopista: | BV11: Dormitorios
D12: Hotel | E12: Agencia Bancaria | O12: I1 | AF12: Otros | AH12: Otros | BD12: Loseta Veneciana | BI12: J | BL12: Frente al Mar | BT12: Castilla - Aplao | BU12: Barrio: | BV12: Escritorio/Estudio
D13: Inmueble a Futuro | E13: Planta Industrial | O13: I2 | BD13: Loseta Vinílica | BT13: Cañete | BU13: Boulevard: | BV13: Hall de ingreso
D14: Institución Educativa | E14: Taller | O14: I3 | BD14: Madera Machihembrada | BT14: Chachapoyas | BU14: Caserío: | BV14: Jardín
D15: Colegio | E15: Almacén | O15: I4 | BD15: Mármol | BT15: Chepen | BU15: Centro Poblado: | BV15: Kitchenette
D16: Universidad | E16: Clínica | O16: E1 | BD16: Mármol Importado | BT16: Chiclayo | BU16: Malecón: | BV16: Lavandería
D17: Instituto | E17: Colegio | O17: E2 | BD17: Parquet | BT17: Chimbote | BU17: Manzana: | BV17: Oficina
D18: Local Comercial | E18: Centro Comercial | O18: E3 | BD18: Parquet de Primera | BT18: Chincha | BU18: Lote: | BV18: Otros
D19: Tienda | E19: Hotel | O19: H2 | BD19: Parquet Fino | BT19: Chota | BU19: Número: | BV19: Pasadizo de Distribución
D20: Stand Comercial | E20: Mixto | O20: H3 | BD20: Porcelanato | BT20: Cusco | BU20: Urbanización: | BV20: Patio
D21: Se desconoce | E21: Terreno | O21: H4 | BD21: Porcelanato Importado | BT21: Espinar | BU21: Bloque: | BV21: Sala
E22: Local Comercial | O22: ZTE-1 | BD22: Terrazo | BT22: Huacho | BU22: Condominio: | BV22: Sala de Capacitación
E23: Tienda | O23: ZTE-2 | BD23: Tierra Compactada | BT23: Huamachuco | BU23: Conjunto Habitacional: | BV23: Sala de estar/family room
E24: Se desconoce | O24: ZTE-3 | BD24: Otros | BT24: Huancavelica | BU24: Edificio: | BV24: Sala de Reuniones
E25: Predio Agrícola | O25: ZRP | BT25: Huancayo | BU25: Finca: | BV25: Tendal
E26: Otro | O26: OU | BT26: Huanta | BU26: Fundo: | BV26: Terraza
O27: ZRE | BT27: Huánuco | BU27: Letra: | BV27: Walking Closet
F28: Forma / Topografía | G28: COMPARACIÓN GENERAL | O28: ZRGSE | BT28: Huaral | BU28: Malecón: | BV28: Tienda
F29: Regular / Plana | G29: Peor | O29: ZMMP | BT29: Huaraz | BU29: Óvalo:
F30: Irregular / Plana | G30: Inferior | O30: LAT | BT30: Ilo | BU30: Sector:
F31: Regular / Pendiente | G31: Similar | O31: (Reglamentación Especial) | BT31: Islay - Mollendo | BU31: Unidad Vecinal:
F32: Irregular / Pendiente | G32: Mejor | BT32: Jaén | BU32: Departamento:
F33: Regular | G33: Superior | BT33: Juanjui | BU33: Estacionamiento:
F34: Plana | BT34: Juliaca | BU34: Depósito:
F35: Irregular | BT35: La Merced | BU35: Oficina:
F36: Regular | BT36: Juliaca | BU36: Depósito:
F37: Pendiente | BT37: La Merced | BU37: Oficina:
F38: Irregular | BT38: La Merced | BU38: Oficina:
BT39: Lima | BU39: Stand:
D40: GERENTE GENERAL - PERITOS | E40: PROFESIÓN | F40: REPEV - CAP O CIP | BT40: Madre De Dios | BU40: Local Comercial:
D41: RICARDO BARTHELMESS SACO | E41: INGENIERO | F41: 561-2001 | BT41: Maynas | BU41: Aires:
D42: ARTURO FERNANDO QUINTANA MACHARÉ | E42: ARQUITECTO | F42: 4111 | BT42: Moquegua
D43: MELISSA ORTIZ BENAVIDES | E43: ARQUITECTA | F43: 10823 | BT43: Moyobamba
D44: SAMUEL PEDRO RODRÍGUEZ ESPINOZA | E44: INGENIERO | F44: 50200 | BT44: Nazca
D45: LUIS ALBERTO FERNÁNDEZ TÁVARA | E45: ARQUITECTO | F45: 5457 | BT45: Otuzco
D46: EDSON FREDDY BUENO CORTEZ | E46: ARQUITECTO | F46: 5628 | BT46: Pasco
D47: RICARDO VARGAS HERNÁNDEZ | E47: INGENIERO | F47: 168932 | BT47: Pisco
D48: JORGE LUIS VERASTEGUI VEGA | E48: INGENIERO | F48: 24764 | BT48: Piura
D49: LUIS ALBERTO SOTOMAYOR | E49: ARQUITECTO | F49: 2988-2021 | BT49: Pucallpa
D50: LUIS MARTIN ARBULÚ NAVARRO | E50: ARQUITECTO | BT50: Puno
D51: GIULIANA ORIETA PINZAS ESTABRIDIS | E51: ARQUITECTA | BT51: Quillabamba
D52: JAIME DIAZ HURTADO | E52: ARQUITECTO | BT52: San Pedro
D53: ELVA VALDIVIEZO VELASCO | E53: ARQUITECTA
D54: JOHAN CRUYFF LAZARTE CAMPOS | E54: ARQUITECTO
D55: ULISES IVAN IBAÑEZ BURGA | E55: INGENIERO
D56: LUIS PALACIOS BRESSOLESE | E56: INGENIERO | BT56: Tacna
D57: JHOSEP CASTILLO ESPINOZA | E57: INGENIERO | BT57: Tarapoto
D58: DIEGO ANTONIO PONCE SANCHEZ | E58: ARQUITECTO | BT58: Tarma
D59: MARIA TERESA RAMIREZ G. | E59: ARQUITECTA | BT59: Tingo Maria
D60: ANA GISELA RODRIGUEZ ARZANI | BT60: Trujillo
BT61: Tumbes
BT62: Yurimaguas

Sheet DECLARACION JURADA
AC2: N° de Solicitud BCP | AO2: : | AP2: =+RESULTADOS!Z12 -> 0
AC3: N° de Servicio Tasadora | AO3: : | AP3: =+RESULTADOS!Z13 -> XXXX-26
AC4: Fecha de Expedición | AO4: : | AP4: =+RESULTADOS!Z14 -> 0
AC5: Fecha última de Vigencia | AO5: : | AP5: =+RESULTADOS!Z15 -> 365
A7: ANEXO
A9: DECLARACIÓN JURADA
B13: Mediante la presente VANET S.A.C., con RUC No. 20432824099, domiciliada en Av. Enrique Canaval y Moreyra N° 385, Oficina 802 - San Isidro, representada por su Gerente General Ing. Ricardo Barthelmess Saco, declara bajo juramento:
B15: 1.- | C15: Tener inscripción y habilitación vigente en el REPEV
B16: 2.- | C16: Contar con la capacidad técnica necesaria para realizar la valuación de los bienes señalados en la presente declaración.
B17: 3.- | C17: Tener conocimiento de las obligaciones y responsabilidades de los peritos en relación a los servicios de valuación de garantías de las empresas del sistema financiero, así como las infracciones y sanciones establecidas en el reglamento del REPEV.
B18: 4.- | C18: No estar incurso en las incompatibilidades señaladas en el "Reglamento de Peritos Valuadores" y demás normas complementarias, para prestar los servicios de valuación del inmueble ubicado en la:
C19: Según Ficha Registral
C20: =+'MEM. DESC. I'!J48 -> 0
C21: Según Autoavalúo
C22: =+'MEM. DESC. I'!J51 -> No se contó con la documentación correspondiente.
C23: Según Inspección Ocular
C24: =+'MEM. DESC. I'!J54 -> 0
C25: Cliente:
C26: =+'MEM. DESC. I'!J42 -> 0
B29: Lima, | E29: =+'MEM. DESC. I'!Z14 -> 0

Sheet ANEXO
AC4: Fecha última de Vigencia | AO4: : | AP4: =+RESULTADOS!Z15 -> 365
G5: N° de Solicitud BCP : | K5: =+'[11]DECLARACION JURADA'!AP7 -> 0
G6: N° de Servicio Tasadora : | K6: =+'DECLARACION JURADA'!AP3 -> XXXX-26
G7: Fecha de Expedición : | K7: =+'DECLARACION JURADA'!AP4 -> 0
G8: Fecha última de Vigencia : | K8: =+'DECLARACION JURADA'!AP5 -> 365
A10: CUESTIONARIO DE VARIABLES AMBIENTALES Y SOCIALES
A12: Zona
A14: 1 | B14: Tipo de Zonificación en donde se ubica la empresa o proyecto
C16: Zona Residencial (R) | E16: Otros Usos (OU) | G16: Minera
C17: Zona Industrial (I) | E17: Monumental (M) | G17: Zona de Recreación Pública
C18: Zonas Comerciales (C) | E18: Reserva Natural (RN) | G18: Otros. Especifique: _______________________
C19: Reglamentacion Especial (ZRE) | E19: Agrícola
A21: 1.1 | B21: Especificar si el inmueble ha sido catalogado como Patrimonio Cultural: | G21: Sí | I21: No
A23: Entorno
A25: 2 | B25: ¿Existe alguna actividad en el entorno inmediato que pueda impactar negativamente en la venta futura del bien, o en la conservación ambiental y sostenibilidad de la comunidad?
C28: Industrias Contaminantes de aire o agua | G28: Otros. Especifique: _______________________
C29: Rellenos Sanitarios / Botaderos
C30: Actividades Ilegales
C31: Delincuencia
C32: Conflictos sociales activos o latentes
C33: Deficiencia de la infraestructura de servicios públicos básicos
C34: No Existe
A36: Riesgos Ambientales Físicos
A38: Riesgos Ambientales Físicos - Agudos
A40: 2 | B40: Hidrológicos - Inundación / Desbordamiento
A42: a) | B42: ¿El inmueble se encuentra cerca de la ribera de un río (hasta 1000 metros)?
C43: Sí | E43: Especifique: _________________________________________________________
C44: No
A46: b) | B46: ¿Existe debido a su ubicación un riesgo de inundación o desbordamiento que dañe la integridad del bien y acceso al mismo?
C48: Sí | E48: Especifique: _________________________________________________________
C49: No
A51: 2.1 | B51: Geológicos/ Hidrológicos - Deslizamientos / Desprendimiento de rocas / Huaicos
A53: a) | B53: ¿El inmueble se encuentra en zona de riesgo, como por ejemplo, en la ladera/falda de un cerro o cercano (hasta 1000 metros) al cauce o quebrada de un huaico?
C54: Sí | E54: Especifique: _________________________________________________________
C55: No
A57: b) | B57: ¿Existe debido a su ubicación un riesgo de deslizamiento, desprendimiento de roca o paso de un huaico que dañe la integridad del bien y acceso al mismo?
C59: Sí | E59: Especifique: _________________________________________________________
C60: No
A62: c) | B62: Especificar adicionalmente si el inmueble tiene en su interior laderas inestables, excavaciones o rellenos.
C63: Sí | E63: Especifique: ______________________________________________________
C64: No
A66: Riesgos Ambientales Físicos - Crónico
A68: 2.2 | B68: Hidrológicos - Aumento del nivel del mar
A70: a) | B70: ¿El inmueble se encuentra cerca (hasta 1000 metros) de la orilla del mar y al nivel del mar ?
C71: Sí | E71: Especifique: _________________________________________________________
C72: No
A74: Riesgos Naturales
A76: 3 | B76: Volcánicos - Flujos de Lava y Gases
A78: a) | B78: ¿Existe debido a su ubicación un riesgo de flujos de lava y gases volcánicos que dañe la integridad del inmueble y acceso al mismo?
C80: Sí | E80: Especifique: _________________________________________________________
C81: No
A83: Características Específicas de los Inmuebles y sus Usos
A85: 4 | B85: Declaratoria de Fábrica
A87: a) | B87: ¿El inmueble cuenta con las edificaciones debidamentes inscritas en Registros Públicos?
C88: Sí Total
C89: Sí Parcial
C90: No
A92: 4.1 | B92: Materiales, daños físicos y actividades contaminantes
A94: a) | B94: ¿Durante la inspección del inmueble se observaron condiciones de trabajo insalubres, o presencia de materiales que podrían causar contaminación o problemas en la salud como por ejemplo los fabricados con asbesto; derrames de hidrocarburos que requieran de un tratamiento especial o vertidos de aguas residuales sin tratamiento al medio ambiente?
C97: Sí | E97: Especifique: _________________________________________________________
C98: No
A100: b) | B100: ¿Durante la inspección se observó un estado de conservación y mantenimiento adecuado del inmueble, junto con una construcción y distribución acorde al uso del bien que no impacte en la seguridad de los trabajadores, con equipos de prevención y lucha contra incendios adecuados, sin daños sobre la estructura y contaminación exterior?
C103: Sí | E103: Especifique: _________________________________________________________
C104: No
A106: 5 | B106: ¿El inmueble tiene vigente alguna de las siguientes certificaciones?
C107: Leed (Platinum o Gold)
C108: Breeam
C109: Edge
C110: Otros | E110: Especifique: ______________________________________________________
C111: Ninguna

Sheet FOTO
T1: N° de Solicitud BCP | Y1: : | Z1: =+RESULTADOS!Z12 -> 0
T2: N° de Servicio Tasadora | Y2: : | Z2: =+RESULTADOS!Z13 -> XXXX-26
T3: Fecha de Expedición | Y3: : | Z3: =+RESULTADOS!Z14 -> 0
T4: Fecha última de Vigencia | Y4: : | Z4: =+RESULTADOS!Z15 -> 365
A5: ANEXO - REGISTRO FOTOGRÁFICO

Sheet FOTO II
T1: N° de Solicitud BCP | Y1: : | Z1: =+FOTO!Z1 -> 0
T2: N° de Servicio Tasadora | Y2: : | Z2: =+RESULTADOS!Z13 -> XXXX-26
T3: Fecha de Expedición | Y3: : | Z3: =+RESULTADOS!Z14 -> 0
T4: Fecha última de Vigencia | Y4: : | Z4: =+RESULTADOS!Z15 -> 365
A5: ANEXO - REGISTRO FOTOGRÁFICO

Sheet FOTO III
T1: N° de Solicitud BCP | Y1: : | Z1: =+RESULTADOS!Z12 -> 0
T2: N° de Servicio Tasadora | Y2: : | Z2: =+RESULTADOS!Z13 -> XXXX-26
T3: Fecha de Expedición | Y3: : | Z3: =+RESULTADOS!Z14 -> 0
T4: Fecha última de Vigencia | Y4: : | Z4: =+RESULTADOS!Z15 -> 365
A5: ANEXO - REGISTRO FOTOGRÁFICO

Sheet FOTO IV
T1: N° de Solicitud BCP | Y1: : | Z1: =+'FOTO III'!Z1 -> 0
T2: N° de Servicio Tasadora | Y2: : | Z2: =+RESULTADOS!Z13 -> XXXX-26
T3: Fecha de Expedición | Y3: : | Z3: =+RESULTADOS!Z14 -> 0
T4: Fecha última de Vigencia | Y4: : | Z4: =+RESULTADOS!Z15 -> 365
A5: ANEXO - REGISTRO FOTOGRÁFICO

Sheet FOTO V 
T1: N° de Solicitud BCP | Y1: : | Z1: =+'FOTO III'!Z1 -> 0
T2: N° de Servicio Tasadora | Y2: : | Z2: =+RESULTADOS!Z13 -> XXXX-26
T3: Fecha de Expedición | Y3: : | Z3: =+RESULTADOS!Z14 -> 0
T4: Fecha última de Vigencia | Y4: : | Z4: =+RESULTADOS!Z15 -> 365
A5: ANEXO - REGISTRO FOTOGRÁFICO

Sheet RRPP
T1: N° de Solicitud BCP | Y1: : | Z1: =+FOTO!Z1:AD1 -> 0
T2: N° de Servicio Tasadora | Y2: : | Z2: =+FOTO!Z2:AD2 -> XXXX-26
T3: Fecha de Expedición | Y3: : | Z3: =+FOTO!Z3:AD3 -> 0
T4: Fecha última de Vigencia | Y4: : | Z4: =+FOTO!Z4:AD4 -> 365
A5: ANEXO - PARTIDA ELECTRÓNICA

Sheet RRPP (2)
T1: N° de Solicitud BCP | Y1: : | Z1: =+FOTO!Z1:AD1 -> 0
T2: N° de Servicio Tasadora | Y2: : | Z2: =+FOTO!Z2:AD2 -> XXXX-26
T3: Fecha de Expedición | Y3: : | Z3: =+FOTO!Z3:AD3 -> 0
T4: Fecha última de Vigencia | Y4: : | Z4: =+FOTO!Z4:AD4 -> 365
A5: ANEXO - PARTIDA ELECTRÓNICA

Sheet RRPP (3)
T1: N° de Solicitud BCP | Y1: : | Z1: =+FOTO!Z1:AD1 -> 0
T2: N° de Servicio Tasadora | Y2: : | Z2: =+FOTO!Z2:AD2 -> XXXX-26
T3: Fecha de Expedición | Y3: : | Z3: =+FOTO!Z3:AD3 -> 0
T4: Fecha última de Vigencia | Y4: : | Z4: =+FOTO!Z4:AD4 -> 365
A5: ANEXO - PARTIDA ELECTRÓNICA

Sheet RRPP (4)
T1: N° de Solicitud BCP | Y1: : | Z1: =+FOTO!Z1:AD1 -> 0
T2: N° de Servicio Tasadora | Y2: : | Z2: =+FOTO!Z2:AD2 -> XXXX-26
T3: Fecha de Expedición | Y3: : | Z3: =+FOTO!Z3:AD3 -> 0
T4: Fecha última de Vigencia | Y4: : | Z4: =+FOTO!Z4:AD4 -> 365
A5: ANEXO - PARTIDA ELECTRÓNICA

Sheet RRPP (5)
T1: N° de Solicitud BCP | Y1: : | Z1: =+FOTO!Z1:AD1 -> 0
T2: N° de Servicio Tasadora | Y2: : | Z2: =+FOTO!Z2:AD2 -> XXXX-26
T3: Fecha de Expedición | Y3: : | Z3: =+FOTO!Z3:AD3 -> 0
T4: Fecha última de Vigencia | Y4: : | Z4: =+FOTO!Z4:AD4 -> 365
A5: ANEXO - PARTIDA ELECTRÓNICA

Sheet RRPP (6)
T1: N° de Solicitud BCP | Y1: : | Z1: =+FOTO!Z1:AD1 -> 0
T2: N° de Servicio Tasadora | Y2: : | Z2: =+FOTO!Z2:AD2 -> XXXX-26
T3: Fecha de Expedición | Y3: : | Z3: =+FOTO!Z3:AD3 -> 0
T4: Fecha última de Vigencia | Y4: : | Z4: =+FOTO!Z4:AD4 -> 365
A5: ANEXO - PARTIDA ELECTRÓNICA

Sheet MUNICIPIO
T1: N° de Solicitud BCP | Y1: : | Z1: =+RRPP!Z1 -> 0
T2: N° de Servicio Tasadora | Y2: : | Z2: =+RRPP!Z2 -> XXXX-26
T3: Fecha de Expedición | Y3: : | Z3: =+RRPP!Z3 -> 0
T4: Fecha última de Vigencia | Y4: : | Z4: =+RRPP!Z4 -> 365
A5: ANEXO - PU DE AUTOAVALÚO

Sheet Hoja1
A1: LISTAS | BN1: TIPO DE FACTOR DE HOMOLOGACIÓN | BT1: LISTAS NO UTILIZADAS
B2: TIPO DE TASACIÓN | D2: TIPO DE INMUEBLE | E2: TIPO DE USO | F2: OBJETO Y PROPÓSITO | G2: TITULACIÓN E INSCRIPCIÓN | H2: OCUPANTE | I2: TIPO DE ZONA | J2: USO PREDOMINANTE | K2: DESARROLLO | L2: NIVEL SOCIOECONÓMICO | M2: TENDENCIA DE DESARROLLO URBANO | N2: DEMANDA / INTERÉS | O2: ZONIFICACIÓN | P2: ALTURA DE EDIFICACIÓN | Q2: VELOCIDAD DE CAMBIO | R2: ESTADO DE CONSERVACIÓN | S2: NIVEL DE EQUIPAMIENTO | T2: INFRAESTRUCTURA | U2: CALIDAD | V2: MATERIAL PREDOMINANTE | W2: ESTADO DE CONSERVACIÓN | X2: CUENTA CON ASCENSOR | Y2: ÁREAS COMUNES | Z2: OBRAS COMPLEMENTARIAS | AA2: MANTENIMIENTO | AB2: SERVICIOS | AC2: UNIDAD | AD2: OBTENCIÓN DEL ÁREA | AE2: CIMENTACIÓN | AF2: ESTRUCTURA | AG2: MUROS | AH2: TECHOS | AI2: COBERTURA | AJ2: INST. ELÉCTRICAS | AK2: INST. GAS | AL2: INST. SANITARIAS | AM2: PUERTAS | AP2: VENTANAS | AS2: MAMPARAS | AV2: MUEBLES DE COCINA | AZ2: BAÑOS | BC2: CLOSETS | BD2: PISOS | BE2: REVESTIMIENTOS | BF2: CERRAJERÍA | BG2: COMPARACIÓN GENERAL | BH2: REGIÓN DE EDIFICACIÓN | BI2: CLASE | BJ2: OBRA | BK2: VISTA | BL2: UBICACIÓN | BM2: TIPO INMUEBLE | BN2: FACTOR | BO2: CONCEPTO DEL FACTOR | BP2: SÍ / NO | BQ2: MÉTODO | BR2: CÓDIGO | BS2: DECLARATORIA DE FÁBRICA | BT2: OFICINAS REGISTRALES | BU2: IDENTIF | BV2: DISTRIBUCIÓN | BX2: Tipo de oferta | BZ2: TIPO DE SUELO
B3: Comercial | D3: Terreno | E3: Casa Habitación | F3: Determinar el Valor Comercial del inmueble para fines de Garantía Hipotecaria | G3: Partida Electrónica | H3: Propietario | I3: Urbana | J3: Vivienda | K3: Creciente | L3: Estrato Alto | M3: Consolidado Homogéneo | N3: Nula | O3: RDMB | P3: Alta | Q3: Rápida | R3: Muy Bueno | S3: Muy Abundante | T3: Completas | U3: Muy Alto | V3: Ladrillo | W3: Nuevo - Estreno | X3: Sí | Y3: Sí, especificadas en cuadro detalle | Z3: Sí, especificadas en cuadro detalle | AA3: Constante | AB3: Sí, todos | AC3: m2 | AD3: F. Reg/Part. Elect | AE3: Platea de Cimentación | AF3: Laminares Curvadas | AG3: Adobe | AH3: Losa Aligerada de C°A° Unidireccional | AI3: Tejas Cerámicas | AJ3: Sin Instalación | AK3: Sin Instalación | AL3: Sin Instalación | AM3: Tipo | AN3: Material | AO3: Sistema | AP3: Marco | AQ3: Vidrio | AR3: Sistema | AS3: Marco | AT3: Vidrio | AU3: Sistema | AV3: Tipo | AW3: Material | AX3: Tableros | AY3: Lavadero | AZ3: Tipo | BA3: Color | BB3: Grifería | BC3: Vestidos de Madera con Cajonería de Cedro | BD3: Alfombra | BE3: Tarrajeo | BF3: Cerradura tipo Yale o Similar | BG3: Peor | BH3: Lima Metropolitana y Callao | BI3: A | BJ3: (Obra Pequeña) | BK3: Al mar | BL3: Interior | BM3: Flat | BN3: C/T | BO3: AC / Terreno | BP3: Sí | BQ3: Método Directo de Costos (O de Reposición) | BR3: 1 | BS3: Tiene | BT3: Abancay | BU3: Calle: | BV3: Almacén | BW3: C°A° | BX3: Transac. | BY3: UNIDAD INMOBILIARIA | BZ3: Arenoso
B4: Hipotecaria | D4: Vivienda | E4: Departamento Flat | F4: Determinar el Valor Comercial del inmueble para fines Judiciales | G4: Ficha Registral | H4: Inquilino | I4: Rural | J4: Comercio | K4: En Renovación | L4: Medio Alto | M4: Consolidado Heterogéneo | N4: Débil | O4: RDB | P4: Media | Q4: Lenta | R4: Bueno | S4: Abundante | T4: Incompletas | U4: Alto | V4: Concreto | W4: Muy Bueno | X4: No | Y4: Escalera de acceso, recepción | Z4: No | AA4: Regularmente | AB4: Solo servicio eléctrico | AC4: ha | AD4: Copia Literal | AE4: Vigas de Cimentación | AF4: Pórticos de Concreto Armado | AG4: Pircado con mezcla de barro | AH4: Losa Aligerada de C°A° Bidireccional | AI4: Tejas de Madera | AJ4: Corriente Monofásica sin empotrar | AK4: Cocina | AL4: Tuberías de agua fría y desagüe | AM4: Apanelada | AN4: Fierro | AO4: Corrediza | AP4: Madera | AQ4: Crudo | AR4: Corrediza | AS4: Madera | AT4: Crudo | AU4: Corrediza | AV4: Bajos | AW4: Concreto | AX4: Madera | AY4: Acero | AZ4: Sifón Top Piece y/o Rapid Jet | BA4: Blanco | BB4: Importada | BC4: Con persianas o paneles | BD4: Bambú | BE4: Pintura | BF4: Alpha Vaivén | BG4: Inferior | BH4: Costa | BI4: B | BJ4: (Obra Mediana) | BK4: Al parque | BL4: Exterior | BM4: Dúplex | BN4: Vis | BO4: Vista (Exterior o Interior) | BP4: No | BQ4: Método de Comparación (O de Mercado) | BR4: 2 | BS4: No Tiene | BT4: Andahuaylas | BU4: Jirón: | BV4: Azotea | BW4: C°A°-Ladrillo | BX4: Oferta | BY4: DEPARTAMENTO | BZ4: Arcilloso
B5: Judicial | D5: Comercio | E5: Departamento Dúplex | G5: Copia Literal | H5: Inquilino Precario | J5: Industria | K5: Estacionario | L5: Estrato Medio | M5: En Proceso de Consolidación | N5: Media | O5: RDM | P5: Baja | Q5: Media | R5: Regular | S5: Suficiente | T5: No tiene | U5: Medio | V5: Concreto - Ladrillo | W5: Bueno | X5: Directo a unidad inmobiliaria | Y5: No corresponde | AA5: No cuenta con mantenimiento | AB5: Solo agua y servicio eléctrico, no desagüe | AC5: varas2 | AD5: Minuta | AE5: Platea y Viga de Cimentación | AF5: Albañilería Confinada | AG5: Drywall / Material liviano | AH5: Losas de C°A° inclinadas | AI5: Ladrillo Pastelero hecho a mano | AJ5: Corriente Monofásica empotrada | AK5: Agua Caliente | AL5: Tuberías de agua fría, caliente y desagüe | AM5: Maciza | AN5: Madera | AO5: Batiente | AP5: Aluminio | AQ5: Templado | AR5: Batiente | AS5: Aluminio | AT5: Templado | AU5: Batiente | AV5: Altos | AW5: Melamine | AX5: Granito | AY5: Fierro Enlozado | AZ5: Flux | BA5: Color | BB5: Nacional | BC5: Con repisas y tubos | BD5: Cemento Bruñado | BE5: Tarrajeo y Pintura | BF5: Bisagras de bronce | BG5: Similar | BH5: Sierra | BI5: C | BJ5: (Obra Grande) | BK5: A basurero | BL5: Esquina | BM5: Tríplex | BN5: Niv | BO5: Nivel (En caso no hubiera Ascensor) | BQ5: Método de la Renta (O de Capitalización) | BR5: 3 | BS5: Parcial | BT5: Arequipa | BU5: Avenida: | BV5: Balcón | BW5: Ladrillo | BY5: ESTACIONAMIENTO | BZ5: Limoso
D6: Local industrial | E6: Departamento Tríplex | G6: No se encuentran inscritos | H6: Terceros | J6: Otro | K6: Decreciente | L6: Medio Bajo | M6: No Consolidado | N6: Fuerte | O6: RDA | P6: Nula | Q6: Nula | R6: Malo | S6: Escaso | T6: En construcción | U6: Bajo | V6: Adobe | W6: Bueno - Regular | AA6: Se desconoce (Visita por exteriores) | AB6: No cuenta con conexión a servicios | AC6: m3 | AD6: Predio Urbano | AE6: Muros de Contención, Platea y Viga de Cimentación | AF6: Albañilería sin Confinar | AG6: Albañilería (Ladrillo) | AH6: Calamina Metálica | AI6: Ladrillo Pastelero hecho a máquina | AJ6: Corriente Trifásica | AK6: Cocina y Agua Caliente | AL6: Sist. de Bombeo de agua potable y desagüe | AM6: Contraplacada | AN6: Otros | AO6: Levadiza | AP6: Fierro | AQ6: Semitemplado | AR6: Otros | AS6: Fierro | AT6: Semitemplado | AU6: Otros | AV6: Altos y Bajos | AW6: MDF | AX6: Mármol | AY6: Otros | AZ6: One Piece | BB6: Estándar | BC6: Con puertas contraplacadas con cajonería | BD6: Cemento Pulido | BE6: Cerámico | BF6: Tipo LGO dos golpes y picaporte | BG6: Mejor | BH6: Selva | BI6: D | BK6: A un cerro | BL6: 02 Frentes | BM6: Loft | BN6: AC | BO6: Áreas Comunes | BR6: 4 | BT6: Ayacucho | BU6: Pasaje: | BV6: Baños | BW6: Est. De Acero | BY6: DEPOSITO | BZ6: Franco Arenoso
D7: Oficina | E7: Departamento Loft | H7: Se desconoce | J7: Mixto | K7: Nulo | L7: Estrato Bajo | O7: RDMA | S7: Muy Escaso | T7: En implementación | U7: Muy Bajo | V7: Ligero / Desmontable | W7: Regular | AB7: Se especifica en cuadro detalle | AC7: Glb | AD7: Inspección Ocular | AE7: Zapatas de Concreto Armado | AF7: Sistema Mixto, Placas y Pórticos de C°A° | AG7: Albañilería (Concreto) | AH7: Fibrocemento sobre viguería metálica | AI7: Torta de Barro | AJ7: Otros | AK7: Otros | AL7: Sist. de Bombeo de agua potable y desagüe por bombeo | AM7: Otros | AO7: Otros | AP7: Otros | AQ7: Otros | AS7: Otros | AT7: Otros | AV7: No Posee | AW7: Madera | AX7: Albañilería | AZ7: Otros | BC7: Con puertas contraplacadas sin cajonería | BD7: Cerámica | BE7: Mayólica | BF7: Tipo LGO dos golpes sin picaporte | BG7: Superior | BI7: E | BK7: Interior | BL7: 03 Frentes | BN7: Eq | BO7: Equipamiento | BR7: 5 | BT7: Bagua | BU7: Carretera: | BV7: Car-port | BW7: Metálico | BY7: OFICINA | BZ7: Franco Arcilloso
D8: Taller | E8: Estacionamiento | H8: Desocupado | L8: Mixto | O8: VT | S8: No Existe | U8: Otros | V8: Noble | W8: Regular - Malo | AC8: ml | AD8: Tasación anterior | AE8: Zapatas de Concreto Simple | AF8: Adobe | AG8: Albañilería (Calcáreo) | AH8: De Madera | AI8: Sin Cobertura | AL8: Otros | AV8: Otros | AW8: Otros | AX8: Postformado | BC8: Con tubos metálicos | BD8: Cerámica Importada | BE8: Porcelanato | BI8: F | BK8: Exterior | BL8: 04 Frentes | BR8: 6 | BT8: Barranca | BU8: AA.HH.: | BV8: Cocina | BW8: Adobe/Quincha | BY8: CASA | BZ8: Franco Limoso
D9: Almacén | E9: Depósito | H9: Familiar | L9: No Aplica | O9: CV | W9: Malo | AC9: Und | AD9: Planos | AE9: Cimientos Corridos de Concreto Ciclópeo | AF9: De Madera | AG9: Placas de Concreto | AH9: Caña o Torta de Barro | AI9: Otros | AX9: Otros | BC9: De melamine con cajonería | BD9: Ladrillo Pastelero | BE9: Otros | BI9: G | BK9: No Corresponde | BL9: Pasaje | BR9: 7 | BT9: Cajamarca | BU9: Alameda: | BV9: Comedor | BW9: Madera
D10: Depósito | E10: Inmueble a Futuro | O10: CZ | W10: En Construcción | AD10: Cálculo de Alícuota | AE10: Cimientos Corridos de Concreto Simple con Zapatas | AF10: Metálica | AG10: De Piedra | AH10: Sin Techo | BC10: Solo con puertas | BD10: Lajas | BI10: H | BL10: Cerro | BT10: Callao | BU10: Asociación: | BV10: Comedor de diario | BW10: Otros
D11: Clínica | E11: Oficinas Administrativas | O11: CM | W11: En Proyecto | AD11: AT Mat.*AC U.I/AC Total | AE11: Otros | AF11: Vigas y columnas de concreto armado | AG11: Otros | AH11: Losa Aligerada y Madera Machihem. | BC11: Sin puertas | BD11: Laminado | BI11: I | BL11: Frente a Parque | BT11: Camana Casma | BU11: Autopista: | BV11: Dormitorios
D12: Hotel | E12: Agencia Bancaria | O12: I1 | AF12: Otros | AH12: Otros | BD12: Loseta Veneciana | BI12: J | BL12: Frente al Mar | BT12: Castilla - Aplao | BU12: Barrio: | BV12: Escritorio/Estudio
D13: Inmueble a Futuro | E13: Planta Industrial | O13: I2 | BD13: Loseta Vinílica | BT13: Cañete | BU13: Boulevard: | BV13: Hall de ingreso
D14: Institución Educativa | E14: Taller | O14: I3 | BD14: Madera Machihembrada | BT14: Chachapoyas | BU14: Caserío: | BV14: Jardín
D15: Colegio | E15: Almacén | O15: I4 | BD15: Mármol | BT15: Chepen | BU15: Centro Poblado: | BV15: Kitchenette
D16: Universidad | E16: Clínica | O16: E1 | BD16: Mármol Importado | BT16: Chiclayo | BU16: Malecón: | BV16: Lavandería
D17: Instituto | E17: Colegio | O17: E2 | BD17: Parquet | BT17: Chimbote | BU17: Manzana: | BV17: Oficina
D18: Local Comercial | E18: Centro Comercial | O18: E3 | BD18: Parquet de Primera | BT18: Chincha | BU18: Lote: | BV18: Otros
D19: Tienda | E19: Hotel | O19: H2 | BD19: Parquet Fino | BT19: Chota | BU19: Número: | BV19: Pasadizo de Distribución
D20: Stand Comercial | E20: Mixto | O20: H3 | BD20: Porcelanato | BT20: Cusco | BU20: Urbanización: | BV20: Patio
D21: Se desconoce | E21: Terreno | O21: H4 | BD21: Porcelanato Importado | BT21: Espinar | BU21: Bloque: | BV21: Sala
E22: Local Comercial | O22: ZTE-1 | BD22: Terrazo | BT22: Huacho | BU22: Condominio: | BV22: Sala de Capacitación
E23: Tienda | O23: ZTE-2 | BD23: Tierra Compactada | BT23: Huamachuco | BU23: Conjunto Habitacional: | BV23: Sala de estar/family room
E24: Se desconoce | O24: ZTE-3 | BD24: Otros | BT24: Huancavelica | BU24: Edificio: | BV24: Sala de Reuniones
E25: Predio Agrícola | O25: ZRP | BT25: Huancayo | BU25: Finca: | BV25: Tendal
E26: Otro | O26: OU | BT26: Huanta | BU26: Fundo: | BV26: Terraza
O27: ZRE | BT27: Huánuco | BU27: Letra: | BV27: Walking Closet
F28: Forma / Topografía | G28: COMPARACIÓN GENERAL | O28: ZRGSE | BT28: Huaral | BU28: Malecón: | BV28: Tienda
F29: Regular / Plana | G29: Peor | O29: ZMMP | BT29: Huaraz | BU29: Óvalo:
F30: Irregular / Plana | G30: Inferior | O30: LAT | BT30: Ilo | BU30: Sector:
F31: Regular / Pendiente | G31: Similar | O31: (Reglamentación Especial) | BT31: Islay - Mollendo | BU31: Unidad Vecinal:
F32: Irregular / Pendiente | G32: Mejor | BT32: Jaén | BU32: Departamento:
F33: Regular | G33: Superior | BT33: Juanjui | BU33: Estacionamiento:
F34: Plana | BT34: Juliaca | BU34: Depósito:
F35: Irregular | BT35: La Merced | BU35: Oficina:
F36: Regular | BT36: Lima | BU36: Stand:
F37: Pendiente | BT37: Madre De Dios | BU37: Local Comercial:
F38: Irregular | BT38: Maynas | BU38: Aires:
BT39: Moquegua
BT40: Moyobamba
D41: GERENTE GENERAL - PERITOS | E41: PROFESIÓN | F41: REPEV - CAP O CIP | BT41: Nazca
D42: RICARDO BARTHELMESS SACO | E42: INGENIERO | F42: 561-2001 | BT42: Otuzco
D43: ARTURO FERNANDO QUINTANA MACHARÉ | E43: ARQUITECTO | F43: 4111 | BT43: Pasco
D44: MELISSA ORTIZ BENAVIDES | E44: ARQUITECTA | F44: 10823 | BT44: Pisco
D45: SAMUEL PEDRO RODRÍGUEZ ESPINOZA | E45: INGENIERO | F45: 50200 | BT45: Piura
D46: LUIS ALBERTO FERNÁNDEZ TÁVARA | E46: ARQUITECTO | F46: 5457 | BT46: Pucallpa
D47: EDSON FREDDY BUENO CORTEZ | E47: ARQUITECTO | F47: 5628 | BT47: Puno
D48: RICARDO VARGAS HERNÁNDEZ | E48: INGENIERO | F48: 168932 | BT48: Quillabamba
D49: LUIS MARTIN ARBULÚ NAVARRO | E49: ARQUITECTO | BT49: San Pedro
D50: GIULIANA ORIETA PINZAS ESTABRIDIS | E50: ARQUITECTA | BT50: Satipo
D51: JAIME DIAZ HURTADO | E51: ARQUITECTO | BT51: Sicuani
D52: ELVA VALDIVIEZO VELAZCO | E52: ARQUITECTA | BT52: Sullana
D53: JOHAN CRUYFF LAZARTE CAMPOS | E53: ARQUITECTO | BT53: Tacna
D54: ALVARO JOSE PRIVAT ZIMMERMANN | E54: ARQUITECTO | BT54: Tarapoto
D55: CARLOS ALONSO HERRERA RIOS | E55: INGENIERO | BT55: Tarma
BT56: Tingo Maria
BT57: Trujillo
BT58: Tumbes
BT59: Yurimaguas

Sheet MUNICIPIO (2)
T1: N° de Solicitud BCP | Y1: : | Z1: =+RRPP!Z1 -> 0
T2: N° de Servicio Tasadora | Y2: : | Z2: =+RRPP!Z2 -> XXXX-26
T3: Fecha de Expedición | Y3: : | Z3: =+RRPP!Z3 -> 0
T4: Fecha última de Vigencia | Y4: : | Z4: =+RRPP!Z4 -> 365
A5: ANEXO - PU DE AUTOAVALÚO

Sheet PLANO DE UBICACION
T1: N° de Solicitud BCP | Y1: : | Z1: =+RRPP!Z1 -> 0
T2: N° de Servicio Tasadora | Y2: : | Z2: =+RRPP!Z2 -> XXXX-26
T3: Fecha de Expedición | Y3: : | Z3: =+RRPP!Z3 -> 0
T4: Fecha última de Vigencia | Y4: : | Z4: =+RRPP!Z4 -> 365
A5: ANEXO - PLANO DE UBICACIÓN

Sheet PLANO DE ZONIFICACION
T1: N° de Solicitud BCP | Y1: : | Z1: =+RRPP!Z1 -> 0
T2: N° de Servicio Tasadora | Y2: : | Z2: =+RRPP!Z2 -> XXXX-26
T3: Fecha de Expedición | Y3: : | Z3: =+RRPP!Z3 -> 0
T4: Fecha última de Vigencia | Y4: : | Z4: =+RRPP!Z4 -> 365
A5: ANEXO - PLANO DE ZONIFICACION

Sheet SUSTENTO DE UBICACION
T1: N° de Solicitud BCP | Y1: : | Z1: =+RRPP!Z1 -> 0 | AX1: N° de Solicitud BCP | BC1: : | BD1: =+RRPP!BD1 -> 0 | CB1: N° de Solicitud BCP | CG1: : | CH1: =+RRPP!CH1 -> 0 | DF1: N° de Solicitud BCP | DK1: : | DL1: =+RRPP!DL1 -> 0
T2: N° de Servicio Tasadora | Y2: : | Z2: =+RRPP!Z2 -> XXXX-26 | AX2: N° de Servicio Tasadora | BC2: : | BD2: =+Z2 -> XXXX-26 | CB2: N° de Servicio Tasadora | CG2: : | CH2: =+BD2 -> XXXX-26 | DF2: N° de Servicio Tasadora | DK2: : | DL2: =+CH2 -> XXXX-26
T3: Fecha de Expedición | Y3: : | Z3: =+RRPP!Z3 -> 0 | AX3: Fecha de Expedición | BC3: : | BD3: =+Z3 -> 0 | CB3: Fecha de Expedición | CG3: : | CH3: =+BD3 -> 0 | DF3: Fecha de Expedición | DK3: : | DL3: =+CH3 -> 0
T4: Fecha última de Vigencia | Y4: : | Z4: =+RRPP!Z4 -> 365 | AX4: Fecha última de Vigencia | BC4: : | BD4: =+Z4 -> 365 | CB4: Fecha última de Vigencia | CG4: : | CH4: =+BD4 -> 365 | DF4: Fecha última de Vigencia | DK4: : | DL4: =+CH4 -> 365
A5: ANEXO - PLANO BGR | AE5: ANEXO - PLANO DE VISOR GEOLLACTA | BI5: ANEXO - GOOGLE EARTH CON MEDICION | CM5: ANEXO - PLANO ÁREA DE TERRENO

Sheet MUESTRAS
T1: N° de Solicitud BCP | Y1: : | Z1: =+'SUSTENTO DE UBICACION'!Z1 -> 0 | AX1: N° de Solicitud BCP | BC1: : | BD1: =+Z1 -> 0
T2: N° de Servicio Tasadora | Y2: : | Z2: =+RRPP!Z2 -> XXXX-26 | AX2: N° de Servicio Tasadora | BC2: : | BD2: =+Z2 -> XXXX-26
T3: Fecha de Expedición | Y3: : | Z3: =+RRPP!Z3 -> 0 | AX3: Fecha de Expedición | BC3: : | BD3: =+RRPP!BD3 -> 0
T4: Fecha última de Vigencia | Y4: : | Z4: =+RRPP!Z4 -> 365 | AX4: Fecha última de Vigencia | BC4: : | BD4: =+RRPP!BD4 -> 0
A5: ANEXO - MUESTRAS TERRENOS | AE5: ANEXO - MUESTRAS DEPARTAMENTOS

Sheet ANEXO MIC
A1: HOJA RESUMEN TASACIÓN - MIC
A2: DIRECCIÓN SEGÚN COPIA LITERAL | D2: =+'MEM. DESC. I'!J48 -> 0
A3: DIRECCIÓN SEGÚN PU | D3: =+'MEM. DESC. I'!J51 -> No se contó con la documentación correspondiente.
A4: DIRECCIÓN DE LA INSPECCIÓN OCULAR | D4: =+'MEM. DESC. I'!J54 -> 0
A5: DISTRITO - PROVINCIA - DEPARTAMENTO | D5: =+'HR-COMÚN TERMINADO'!F47 -> 0 | F5: =+'HR-COMÚN TERMINADO'!O47 -> 0 | H5: =+'HR-COMÚN TERMINADO'!Y47 -> 0
A7: FECHA DE EXPEDICION DE TASACIÓN | D7: =+'HR-COMÚN TERMINADO'!Z14 -> 0 | F7: TICA | G7: =+'HR-COMÚN TERMINADO'!J104 -> 3.48
C9: DÓLARES | D9: SOLES | H9: DÓLARES | I9: SOLES
A10: VALOR COMERCIAL | C10: =+'HR-COMÚN TERMINADO'!M94 -> 0 | D10: =+'HR-COMÚN TERMINADO'!M95 -> 0 | F10: VALOR DEL TERRENO | H10: =+REPOSICIÓN!X25 -> 0 | I10: =+H10*G7 -> 0
A11: VALOR DE REALIZACION | C11: =+'HR-COMÚN TERMINADO'!M96 -> 0 | D11: =+'HR-COMÚN TERMINADO'!M97 -> 0 | F11: VALOR DE RECONSTRUCCION | H11: =+'HR-COMÚN TERMINADO'!M100 -> 0 | I11: =H11*G7 -> 0
A13: MATERIAL DE CONSTRUCCIÓN | C13: =+'HR-COMÚN TERMINADO'!H70 -> 0 | F13: ESTADO DE CONSERVACION | H13: =+'MEM. DESC. I'!X99 -> 0
A14: AREA TERRENO (m2) | C14: =+'MEM. DESC. II'!S44 -> 0 | F14: AREA EDIFICACION (m2) | H14: =+'MEM. DESC. II'!K56+'MEM. DESC. II'!K65 -> 0
A16: USO DE INMUEBLE | C16: % | D16: TIPO | F16: PERITO TASADOR | G16: ….. / Ricardo Barthelmess Saco
C17: =+'HR-COMÚN TERMINADO'!L55 -> 100 | D17: =+'HR-COMÚN TERMINADO'!F55 -> Departamento Flat
C18: =+'HR-COMÚN TERMINADO'!L56 -> 0 | D18: =+'HR-COMÚN TERMINADO'!F56 -> 0
C19: =+'HR-COMÚN TERMINADO'!L57 -> 0 | D19: =+'HR-COMÚN TERMINADO'!F57 -> 0
C20: =+'[1]MEM. DESC. I'!AB83 -> 0 | D20: =+'[1]MEM. DESC. I'!U83 -> 0
A22: OBSERVACIONES GENERALES | D22: =+'HR-COMÚN TERMINADO'!F75 -> 0
A42: DESCRIPCION Y DISTRIBUCION DEL INMUEBLE | D42: =+'MEM. DESC. I'!J108 -> Descripción Distribución: Primer piso: Segundo piso: Tercer piso:

Sheet VUE
A1: VALORES UNITARIOS OFICIALES DE EDIFICACION
A3: AÑO: | B3: 2015 | D3: FECHA: | E3: 41943 | H3: NORMA: | I3: R.M. N° 278-2013-Vivienda
A5: FACTOR DE OFICIALIZACIÓN: | F5: 0.68 | H5: RANGO DE LA REGIÓN SELECCIONADA: | M5: Lima
A6: IMPUESTO GENERAL A LAS VENTAS: | F6: 1.18 | H6: FACTOR DE AJUSTE RESULTANTE: | M6: =IGV*F7/F5 -> 1.8220588
A7: FACTOR DE INCREMENTO POR ALTURA: | F7: =IF(NoPisos<6, 1,1.05) -> 1.05
A9: LIMA METROPOLITANA Y CALLAO
B10: 1 | C10: 2 | D10: 3 | E10: 4 | F10: 5 | G10: 6 | H10: 7 | I10: 1 | J10: 2 | K10: 3 | L10: 4 | M10: 5 | N10: 6 | O10: 7
A11: A | B11: 457.46 | C11: 277.84 | D11: 245.37 | E11: 248.26 | F11: 267.59 | G11: 90.3 | H11: 265.38 | I11: Estructuras laminadas curvadas de concreto armado que incluyen en una sola armadura la cimentación y el techo (para este caso no se considera el componente N° 2) | J11: Losa o aligerado de concreto armado con luces mayores de 6m con sobrecarga mayor a 300 Kg/m2 | K11: Mármol importado, piedras naturales, porcelanato | L11: Aluminio pesado con perfiles especiales, madera fina ornamental (caoba, cedro o pino selecto), vidrio insulado | M11: Mármol importado, madera fina (caoba o similar), baldosa acústica en techo o similar | N11: Baños completos de lujo importados con enchape fino (mármol o similar) | O11: Aire acondicionado, iluminación especial, ventilación forzada, sistema hidroneumático, agua caliente y fría, intercomunicador, alarmas, ascensor, sistema de bombeo de agua y desagüe, teléfono, gas natural
A12: B | B12: 294.94 | C12: 181.27 | D12: 147.07 | E12: 130.86 | F12: 202.74 | G12: 68.66 | H12: 193.76 | I12: Columnas, vigas y/o placas de concreto armado y/o metálicas | J12: Aligerados o losas de concreto armado inclinadas | K12: Mármol nacional o reconstituido, parquet fino (olivo, chonta o similar), cerámica importada, madera fina | L12: Aluminio o madera fina (caoba o similar) de diseño especial, vidrio tratado polarizado y curvado, laminado o templado | M12: Mármol nacional, madera fina (caoba o similar), enchapes en techos | N12: Baños completos importados con mayólica o cerámico decorativo importado | O12: Sistema de bombeo de agua potable, ascensor, teléfono, agua caliente y fría, gas natural
A13: C | B13: 203.02 | C13: 149.76 | D13: 96.79 | E13: 84.58 | F13: 150.4 | G13: 47.63 | H13: 122.23 | I13: Placas de concreto e=10 a 15cm, albañilería armada, ladrillo o similar con columnas y vigas de amarre de concreto armado | J13: Aligerado o losas de concreto armado horizontales | K13: Madera fina machihembrada, terrazo | L13: Aluminio o madera fina (caoba o similar), vidrio tratado polarizado, laminado o templado | M13: Superficie caravista obtenida mediante encofrado especial, enchape en techos | N13: Baños completos nacionales con mayólica o cerámico nacional de color | O13: Sistema de bombeo de agua potable, teléfono, agua caliente y fría, gas natural
A14: D | B14: 196.33 | C14: 95.06 | D14: 85.38 | E14: 74.09 | F14: 115.4 | G14: 25.41 | H14: 77.22 | I14: Ladrillo o similar sin elementos de concreto armado, drywall o similar, incluye techo (para este caso no se considera el componente N° 2) | J14: Calamina metálica, fibrocemento sobre viguería metálica | K14: Parquet de primera, laja, cerámica nacional, loseta veneciana 40x40, piso laminado | L14: Ventanas de aluminio, puertas de madera selecta, vidrio tratado transparente | M14: Enchape de madera o laminados, piedra o material vitrificado | N14: Baños completos nacionales blancos con mayólica blanca | O14: Agua fría, agua caliente, corriente trifásica, teléfono, gas natural
A15: E | B15: 138.22 | C15: 35.44 | D15: 57.21 | E15: 63.39 | F15: 79.39 | G15: 14.94 | H15: 56.08 | I15: Adobe, tapial o quincha | J15: Madera selecta tratada con material impermeabilizante | K15: Parquet de segunda, loseta veneciana 30x30, lajas de cemento con canto rodado | L15: Ventanas de fierro, puertas de madera selecta (caoba o similar), vidrio simple transparente | M15: Superficie de ladrillo caravista | N15: Baños con mayólica blanca parcial | O15: Agua fría, agua caliente, corriente monofásica, teléfono, gas natural
A16: F | B16: 104.09 | C16: 19.49 | D16: 39.07 | E16: 47.59 | F16: 55.97 | G16: 11.13 | H16: 32.08 | I16: Madera (estoraque, pumaquiro, huayruro, machinga, catahua amarilla, copaiba, diablo fuerte, tornillo o similares), drywall o similar sin techo | J16: Calamina metálica, fibrocemento o tejas sobre tijerales o viguería de madera corriente | K16: Loseta corriente, canto rodado, alfombra | L16: Ventanas de fierro o aluminio industrial, puertas contraplacadas de madera (cedro o similar), puertas en material MDF o HDF, vidrio simple transparente | M16: Tarrajeo frotachado y/o yeso moldurado, pintura lavable o barnizado sobre madera | N16: Baños blancos sin mayólica | O16: Agua fría, corriente monofásica, teléfono, gas natural
A17: G | B17: 61.33 | C17: 13.4 | D17: 34.48 | E17: 25.71 | F17: 45.89 | G17: 7.65 | H17: 29.76 | I17: Pircado con mezcla de barro | J17: Madera rústica o caña con torta de barro | K17: Loseta vinílica, cemento bruñado coloreado, tapizón | L17: Madera corriente con marcos en puertas y ventanas de PVC o madera corriente | M17: Estucado de yeso y/o barro, pintura al temple o agua | N17: Sanitarios básicos de losa de segunda, fierro fundido o granito | O17: Agua fría, corriente monofásica, teléfono
A18: H | B18: 0 | C18: 0 | D18: 21.57 | E18: 12.85 | F18: 18.36 | G18: 0 | H18: 16.07 | I18: (No corresponde) | J18: Sin techo | K18: Cemento pulido, ladrillo corriente, entablado corriente | L18: Madera rústica | M18: Pintado en ladrillo rústico, placa de concreto o similar | N18: Sin aparatos sanitarios | O18: Agua fría, corriente monofásica sin empotrar
A19: I | B19: 0 | C19: 0 | D19: 4.31 | E19: 0 | F19: 0 | G19: 0 | H19: 0 | I19: (No corresponde) | J19: (No corresponde) | K19: Tierra compactada | L19: Sin puertas ni ventanas | M19: Sin revestimientos, en ladrillo, adobe o similar | N19: (No corresponde) | O19: Sin instalación eléctricia ni sanitaria
A20: J | B20: 0 | C20: 0 | D20: 0 | E20: 0 | F20: 0 | G20: 0 | H20: 0 | I20: (No corresponde) | J20: (No corresponde) | K20: (No corresponde) | L20: (No corresponde) | M20: (No corresponde) | N20: (No corresponde) | O20: (No corresponde)
A22: COSTA
B23: 1 | C23: 2 | D23: 3 | E23: 4 | F23: 5 | G23: 6 | H23: 7 | I23: 1 | J23: 2 | K23: 3 | L23: 4 | M23: 5 | N23: 6 | O23: 7
A24: A | B24: 452.88 | C24: 275.06 | D24: 242.91 | E24: 245.78 | F24: 264.91 | G24: 89.39 | H24: 257.97 | I24: Estructuras laminadas curvadas de concreto armado que incluyen en una sola armadura la cimentación y el techo (para este caso no se considera el componente N° 2) | J24: Losa o aligerado de concreto armado con luces mayores de 6m con sobrecarga mayor a 300 Kg/m2 | K24: Mármol importado, piedras naturales, porcelanato | L24: Aluminio pesado con perfiles especiales, madera fina ornamental (caoba, cedro o pino selecto), vidrio insulado | M24: Mármol importado, madera fina (caoba o similar), baldosa acústica en techo o similar | N24: Baños completos de lujo importados con enchape fino (mármol o similar) | O24: Aire acondicionado, iluminación especial, ventilación forzada, sistema hidroneumático, agua caliente y fría, intercomunicador, alarmas, ascensor, sistema de bombeo de agua y desagüe, teléfono
A25: B | B25: 291.99 | C25: 179.46 | D25: 145.6 | E25: 129.55 | F25: 200.71 | G25: 67.97 | H25: 187.08 | I25: Columnas, vigas y/o placas de concreto armado y/o metálicas | J25: Aligerados o losas de concreto armado inclinadas | K25: Mármol nacional o reconstituido, parquet fino (olivo, chonta o similar), cerámica importada, madera fina | L25: Aluminio o madera fina (caoba o similar) de diseño especial, vidrio tratado polarizado y curvado, laminado o templado | M25: Mármol nacional, madera fina (caoba o similar), enchapes en techos | N25: Baños completos importados con mayólica o cerámico decorativo importado | O25: Sistema de bombeo de agua potable, ascensor, teléfono, agua caliente y fría
A26: C | B26: 200.99 | C26: 148.26 | D26: 95.83 | E26: 83.73 | F26: 148.9 | G26: 47.15 | H26: 116.41 | I26: Placas de concreto e=10 a 15cm, albañilería armada, ladrillo o similar con columnas y vigas de amarre de concreto armado | J26: Aligerado o losas de concreto armado horizontales | K26: Madera fina machihembrada, terrazo | L26: Aluminio o madera fina (caoba o similar), vidrio tratado polarizado, laminado o templado | M26: Superficie caravista obtenida mediante encofrado especial, enchape en techos | N26: Baños completos nacionales con mayólica o cerámico nacional de color | O26: Sistema de bombeo de agua potable, teléfono, agua caliente y fría
A27: D | B27: 194.37 | C27: 94.11 | D27: 84.53 | E27: 73.35 | F27: 114.24 | G27: 25.16 | H27: 73.68 | I27: Ladrillo o similar sin elementos de concreto armado, drywall o similar, incluye techo (para este caso no se considera el componente N° 2) | J27: Calamina metálica, fibrocemento sobre viguería metálica | K27: Parquet de primera, laja, cerámica nacional, loseta veneciana 40x40, piso laminado | L27: Ventanas de aluminio, puertas de madera selecta, vidrio tratado transparente | M27: Enchape de madera o laminados, piedra o material vitrificado | N27: Baños completos nacionales blancos con mayólica blanca | O27: Agua fría, agua caliente, corriente trifásica, teléfono
A28: E | B28: 136.83 | C28: 35.08 | D28: 56.64 | E28: 62.76 | F28: 78.6 | G28: 14.79 | H28: 53.56 | I28: Adobe, tapial o quincha | J28: Madera selecta tratada con material impermeabilizante | K28: Parquet de segunda, loseta veneciana 30x30, lajas de cemento con canto rodado | L28: Ventanas de fierro, puertas de madera selecta (caoba o similar), vidrio simple transparente | M28: Superficie de ladrillo caravista | N28: Baños con mayólica blanca parcial | O28: Agua fría, agua caliente, corriente monofásica, teléfono
A29: F | B29: 103.05 | C29: 19.3 | D29: 38.68 | E29: 47.11 | F29: 55.41 | G29: 11.02 | H29: 29.46 | I29: Madera (estoraque, pumaquiro, huayruro, machinga, catahua amarilla, copaiba, diablo fuerte, tornillo o similares), drywall o similar sin techo | J29: Calamina metálica, fibrocemento o tejas sobre tijerales o viguería de madera corriente | K29: Loseta corriente, canto rodado, alfombra | L29: Ventanas de fierro o aluminio industrial, puertas contraplacadas de madera (cedro o similar), puertas en material MDF o HDF, vidrio simple transparente | M29: Tarrajeo frotachado y/o yeso moldurado, pintura lavable o barnizado sobre madera | N29: Baños blancos sin mayólica | O29: Agua fría, corriente monofásica, teléfono
A30: G | B30: 60.72 | C30: 13.26 | D30: 34.13 | E30: 25.45 | F30: 45.43 | G30: 7.57 | H30: 15.91 | I30: Pircado con mezcla de barro | J30: Madera rústica o caña con torta de barro | K30: Loseta vinílica, cemento bruñado coloreado, tapizón | L30: Madera corriente con marcos en puertas y ventanas de PVC o madera corriente | M30: Estucado de yeso y/o barro, pintura al temple o agua | N30: Sanitarios básicos de losa de segunda, fierro fundido o granito | O30: Agua fría, corriente monofásica sin empotrar
A31: H | B31: 0 | C31: 0 | D31: 21.36 | E31: 12.72 | F31: 18.17 | G31: 0 | H31: 0 | I31: (No corresponde) | J31: Sin techo | K31: Cemento pulido, ladrillo corriente, entablado corriente | L31: Madera rústica | M31: Pintado en ladrillo rústico, placa de concreto o similar | N31: Sin aparatos sanitarios | O31: Sin instalación eléctricia ni sanitaria
A32: I | B32: 0 | C32: 0 | D32: 4.27 | E32: 0 | F32: 0 | G32: 0 | H32: 0 | I32: (No corresponde) | J32: (No corresponde) | K32: Tierra compactada | L32: Sin puertas ni ventanas | M32: Sin revestimientos, en ladrillo, adobe o similar | N32: (No corresponde) | O32: (No corresponde)
A33: J | B33: 0 | C33: 0 | D33: 0 | E33: 0 | F33: 0 | G33: 0 | H33: 0 | I33: (No corresponde) | J33: (No corresponde) | K33: (No corresponde) | L33: (No corresponde) | M33: (No corresponde) | N33: (No corresponde) | O33: (No corresponde)
A35: SIERRA
B36: 1 | C36: 2 | D36: 3 | E36: 4 | F36: 5 | G36: 6 | H36: 7 | I36: 1 | J36: 2 | K36: 3 | L36: 4 | M36: 5 | N36: 6 | O36: 7
A37: A | B37: 504.49 | C37: 262.32 | D37: 186.13 | E37: 199.11 | F37: 251.26 | G37: 89.11 | H37: 317.54 | I37: Estructuras laminadas curvadas de concreto armado que incluyen en una sola armadura la cimentación y el techo (para este caso no se considera el componente N° 2) | J37: Losa o aligerado de concreto armado con luces mayores de 6m con sobrecarga mayor a 300 Kg/m2 | K37: Mármol importado, piedras naturales, porcelanato | L37: Aluminio pesado con perfiles especiales, madera fina ornamental (caoba, cedro o pino selecto), vidrio insulado | M37: Mármol importado, madera fina (caoba o similar), baldosa acústica en techo o similar | N37: Baños completos de lujo importados con enchape fino (mármol o similar) | O37: Aire acondicionado, iluminación especial, ventilación forzada, sistema hidroneumático, agua caliente y fría, intercomunicador, alarmas, ascensor, sistema de bombeo de agua y desagüe, teléfono
A38: B | B38: 300.14 | C38: 180.34 | D38: 155.2 | E38: 176.2 | F38: 200.68 | G38: 63.66 | H38: 186.77 | I38: Columnas, vigas y/o placas de concreto armado y/o metálicas | J38: Aligerados o losas de concreto armado inclinadas | K38: Mármol nacional o reconstituido, parquet fino (olivo, chonta o similar), cerámica importada, madera fina | L38: Aluminio o madera fina (caoba o similar) de diseño especial, vidrio tratado polarizado y curvado, laminado o templado | M38: Mármol nacional, madera fina (caoba o similar), enchapes en techos | N38: Baños completos importados con mayólica o cerámico decorativo importado | O38: Sistema de bombeo de agua potable, ascensor, teléfono, agua caliente y fría
A39: C | B39: 217.76 | C39: 126.2 | D39: 100.43 | E39: 128.56 | F39: 166.09 | G39: 41.56 | H39: 138.97 | I39: Placas de concreto e=10 a 15cm, albañilería armada, ladrillo o similar con columnas y vigas de amarre de concreto armado | J39: Aligerado o losas de concreto armado horizontales | K39: Madera fina machihembrada, terrazo | L39: Aluminio o madera fina (caoba o similar), vidrio tratado polarizado, laminado o templado | M39: Superficie caravista obtenida mediante encofrado especial, enchape en techos | N39: Baños completos nacionales con mayólica o cerámico nacional de color | O39: Sistema de bombeo de agua potable, teléfono, agua caliente y fría
A40: D | B40: 201.14 | C40: 85.43 | D40: 82.35 | E40: 75.4 | F40: 127.04 | G40: 25.43 | H40: 78.75 | I40: Ladrillo o similar sin elementos de concreto armado, drywall o similar, incluye techo (para este caso no se considera el componente N° 2) | J40: Calamina metálica, fibrocemento sobre viguería metálica | K40: Parquet de primera, laja, cerámica nacional, loseta veneciana 40x40, piso laminado | L40: Ventanas de aluminio, puertas de madera selecta, vidrio tratado transparente | M40: Enchape de madera o laminados, piedra o material vitrificado | N40: Baños completos nacionales blancos con mayólica blanca | O40: Agua fría, agua caliente, corriente trifásica, teléfono
A41: E | B41: 157.9 | C41: 39.22 | D41: 68.11 | E41: 57.6 | F41: 105.69 | G41: 12.47 | H41: 43.82 | I41: Adobe, tapial o quincha | J41: Madera selecta tratada con material impermeabilizante | K41: Parquet de segunda, loseta veneciana 30x30, lajas de cemento con canto rodado | L41: Ventanas de fierro, puertas de madera selecta (caoba o similar), vidrio simple transparente | M41: Superficie de ladrillo caravista | N41: Baños con mayólica blanca parcial | O41: Agua fría, agua caliente, corriente monofásica, teléfono
A42: F | B42: 98.46 | C42: 31.34 | D42: 55.62 | E42: 44.54 | F42: 63.02 | G42: 10.6 | H42: 28.49 | I42: Madera (estoraque, pumaquiro, huayruro, machinga, catahua amarilla, copaiba, diablo fuerte, tornillo o similares), drywall o similar sin techo | J42: Calamina metálica, fibrocemento o tejas sobre tijerales o viguería de madera corriente | K42: Loseta corriente, canto rodado, alfombra | L42: Ventanas de fierro o aluminio industrial, puertas contraplacadas de madera (cedro o similar), puertas en material MDF o HDF, vidrio simple transparente | M42: Tarrajeo frotachado y/o yeso moldurado, pintura lavable o barnizado sobre madera | N42: Baños blancos sin mayólica | O42: Agua fría, corriente monofásica, teléfono
A43: G | B43: 58.01 | C43: 0 | D43: 41.6 | E43: 26.24 | F43: 46.82 | G43: 7.28 | H43: 16.78 | I43: Pircado con mezcla de barro | J43: Madera rústica o caña con torta de barro | K43: Loseta vinílica, cemento bruñado coloreado, tapizón | L43: Madera corriente con marcos en puertas y ventanas de PVC o madera corriente | M43: Estucado de yeso y/o barro, pintura al temple o agua | N43: Sanitarios básicos de losa de segunda, fierro fundido o granito | O43: Agua fría, corriente monofásica sin empotrar
A44: H | B44: 0 | C44: 0 | D44: 22.48 | E44: 13.12 | F44: 18.73 | G44: 0 | H44: 0 | I44: (No corresponde) | J44: Sin techo | K44: Cemento pulido, ladrillo corriente, entablado corriente | L44: Madera rústica | M44: Pintado en ladrillo rústico, placa de concreto o similar | N44: Sin aparatos sanitarios | O44: Sin instalación eléctricia ni sanitaria
A45: I | B45: 0 | C45: 0 | D45: 4.95 | E45: 0 | F45: 0 | G45: 0 | H45: 0 | I45: (No corresponde) | J45: (No corresponde) | K45: Tierra compactada | L45: Sin puertas ni ventanas | M45: Sin revestimientos, en ladrillo, adobe o similar | N45: (No corresponde) | O45: (No corresponde)
A46: J | B46: 0 | C46: 0 | D46: 0 | E46: 0 | F46: 0 | G46: 0 | H46: 0 | I46: (No corresponde) | J46: (No corresponde) | K46: (No corresponde) | L46: (No corresponde) | M46: (No corresponde) | N46: (No corresponde) | O46: (No corresponde)
A48: SELVA
B49: 1 | C49: 2 | D49: 3 | E49: 4 | F49: 5 | G49: 6 | H49: 7 | I49: 1 | J49: 2 | K49: 3 | L49: 4 | M49: 5 | N49: 6 | O49: 7
A50: A | B50: 528.43 | C50: 270.63 | D50: 329.87 | E50: 223.86 | F50: 265.44 | G50: 96.85 | H50: 327.38 | I50: Estructuras laminadas curvadas de concreto armado que incluyen en una sola armadura la cimentación y el techo (para este caso no se considera el componente N° 2) | J50: Losa o aligerado de concreto armado con luces mayores de 6m con sobrecarga mayor a 300 Kg/m2 | K50: Mármol importado, piedras naturales, porcelanato | L50: Aluminio pesado con perfiles especiales, madera fina ornamental (caoba, cedro o pino selecto), vidrio insulado | M50: Mármol importado, madera fina (caoba o similar), baldosa acústica en techo o similar | N50: Baños completos de lujo importados con enchape fino (mármol o similar) | O50: Aire acondicionado, iluminación especial, ventilación forzada, sistema hidroneumático, agua caliente y fría, intercomunicador, alarmas, ascensor, sistema de bombeo de agua y desagüe, teléfono
A51: B | B51: 360.54 | C51: 191.17 | D51: 158.1 | E51: 177.56 | F51: 182.96 | G51: 68.83 | H51: 196.12 | I51: Columnas, vigas y/o placas de concreto armado y/o metálicas | J51: Aligerados o losas de concreto armado inclinadas | K51: Mármol nacional o reconstituido, parquet fino (olivo, chonta o similar), cerámica importada, madera fina | L51: Aluminio o madera fina (caoba o similar) de diseño especial, vidrio tratado polarizado y curvado, laminado o templado | M51: Mármol nacional, madera fina (caoba o similar), enchapes en techos | N51: Baños completos importados con mayólica o cerámico decorativo importado | O51: Sistema de bombeo de agua potable, ascensor, teléfono, agua caliente y fría
A52: C | B52: 266.31 | C52: 144.23 | D52: 103.74 | E52: 135.28 | F52: 156.07 | G52: 48.56 | H52: 142.99 | I52: Placas de concreto e=10 a 15cm, albañilería armada, ladrillo o similar con columnas y vigas de amarre de concreto armado | J52: Aligerado o losas de concreto armado horizontales | K52: Madera fina machihembrada, terrazo | L52: Aluminio o madera fina (caoba o similar), vidrio tratado polarizado, laminado o templado | M52: Superficie caravista obtenida mediante encofrado especial, enchape en techos | N52: Baños completos nacionales con mayólica o cerámico nacional de color | O52: Sistema de bombeo de agua potable, teléfono, agua caliente y fría
A53: D | B53: 205.91 | C53: 125.75 | D53: 87.95 | E53: 90.68 | F53: 112.78 | G53: 32.93 | H53: 79.52 | I53: Ladrillo o similar, drywall o similar incluye techo (para este caso no se considera el componente N° 2) | J53: Calamina metálica, fibrocemento sobre viguería metálica | K53: Parquet de primera, laja, cerámica nacional, loseta veneciana 40x40, piso laminado | L53: Ventanas de aluminio, puertas de madera selecta, vidrio tratado transparente | M53: Enchape de madera o laminados, piedra o material vitrificado | N53: Baños completos nacionales blancos con mayólica blanca | O53: Agua fría, agua caliente, corriente trifásica, teléfono
A54: E | B54: 163.5 | C54: 91.55 | D54: 70.96 | E54: 58.88 | F54: 85.51 | G54: 16.34 | H54: 53.76 | I54: Madera selecta tratada sobre pilotaje de madera con base de concreto, con muros de madera contraplacada o similar | J54: Madera selecta tratada con material impermeabilizante | K54: Parquet de segunda, loseta veneciana 30x30, lajas de cemento con canto rodado | L54: Ventanas de fierro, puertas de madera selecta (caoba o similar), vidrio simple transparente | M54: Superficie de ladrillo caravista | N54: Baños con mayólica blanca parcial | O54: Agua fría, agua caliente, corriente monofásica, teléfono
A55: F | B55: 128.93 | C55: 42.1 | D55: 57.78 | E55: 48.02 | F55: 66.11 | G55: 13.89 | H55: 29.69 | I55: Adobe o similar | J55: Calamina metálica, fibrocemento o tejas sobre tijerales de madera | K55: Loseta corriente, canto rodado, alfombra | L55: Ventanas de fierro o aluminio industrial, puertas contraplacadas de madera (cedro o similar), puertas en material MDF o HDF, vidrio simple transparente | M55: Tarrajeo frotachado y/o yeso moldurado, pintura lavable o barnizado sobre madera | N55: Baños blancos sin mayólica | O55: Agua fría, corriente monofásica, teléfono
A56: G | B56: 111.67 | C56: 33.12 | D56: 47.77 | E56: 28.34 | F56: 55.25 | G56: 9.56 | H56: 17.52 | I56: Madera tratada selecta con base de concreto, con muros de madera tipo contraplacada o similar, drywall o similar sin techo | J56: Techos de palmas (crisnejas) | K56: Loseta vinílica, cemento bruñado coloreado, tapizón | L56: Madera corriente con marcos en puertas y ventanas de PVC o madera corriente | M56: Estucado de yeso y/o barro, pintura al temple o agua | N56: Sanitarios básicos de losa de segunda, fierro fundido o granito | O56: Agua fría, corriente monofásica sin empotrar
A57: H | B57: 55.84 | C57: 0 | D57: 18.38 | E57: 14.17 | F57: 22.1 | G57: 0 | H57: 0 | I57: Madera corriente | J57: Sin techo | K57: Cemento pulido, ladrillo corriente, entablado corriente | L57: Madera rústica | M57: Pintado en ladrillo rústico, placa de concreto o similar | N57: Sin aparatos sanitarios | O57: Sin instalación eléctricia ni sanitaria
A58: I | B58: 22.33 | C58: 0 | D58: 4.04 | E58: 0 | F58: 0 | G58: 0 | H58: 0 | I58: Madera rústica | J58: (No corresponde) | K58: Tierra compactada | L58: Sin puertas ni ventanas | M58: Sin revestimientos, en ladrillo, adobe o similar | N58: (No corresponde) | O58: (No corresponde)
A59: J | B59: 8.93 | C59: 0 | D59: 0 | E59: 0 | F59: 0 | G59: 0 | H59: 0 | I59: Caña, guayaquil, pona o pintoc | J59: (No corresponde) | K59: (No corresponde) | L59: (No corresponde) | M59: (No corresponde) | N59: (No corresponde) | O59: (No corresponde)
