Workbook
Name ÁreaTechada: '[1]MD Áreas'!$K$43
Name ÁreaTerreno: '[1]MD Áreas'!$S$33
Name DirecInSitu: '[1]MD Datos'!$J$53
Name DirecPU: '[1]MD Datos'!$J$51
Name DirecRegistral: '[1]MD Datos'!$J$49
Name Expedición: '[1]MD Datos'!$Z$14
Name JKLKL: #REF!
Name Porcentajededucciones: '[1]RESUL VC'!$R$59
Name Producto1: OFFSET([1]Listas!$A$3,0,0,COUNTA([1]Listas!$A$1:$A$65536)-2)
Name TipoTasación: OFFSET([1]Listas!$C$3,0,0,COUNTA([1]Listas!$C$1:$C$65536)-1)
Name VC: '[1]RESUL VC'!$X$45
Name VT: '[1]AM Costos'!$X$28

Sheet HOJA DE RESUMEN
V12: N° de Folio
V13: N° de Servicio Tasadora
B14: 10 / EL / JB | V14: Fecha de Expedición | AA14: 45658
V15: Fecha de caducidad | AA15: =AA14+365 -> 46023
B16: INFORME DE TASACIÓN
B17: BIEN TERMINADO
B38: SOLICITANTE: | H38: BANBIF | N38: OF. | O38: - | T38: FUNC. | V38: Tasaciones PN
B40: CLIENTE: | H40: =+MEMORIA!S14 -> 0
B42: PROPIETARIOS: | H42: =+MEMORIA!S15 -> 0
B44: FECHA DE INSPECCIÓN OCULAR: | R44: LATITUD/LONGITUD:
B46: DIRECCIÓN RRPP: | H46: =+MEMORIA!C27 -> 0
B48: DIRECCIÓN MUNICIPAL: | H48: =+MEMORIA!C29 -> 0
B50: DIRECCIÓN EN SITU: | H50: =+MEMORIA!C31 -> 0
B52: DESCRIPCIÓN: | H52: TIPO DE USO | N52: % | S52: TIPO DE USO | Z52: %
G53: 1 | H53: Departamento | N53: 1 | R53: 2
G54: 3 | R54: 4
B56: ANTIGÜEDAD | H56: =2025-MEMORIA!O100 -> 2025 | O56: De acuerdo a expediente documental y tipo de construcción predominante
B58: CARGAS: | H58: SÍ | K58: NO | N58: Gravámenes | U58: SÍ | Y58: NO
B60: TIPO DE CAMBIO APLICADO: | L60: Soles / Dólar
B62: DOLARES | C62: VALORES INSCRITOS EN RRPP | H62: TERRENO | K62: EDIFICACIÓN | Q62: OTROS | U62: Valor Comercial | X62: VRI | AA62: % | AB62: Valores Asegurables
C63: Descripción | H63: Área | I63: Valor | K63: Área Techada | M63: Área Ocupada | O63: Valor | Q63: Valor Áreas Comunes | S63: Valor Obras Complementarias
C64: =+MEMORIA!D75 -> Departamento N° …. | H64: =+MEMORIA!AO35 -> 0 | I64: =+MEMORIA!AO147 -> 0 | K64: =+MEMORIA!V76 -> 0 | M64: =+MEMORIA!AD76 -> 0 | O64: =+MEMORIA!AM269 -> 0 | Q64: =+MEMORIA!AM270 -> 0 | S64: =+MEMORIA!AM271 -> 0 | U64: =+MEMORIA!AM272 -> 0 | X64: =+MEMORIA!AM299 -> 0 | AA64: =+MEMORIA!I297 -> 0.8 | AB64: =+MEMORIA!AM312 -> 0
C65: =+MEMORIA!D77 -> Estacionamiento N° … | H65: =+MEMORIA!AO37 -> 0 | I65: =+MEMORIA!AO150 -> 0 | K65: =+MEMORIA!V77 -> 0 | M65: =+MEMORIA!AD77 -> 0 | O65: =+MEMORIA!AM275 -> 0 | Q65: =+MEMORIA!AM276 -> 0 | S65: =+MEMORIA!AM277 -> 0 | U65: =+MEMORIA!AM278 -> 0 | X65: =+MEMORIA!AM301 -> 0 | AA65: =+AA64 -> 0.8 | AB65: =+MEMORIA!AM318 -> 0
C66: =+MEMORIA!D78 -> Depósito N°.. | H66: =+MEMORIA!AO39 -> 0 | I66: =+MEMORIA!AO153 -> 0 | K66: =+MEMORIA!V78 -> 0 | M66: =+MEMORIA!AD78 -> 0 | O66: =+MEMORIA!AM281 -> 0 | Q66: =+MEMORIA!AM282 -> 0 | S66: =+MEMORIA!AM283 -> 0 | U66: =+MEMORIA!AM284 -> 0 | X66: =+MEMORIA!AM303 -> 0 | AA66: =+MEMORIA!I299 -> 0.8 | AB66: =+MEMORIA!AM324 -> 0
C67: VALORES NO INSCRITOS EN RRPP
C68: =+C64 -> Departamento N° …. | H68: 0 | I68: 0 | K68: 0 | M68: 0 | O68: 0 | Q68: 0 | S68: 0 | U68: 0 | X68: 0 | AA68: 0 | AB68: 0
C69: TOTAL | H69: =SUM(H64:H68) -> 0 | I69: =SUM(I64:J68) -> 0 | K69: =SUM(K64:L68) -> 0 | M69: =SUM(M64:N68) -> 0 | O69: =SUM(O64:P68) -> 0 | Q69: =SUM(Q64:R68) -> 0 | S69: =SUM(S64:T68) -> 0 | U69: =SUM(U64:W68) -> 0 | X69: =SUM(X64:Z68) -> 0 | AB69: =SUM(AB64:AD68) -> 0
B71: SOLES | C71: VALORES INSCRITOS EN RRPP | H71: TERRENO | K71: EDIFICACIÓN | Q71: OTROS | U71: Valor Comercial | X71: VRI | AA71: % | AB71: Valores Asegurables
C72: Descripción | H72: Área | I72: Valor | K72: Área Techada | M72: Área Ocupada | O72: Valor | Q72: Valor Áreas Comunes | S72: Valor Obras Complementarias
C73: =+C64 -> Departamento N° …. | H73: =+H64 -> 0 | I73: =+I64*H60 -> 0 | K73: =+K64 -> 0 | M73: =+M64 -> 0 | O73: =+O64*$H$60 -> 0 | Q73: =+Q64*$H$60 -> 0 | S73: =+S64*$H$60 -> 0 | U73: =+U64*H60 -> 0 | X73: =+X64*H60 -> 0 | AA73: =+AA64 -> 0.8 | AB73: =+AB64*H60 -> 0
C74: =+C65 -> Estacionamiento N° … | H74: =+H65 -> 0 | I74: =+I65*H60 -> 0 | K74: =+K65 -> 0 | M74: =+M65 -> 0 | O74: =+O65*$H$60 -> 0 | Q74: =+Q65*$H$60 -> 0 | S74: =+S65*$H$60 -> 0 | U74: =+U65*H60 -> 0 | X74: =+X65*H60 -> 0 | AA74: =+AA65 -> 0.8 | AB74: =+AB65*H60 -> 0
C75: =+C66 -> Depósito N°.. | H75: =+H66 -> 0 | I75: =+I66*H60 -> 0 | K75: =+K66 -> 0 | M75: =+M66 -> 0 | O75: =+O66*$H$60 -> 0 | Q75: =+Q66*$H$60 -> 0 | S75: =+S66*$H$60 -> 0 | U75: =+U66*H60 -> 0 | X75: =+X66*H60 -> 0 | AA75: =+AA66 -> 0.8 | AB75: =+AB66*H60 -> 0
C76: VALORES NO INSCRITOS EN RRPP
C77: =+C68 -> Departamento N° …. | H77: =+H68 -> 0 | I77: =+I68*H60 -> 0 | K77: =+K68 -> 0 | M77: =+M68 -> 0 | O77: 0 | Q77: =+Q68*H60 -> 0 | S77: =+S68*H60 -> 0 | U77: =+U68*H60 -> 0 | X77: =+X68*H60 -> 0 | AA77: =+AA73 -> 0.8 | AB77: =+AB68*H60 -> 0
C78: TOTAL | I78: =SUM(I73:J77) -> 0 | K78: =SUM(K73:L77) -> 0 | M78: =SUM(M73:N77) -> 0 | O78: =SUM(O73:P77) -> 0 | Q78: =SUM(Q73:R77) -> 0 | S78: =SUM(S73:T77) -> 0 | U78: =SUM(U73:W77) -> 0 | X78: =SUM(X73:Z77) -> 0 | AB78: =SUM(AB73:AD77) -> 0
B80: TIPO DE TASACIÓN: | R80: INSTANCIA DE TASACIÓN: | Y80: Nueva
B82: TIPO DE INMUEBLE TASADO:
B84: DETALLE: DECLARATORIA DE FAB. / CARGAS / GRÁVAMEN | H84: - (SI, NO) cuenta con declaratoria de fábrica. - (SI, NO) cuenta con carga (afecta o no al valor comercial) - (SI, NO) cuenta con grávamen.
I86: SI | K86: NO | Q86: SI | S86: NO | AA86: SI | AC86: NO
B87: FACTIBILIDAD: | H87: LUZ | O87: AGUA | Y87: DESAGUE
I89: SI | K89: NO
B90: CERTIFICADO DE PARÁMETROS URBANÍSTICOS (CPU):
B92: OBSERVACIONES: | H92: =+MEMORIA!C104 -> 0
C94: ADVERTENCIAS | H94: -
C95: LINDEROS
C96: =+MEMORIA!D75 -> Departamento N° ….
C97: FRENTE : | AD97: ml
C99: DERECHA : | AD99: ml
C101: IZQUIERDA : | AD101: ml
C103: FONDO : | AD103: ml
C104: TOTAL DEL PERIMETRO | AB104: =SUM(AB97:AC103) -> 0 | AD104: ml
C105: =+MEMORIA!D77 -> Estacionamiento N° …
C106: FRENTE : | AD106: ml
C108: DERECHA : | AD108: ml
C110: IZQUIERDA : | AD110: ml
C112: FONDO : | AD112: ml
C113: TOTAL DEL PERIMETRO | AB113: =SUM(AB106:AC112) -> 0 | AD113: ml
C114: =+MEMORIA!D78 -> Depósito N°..
C115: FRENTE : | AD115: ml
C117: DERECHA : | AD117: ml
C119: IZQUIERDA : | AD119: ml
C121: FONDO : | AD121: ml
C122: TOTAL DEL PERIMETRO | AB122: =SUM(AB115:AC121) -> 0 | AD122: ml
G125: FIRMA | W125: FIRMA
C126: PERITO: | G126: RICARDO BARTHELMESS SACO | R126: PERITO: | W126: (…. / ….... / CY)
C127: REPEV: | G127: N° 561-2001 | R127: REPEV:
B130: * VANET S.A.C. trabaja el presente informe en formato aprobado por el banco Banbif.

Sheet MEMORIA
Q11: INFORME N° 25
A12: "VALUACIÓN COMERCIAL DE INMUEBLE "
A14: CLIENTE DE | Q14: :
A15: PROPIETARIO | R15: :
A16: FECHA INFORME | R16: : | S16: Lima,
A18: A) | C18: OBJETIVO/ANTECEDENTES/METODOLOGÍA
C19: El objetivo del presente informe es determinar el valor de mercado y de realización del inmueble.
C20: La visita de inspección se realizó el ../.../2025, en presencia del …......................, previa coordinación al teléfono …........... tomándose las vistas fotográficas correspondientes.
C21: Para efectos del presente informe se contó con: ….............
C22: La metodología aplicada en el presente informe es la indicada en el Reglamento Nacional de Tasaciones del Perú vigente a la fecha.
A23: B) | C23: MEMORIA DESCRIPTIVA
A24: 1 | C24: UBICACIÓN
C25: El inmueble materia de valuación se encuentra ubicado en:
C26: Según Ficha Registral
C28: Según Autoavalúo
C30: Según Inspección ocular
A32: =1+A24 -> 2 | C32: ÁREA DE TERRENO | O32: (Según …......)
C33: Terreno matriz | AT33: m2
C34: Porcentaje correspondiente al Departamento N° …........%
C35: Al departamento le corresponde un área de terreno de: | AT35: m2
C36: Porcentaje correspondiente al estacionamiento N° ...%
C37: Al estacionamiento le corresponde un área de terreno de: | AT37: m2
C38: Porcentaje correspondiente al depósito N° …...%
C39: Al depósito le corresponde un área de terreno de: | AT39: m2
A40: =+A32+1 -> 3 | C40: DESCRIPCIÓN
C43: Vista interior | P43: Vista exterior | Y43: X
C45: Estacionamientos | P45: Tipo: | AA45: Simple | AH45: Doble lineal | AQ45: Doble paralelo
C47: Depósito(s):
A48: =+A40+1 -> 4 | C48: OCUPACIÓN Y USOS
A50: =+A48+1 -> 5 | C50: INSCRIPCIÓN
C51: El inmueble corre inscrito según Partida Registral Nº ….......... de la Oficina Registral de la Propiedad Inmueble de …..
A52: =+A50+1 -> 6 | C52: ZONIFICACION (Referencial / No Oficial)
C54: Nota.- Se recomienda solicitar Certificado de Parámetros.
C56: MAPA | AJ56: LEYENDA
A68: =+A52+1 -> 7 | C68: ENTORNO URBANO E INFRAESTRUCTURA DE SERVICIOS
A70: =+A68+1 -> 8 | C70: DISTRIBUCIÓN
A72: =+A70+1 -> 9 | C72: AREAS CONSTRUIDAS | P72: (Según …........................)
C74: Detalle | V74: Área Techada | AD74: Área Ocupada
C75: a. | D75: Departamento N° …. | AB75: m2 | AJ75: m2
C76: TOTAL | H76: =+C72 -> AREAS CONSTRUIDAS | V76: =SUM(V75:AA75) -> 0 | AB76: m2 | AD76: =SUM(AD75:AI75) -> 0 | AJ76: m2
C77: b. | D77: Estacionamiento N° … | AB77: m2 | AJ77: m2
C78: c. | D78: Depósito N°.. | AB78: m2 | AJ78: m2
A79: =1+A72 -> 10 | C79: EDIFICACIÓN
AR81: Valor Unit. US$ /m2
C82: Muros, cimentación, elementos estructurales y columnas:
C83: .
C84: Techos:
C86: Pisos:
C88: Puertas y Ventanas
C90: Revestimientos
C92: Baños:
C94: Instalaciones
C96: TOTAL VALOR UNITARIO | AM96: =SUM(AM82:AQ95) -> 0 | AR96: =SUM(AR82:AV95) -> 0
A97: =A79+1 -> 11 | C97: ANTIGÜEDAD, ESTADO Y DEPRECIACION
C99: Edificación | O99: Antigüedad | U99: Estado | AC99: Deprec. %
C100: Inmueble | R100: años
A101: =1+A97 -> 12 | C101: SERVIDUMBRES
A103: =A101+1 -> 13 | C103: OBSERVACIONES
A105: =A103+1 -> 14 | C105: NOTA
C107: F | E107: El presente informe no considera los vicios ocultos que tenga el inmueble que no han podido ser identificados en el momento de la inspección o que pudiese tener el inmueble a futuro.
C109: F | E109: La presente valuación no incluye estudio de títulos de propiedad.
C111: F | E111: El nombre del propietario se consigna según la documentación presentada.
C113: F | E113: VANET S.A.C. sólo se responsabiliza por los valores vertidos en el presente informe, los cuales son determinados en base a la documentación presentada.
C115: F | E115: Este informe incluye un código QR en la parte superior derecha de la hoja frontal, el cual permite verificar su autenticidad. Al escanearlo, debe redirigir al sitio oficial www.vanetperu.com, donde podrá consultarse la versión original emitida por la empresa.
A116: -.&&&&&&&.-
A117: C.- | C117: DESARROLLO DE LA VALUACIÓN COMERCIAL
R118: =+Q11 -> INFORME N° 25 | AB118: =+AB11 -> 0
A119: 1 | C119: VALOR DEL | J119: TERRENO
C120: Para determinar el valor de mercado del TERRENO se han tomado en consideración las últimas operaciones de compra venta de los inmuebles adyacentes al que es materia de valuación por ser de características similares; así mismo, se ha considerado la oferta y demanda existente para inmuebles de condiciones semejantes.
C122: CUADRO COMPARATIVO
C124: UBICACIÓN | R124: Zonificación | U124: Antigüedad | X124: Área de terreno m2 | AA124: Área construida m2 | AD124: V. Tot. Inm. US$ | AI124: V. Const. US$ | AN124: Valor de Terr.US$ | AS124: V. U. US$/m2
C125: "OFERTA EN EL MERCADO"
AN126: =+AD126-AI126 -> 0 | AS126: =+AN126/X126 -> #DIV/0!
AN127: =+AD127-AI127 -> 0 | AS127: =+AN127/X127 -> #DIV/0!
AN128: =+AD128-AI128 -> 0 | AS128: =+AN128/X128 -> #DIV/0!
C129: "INMUEBLES VENDIDOS - VENTAS CERRADAS" Tomado del aplicativo Vanetmap
AN130: =+AD130-AI130 -> 0 | AS130: =+AN130/X130 -> #DIV/0!
AC143: / m2
C144: Valor del | I144: =+J119 -> TERRENO
C145: =+D75 -> Departamento N° ….
C146: Factor de Reajuste Comercial de: | U146: 1
C147: =+AO35 -> 0 | I147: m2 | L147: x | N147: =+V143 -> 0 | U147: /m2 | AF147: x | AI147: =+U146 -> 1 | AM147: = | AO147: =+C147*N147*AI147 -> 0
C148: =+D77 -> Estacionamiento N° …
C149: Factor de Reajuste Comercial de: | U149: 1
C150: =+AO37 -> 0 | I150: m2 | L150: x | N150: =+N147 -> 0 | U150: /m2 | AF150: x | AI150: =+U149 -> 1 | AM150: = | AO150: =+C150*N150*AI150 -> 0
C151: =+D78 -> Depósito N°..
C152: Factor de Reajuste Comercial de: | U152: 1
C153: =+AO39 -> 0 | I153: m2 | L153: x | N153: =+N150 -> 0 | U153: /m2 | AF153: x | AI153: =+U152 -> 1 | AM153: = | AO153: =+C153*N153*AI153 -> 0
C154: =+C119 -> VALOR DEL | K154: =+J119 -> TERRENO | AM154: = | AO154: =SUM(AO147:AV153) -> 0
A155: =1+A119 -> 2 | C155: VALOR DE LA EDIFICACIÓN
C156: =+C145 -> Departamento N° ….
C157: Área techada
C158: =+V75 -> 0 | I158: m2 | L158: x | N158: =+AR96 -> 0 | T158: /m2 | Y158: x | AA158: =1-AC100 -> 1 | AF158: x | AI158: =+AI147 -> 1 | AM158: = | AO158: =+C158*N158*AA158*AI158 -> 0
C159: Área sin techar
C160: =+AD75-V75 -> 0 | I160: m2 | L160: x | T160: /m2 | Y160: x | AA160: =+AA158 -> 1 | AF160: x | AI160: =+AI158 -> 1 | AM160: = | AO160: =+C160*N160*AA160*AI160 -> 0
C161: =+C148 -> Estacionamiento N° …
C162: =+V77 -> 0 | I162: m2 | L162: x | N162: 200 | T162: /m2 | Y162: x | AA162: =+AA158 -> 1 | AF162: x | AI162: =+AI150 -> 1 | AM162: = | AO162: =+C162*N162*AA162*AI162 -> 0
C163: =+C151 -> Depósito N°..
C164: =+V78 -> 0 | I164: m2 | L164: x | N164: 200 | T164: /m2 | Y164: x | AA164: =+AA162 -> 1 | AF164: x | AI164: =+AI153 -> 1 | AM164: = | AO164: =+C164*N164*AA164*AI164 -> 0
C165: =+C155 -> VALOR DE LA EDIFICACIÓN | AM165: = | AO165: =SUM(AO158:AV164) -> 0
...

Sheet C2
E14: HOJA RESUMEN TASACIÓN DE INMUEBLES - FONDO MIVIVIENDA S.A. - C.02
A16: FECHA DE VALUACIÓN | I16: DE | T16: DE | V16: 2025
A18: ENTIDAD FINANCIERA | G18: BANCO INTERAMERICANO DE FINANZAS | Z18: PROPIETARIO | AA18: =+MEMORIA!S15 -> 0
A20: BENEFICIARIO | G20: =+MEMORIA!S14 -> 0 | AE20: DNI / LE / CIP / CE
A22: PERITO TASADOR | G22: VANET S.A.C. | AF22: REPEV. SBS | AK22: 561 2001
A24: UBICACIÓN DEL INMUEBLE | G24: Carrt. | I24: Av. | K24: Jr. | M24: Calle | O24: Psje | S24: =+MEMORIA!C27 -> 0
A26: N° / Mza./Lt | F26: Dpto./Int. | N26: Urb./Loc
A28: Departamento | M28: Provincia | Z28: Distrito | AG28: =+'ANEXO II'!D12 -> 0
A30: CLASIFICACIÓN | F30: BIEN FUTURO | M30: a) En Proyecto | T30: b) En Construcción | AC30: c) En acabados | AL30: d) Culminado
G31: *Bien futuro: inmueble en proyecto, en construcción o en acabados sin declaratoria de fábrica inscrita en RR.PP.
F32: BIEN TERMINADO | M32: Registro: RPI | T32: RPU | W32: Zona | AA32: Ficha | AF32: Partida | AL32: N°
F33: *Bien terminado: Inmueble con construcción terminada, con declaratoria de fábrica y de ser el caso independización inscritas en los RR.PP.
A35: DESCRIPCIÓN DEL INMUEBLE
A37: TIPO DE INMUEBLE | L37: CASA | W37: DEPARTAMENTO | AA37: X | AD37: Si vive en un departamento, indicar el piso
A39: AREAS | P39: AREA DEL TERRENO | R39: =+MEMORIA!AO35 -> 0 | U39: M2 | AG39: AREA CONSTRUIDA | AL39: =+MEMORIA!V75 -> 0 | AO39: M2
A42: ESTADO DE CONSERVACIÓN | J42: Bueno | O42: Regular | S42: Malo | AA42: ANTIGÜEDAD CONSTRUCCIÓN | AL42: =+'HOJA DE RESUMEN'!H56 -> 2025 | AO42: años
A46: Sala-Comedor | F46: SI | H46: NO | L46: Dormitorios (Cantidad) | Y46: Cochera (Cantidad)
A47: Cocina | F47: SI | H47: NO | L47: Dormitorio de Servicio | S47: SI | U47: NO | Y47: Jardín | AF47: SI | AJ47: NO
A48: Baños (Cantidad) | L48: Cuarto de Estudio | S48: SI | U48: NO | Y48: Terraza | AF48: SI | AJ48: NO
A49: Baño de Servicio | F49: SI | H49: NO | L49: Lavandería | S49: SI | U49: NO | Y49: Parque de uso común | AF49: SI | AJ49: NO
L50: Instalaciones de gas natural | S50: SI | U50: NO | Y50: Sala común | AF50: SI | AJ50: NO
Y51: Canchas/Gimnasios | AF51: SI | AJ51: NO
Y52: Piscina común | AF52: SI | AJ52: NO
A55: ESPECIFICACIONES TECNICAS
A57: ESTRUCTURAS
A58: CIMENTACIÓN | J58: COLUMNAS | Q58: VIGAS | X58: TECHOS | AE58: MUROS
A59: Platea de cimentación | J59: a) Concreto | Q59: a) Concreto | X59: Aligerado | AE59: Concreto | AM59: Tipos de albañilería
A60: Cimientos corridos | J60: b) Acero | Q60: b) Acero | X60: Maciso | AE60: Albañilería | AK60: Arcilla | AO60: Concreto
A61: Viga de cimentación | J61: a) y b) | Q61: a) y b) | AK61: Calcáreo | AO61: Adobe
A63: ACABADOS
B66: PUERTAS | E66: TIPO | I66: a) Apanelada | O66: b) Maciza | T66: c) Contraplacada | AB66: VENTANAS | AH66: Madera | AL66: Aluminio
E67: MATERIAL | I67: a) Fierro | O67: b) Madera | T67: c) Otros | AH67: Fierro | AL67: Otros
A70: MUEBLES DE COCINA | AB70: APARATOS SANITARIOS
A71: AMOBLADA | J71: NO AMOBLADA | AF71: BLANCO | AK71: COLOR
A73: PISOS
B74: AMBIENTE | H74: Vinílico | M74: Parquet | R74: Machimbrado | W74: Cemento | AB74: Cerámica | AH74: Otro
B75: Sala-Comedor
B76: Baños
B77: Dormitorios
A79: PRECIOS REFERENCIALES
A81: N° | B81: UBICACIÓN | P81: AT (m2) | U81: AC (m2) | Z81: PRECIO (US$) | AH81: FUENTE
A82: 1 | B82: =+MEMORIA!C126 -> 0 | P82: =+MEMORIA!X126 -> 0 | U82: =+MEMORIA!AA126 -> 0 | Z82: =+MEMORIA!AS126 -> #DIV/0! | AH82: =+B82 -> 0
A83: 2 | B83: =+MEMORIA!C127 -> 0 | P83: =+MEMORIA!X127 -> 0 | U83: =+MEMORIA!AA127 -> 0 | Z83: =+MEMORIA!AS127 -> #DIV/0! | AH83: =+B83 -> 0
A84: 3 | B84: =+MEMORIA!C128 -> 0 | P84: =+MEMORIA!X128 -> 0 | U84: =+MEMORIA!AA128 -> 0 | Z84: =+MEMORIA!AS128 -> #DIV/0! | AH84: =+B84 -> 0
A85: 4 | B85: =+MEMORIA!C130 -> 0 | P85: =+MEMORIA!X130 -> 0 | U85: =+MEMORIA!AA130 -> 0 | Z85: =+MEMORIA!AS130 -> #DIV/0! | AH85: =+B85 -> 0
A86: 5 | B86: =+MEMORIA!C244 -> 0 | P86: 0 | U86: =+MEMORIA!AA244 -> 0 | Z86: =+MEMORIA!AS244 -> #DIV/0! | AH86: =+B86 -> 0
A87: 6 | B87: =+MEMORIA!C245 -> 0 | P87: =+MEMORIA!X248 -> 0 | U87: =+MEMORIA!AA245 -> 0 | Z87: =+MEMORIA!AS245 -> #DIV/0! | AH87: =+B87 -> 0
A88: 7 | B88: =+MEMORIA!C247 -> 0 | P88: =+MEMORIA!X249 -> 0 | U88: =+MEMORIA!AA247 -> 0 | Z88: =+MEMORIA!AS247 -> #DIV/0! | AH88: =+B88 -> 0
A90: VALORIZACIONES
A92: VALOR DEL TERRENO (En S/.) | N92: =+'HOJA DE RESUMEN'!I73 -> 0 | AC92: (*) SEGÚN LA RESOLUCIÓN SBS N° 808-2003 EL VALOR DE REALIZACIÓN SE ENTIENDE COMO EL VALOR NETO QUE LA EMPRESA ESPERA RECUPERAR COMO CONSECUENCIA DE LA EVENTUAL VENTA O EJECUCIÓN DEL BIEN, EN LA SITUACIÓN COMO Y DONDE ESTÉ. POR TANTO, ESTE VALOR DEBE CONSIDERAR LOS CASTIGOS Y CARGOS POR CONCEPTO DE IMPUESTOS EN LAS VENTAS, COMISIONES, FLETES, MERMAS, ETC.
A94: VALOR DEL CASCO HABITABLE (En S/.) | N94: =+(MEMORIA!AO348+MEMORIA!AO352+MEMORIA!AO354)*'HOJA DE RESUMEN'!H60 -> 0
A96: VALOR DEL ESTACIONAMIENTO (En S/.) | N96: =+'HOJA DE RESUMEN'!U74 -> 0
A98: VALOR DEL DEPOSITO (En S/.) | N98: =+'HOJA DE RESUMEN'!U75 -> 0
A100: VALOR COMERCIAL DEL INMUEBLE (En S/.) | N100: =+'HOJA DE RESUMEN'!U78 -> 0
A102: VALOR DE REALIZACIÓN (*) (En S/.) | N102: =+'HOJA DE RESUMEN'!X78 -> 0
A104: COMENTARIOS / OBSERVACIONES
AC109: FIRMA DEL PERITO VALUADOR
A111: 1. En caso los datos de la valorización se hayan obtenido en nuevos soles, se deberá utilizar el tipo
A112: de cambio promedio compra SBS, al cierre del día hábil anterior, a la fecha de realizada la tasación
A113: 2. En caso de Bien Futuro, firmará preliminarmente, el ingeniero supervisor de la EF que financie el
A114: proyecto inmobiliario.
AC116: NOMBRES Y APELLIDOS
AC117: REPEV S.B.S
AC118: C.I.P.

Sheet ANEXO I
B12: CHECKLIST VARIABLES AMBIENTALES PARA INMUEBLES Y PROYECTOS INMOBILIARIOS
B14: 1.- | D14: Inmueble en zona:
D16: a) | F16: Residencial | Z16: d) | AB16: Industrial
D18: b) | F18: Rústico | Z18: e) | AB18: Otros:
D20: c) | F20: Comercial
B22: 2.- | D22: Entorno:
D24: a) | F24: Consolidado | Z24: e) | AB24: No homogéneo
D26: b) | F26: Homogéneo | Z26: f) | AB26: Patrimonio cultural
D28: c) | F28: Área protegida | Z28: g) | AB28: Otros
D30: d) | F30: No consolidado
B32: 3.- | D32: ¿Existe Riesgo de deslizamiento que pueda afectar el inmueble?
K34: Si | AA34: No
B36: 4.- | D36: ¿Existe Riesgo de inundación?
K38: Si | AA38: No
D40: ¿Se encuentra cerca de una ribera de rio, orillas del mar?
K42: Si | AA42: No
B44: 5.- | D44: Indicar si el inmueble tiene ladera inestables, excavaciones, rellenos:
K46: Si | AA46: No
B48: 6.- | D48: ¿Hay actividad industrial cerca del inmueble?
K50: Si | AA50: No
D52: ¿Cuál?
D56: ¿Existe alguna actividad cerca de la propiedad que pueda causar contaminación?
K58: Si | AA58: No
D60: ¿Cuál?
B64: 7.- | D64: Detalle cualquier material potencial con asbesto observado (tuberías, materiales para pared, piso, techo) e indique la condición (intacta, dañada).
B69: 8.- | D69: Detalle cualquier evidencia de relleno, botadero en los alrededores de la propiedad.
B74: 9.- | D74: Se encuentra la fábrica debidamente inscrita en Registros Públicos
K76: Si | AA76: No
B78: 10.- | D78: ¿Existen otras variables que puedan ocasionar pérdida en el valor de la propiedad?
K80: Si | AA80: No
D82: ¿Cuáles?
B87: LLENAR EN EL CASO DE INMUEBLES DE USO INDUSTRIALY/O COMERCIAL
B90: 11.- | D90: ¿Existe derrames de hidrocarburos en el inmueble, manchas de aceite, etc.?
K92: Si | AA92: No
D94: Descripción:
B100: 12.- | D100: Indicar que no haya vertidos de aguas residuales sin tratamiento hacia quebradas, ríos o suelos.
K102: Si | AA102: No
D104: Descripción:
B110: 13.- | D110: Liste cualquier otro tema como por ejemplo: limpieza, daños a la fábrica, temas de desagüe, temas de seguridad para los trabajadores.
D112: Descripción:
D123: Inspección realizada por: | N123: Nombre: | X123: Fecha: | AH123: Firma:

Sheet ANEXO II
A5: ANEXO
A7: PROPIETARIO | C7: =+MEMORIA!S15 -> 0
A8: CLIENTE | C8: =+MEMORIA!S14 -> 0
A10: DIRECCION | G10: NUMERO DE | I10: AÑO | J10: TIPO | K10: USO | L10: ESTADO | M10: M.C.P (*) | N10: VALOR DECLARADO EN US$
A11: AVENIDA | B11: MZ | C11: LOTE | D11: DISTRITO | E11: PROVINCIA | F11: DEPARTAMENTO | G11: PISOS | H11: SOTANOS | I11: CONSTRUCCION | J11: (I) | K11: (I) | L11: (II) | M11: (IV) | N11: EDIFICACIONES
H12: - | I12: =2025-MEMORIA!O100 -> 2025 | J12: 3 | K12: 1 | L12: 3 | M12: 1 | N12: =+MEMORIA!AM269+MEMORIA!AM270+MEMORIA!AM271+MEMORIA!AM275+MEMORIA!AM276+MEMORIA!AM277+MEMORIA!AM281+MEMORIA!AM282+MEMORIA!AM283 -> 0
M13: TOTAL | N13: =+N12 -> 0
A18: (*) M.C.P = Material de construcción predominante
A20: Tipo (I) | D20: Uso (I) | F20: Estado (II) | I20: MCP (IV)
A22: 1.- Inmueble hasta 04 Pisos | D22: 1.- Vivienda | F22: 1.- Terreno Cercado | I22: 1.- Concreto Armado
A23: 2.- Inmueble entre 05 y 10 pisos | D23: 2.- Oficina | F23: 2.- En Construcción | I23: 2.- Ladrillo y cemento
A24: 3.- Inmueble + de 10 pisos | D24: 3.- Taller | F24: 3.- Construido con 1 M.C.P. | I24: 3.- Estructura de acero / metálica
A25: 4.- Nave Industrial | D25: 4.- Comercial | F25: 4.- Construido con + M.C.P. | I25: 4.- Adobe / Quincha
A26: 5.- Otros | D26: 5.- Industrial | F26: 5.- Construido por Etapas | I26: 5.- Madera
D27: 6.- Almacén | I27: 6.- Otro
D28: 7.- Colegio
D29: 8.- Centro de Salud
D30: 9.- Mina
D31: 10.- Otro

Sheet FOTO
A2: =+MEMORIA!AC265 -> 0 | C2: / … | O2: =+A2 -> 0 | Q2: =+C2 -> / … | AD2: =+O2 -> 0 | AF2: =+Q2 -> / …
B20: 1 | I20: =+B20+1 -> 2 | P20: =+I57+1 -> 7 | W20: =+P20+1 -> 8 | AE20: =1+W57 -> 13 | AL20: =+AE20+1 -> 14
B39: =+I20+1 -> 3 | I39: =+B39+1 -> 4 | P39: =1+W20 -> 9 | W39: =+P39+1 -> 10 | AE39: =+AL20+1 -> 15 | AL39: =+AE39+1 -> 16
B57: =+I39+1 -> 5 | I57: =+B57+1 -> 6 | P57: =1+W39 -> 11 | W57: =+P57+1 -> 12 | AE57: =+AL39+1 -> 17 | AL57: =+AE57+1 -> 18
W58: =+#REF!+1 -> #REF! | X58: BAÑO DE OFICINA DE DIRECTOR

Sheet Listado $
B2: PLANTILLA DE CARGA MASIVA DE DETALLE DE GARANTÍA
B4: Ubicación | K4: Bien
A5: Nro registro | B5: Tipo de vía | C5: Nombre de vía | D5: Nro | E5: Interior | F5: Urbanización | G5: Departamento | H5: Provincia | I5: Distrito | J5: Referencia | K5: Tipo de bien | L5: Descripción | M5: Número de motor | N5: Número de serie | O5: Número de placa | P5: Año | Q5: Modelo | R5: Marca | S5: Valor comercial | T5: Valor de realización | U5: Valor de terreno | V5: Valor de edificación | W5: Valor de obras complementarias | X5: Valor de areas comunes | Y5: Valor de area no declarado | Z5: Valor similar a nuevo | AA5: Valor asegurable | AB5: Area de terreno (m2) | AC5: Contacto
A6: 1 | G6: Lima | H6: Lima | K6: 0014 | L6: Departamento | S6: =+'HOJA DE RESUMEN'!U64 -> 0 | T6: =+'HOJA DE RESUMEN'!X64 -> 0 | U6: =+'HOJA DE RESUMEN'!I64 -> 0 | V6: =+'HOJA DE RESUMEN'!O64 -> 0 | W6: =+'HOJA DE RESUMEN'!S64 -> 0 | X6: =+'HOJA DE RESUMEN'!Q64 -> 0 | Y6: =+'HOJA DE RESUMEN'!U68 -> 0 | AA6: =+'HOJA DE RESUMEN'!AB64 -> 0 | AB6: =+'HOJA DE RESUMEN'!H64 -> 0 | AC6: =+'HOJA DE RESUMEN'!V38 -> Tasaciones PN
A7: 2 | G7: Lima | H7: Lima | K7: 0028 | L7: Estacionamiento | S7: =+'HOJA DE RESUMEN'!U65 -> 0 | T7: =+'HOJA DE RESUMEN'!X65 -> 0 | U7: =+'HOJA DE RESUMEN'!I65 -> 0 | V7: =+'HOJA DE RESUMEN'!O65 -> 0 | W7: =+'HOJA DE RESUMEN'!S65 -> 0 | X7: =+'HOJA DE RESUMEN'!Q65 -> 0 | Y7: =+'HOJA DE RESUMEN'!U69 -> 0 | AA7: =+'HOJA DE RESUMEN'!AB65 -> 0 | AB7: =+'HOJA DE RESUMEN'!H65 -> 0 | AC7: Tasaciones PN
A8: 3 | G8: Lima | H8: Lima | K8: 0088 | L8: Deposito | S8: =+'HOJA DE RESUMEN'!U66 -> 0 | T8: =+'HOJA DE RESUMEN'!X66 -> 0 | U8: =+'HOJA DE RESUMEN'!I66 -> 0 | V8: =+'HOJA DE RESUMEN'!O66 -> 0 | W8: =+'HOJA DE RESUMEN'!S66 -> 0 | X8: =+'HOJA DE RESUMEN'!Q66 -> 0 | Y8: =+'HOJA DE RESUMEN'!U70 -> 0 | AA8: =+'HOJA DE RESUMEN'!AB66 -> 0 | AB8: =+'HOJA DE RESUMEN'!H66 -> 0 | AC8: Tasaciones PN
A9: 4
A10: 5
A11: 6
A12: 7
A13: 8
A14: 9
A15: 10
A16: 11
A17: 12
A18: 13
A19: 14
A20: 15
... A105: 100

Sheet SUSTENTO DE UBICACION
A2: =+FOTO!A2 -> 0 | C2: =+FOTO!C2 -> / … | O2: =+A2 -> 0 | Q2: =+C2 -> / …
B4: PLANO BGR | P4: PLANO DE VISOR GEOLLACTA
B34: GOOGLE EARTH CON MEDICION | P34: PLANO ÁREA DE TERRENO

Sheet Listado S.
B2: PLANTILLA DE CARGA MASIVA DE DETALLE DE GARANTÍA
B4: Ubicación | K4: Bien
A5: Nro registro | B5: Tipo de vía | C5: Nombre de vía | D5: Nro | E5: Interior | F5: Urbanización | G5: Departamento | H5: Provincia | I5: Distrito | J5: Referencia | K5: Tipo de bien | L5: Descripción | M5: Número de motor | N5: Número de serie | O5: Número de placa | P5: Año | Q5: Modelo | R5: Marca | S5: Valor comercial | T5: Valor de realización | U5: Valor de terreno | V5: Valor de edificación | W5: Valor de obras complementarias | X5: Valor de areas comunes | Y5: Valor de area no declarado | Z5: Valor similar a nuevo | AA5: Valor asegurable | AB5: Area de terreno (m2) | AC5: Contacto
A6: 1 | C6: =+MEMORIA!C31 -> 0 | G6: Lima | H6: Lima | I6: =+'ANEXO II'!D12 -> 0 | K6: 0014 | L6: Departamento | S6: =+'HOJA DE RESUMEN'!U73 -> 0 | T6: =+'HOJA DE RESUMEN'!X73 -> 0 | U6: =+'HOJA DE RESUMEN'!I73 -> 0 | V6: =+'HOJA DE RESUMEN'!O73 -> 0 | W6: =+'HOJA DE RESUMEN'!S73 -> 0 | X6: =+'HOJA DE RESUMEN'!Q73 -> 0 | Y6: =+'HOJA DE RESUMEN'!U77 -> 0 | AA6: =+'HOJA DE RESUMEN'!AB73 -> 0 | AB6: =+'HOJA DE RESUMEN'!H64 -> 0 | AC6: =+'HOJA DE RESUMEN'!V38 -> Tasaciones PN
A7: 2 | C7: =+C6 -> 0 | G7: Lima | H7: Lima | I7: =+I6 -> 0 | K7: 0028 | L7: Estacionamiento | S7: =+'HOJA DE RESUMEN'!U74 -> 0 | T7: =+'HOJA DE RESUMEN'!X74 -> 0 | U7: =+'HOJA DE RESUMEN'!I74 -> 0 | V7: =+'HOJA DE RESUMEN'!O74 -> 0 | W7: =+'HOJA DE RESUMEN'!S74 -> 0 | X7: =+'HOJA DE RESUMEN'!Q74 -> 0 | AA7: =+'HOJA DE RESUMEN'!AB74 -> 0 | AB7: =+'HOJA DE RESUMEN'!H65 -> 0 | AC7: Tasaciones PN
A8: 3 | C8: =+C7 -> 0 | G8: Lima | H8: Lima | I8: =+I7 -> 0 | K8: 0088 | L8: Deposito | S8: =+'HOJA DE RESUMEN'!U75 -> 0 | T8: =+'HOJA DE RESUMEN'!X75 -> 0 | U8: =+'HOJA DE RESUMEN'!I75 -> 0 | V8: =+'HOJA DE RESUMEN'!O75 -> 0 | W8: =+'HOJA DE RESUMEN'!S75 -> 0 | X8: =+'HOJA DE RESUMEN'!Q75 -> 0 | AA8: =+'HOJA DE RESUMEN'!AB75 -> 0 | AB8: =+'HOJA DE RESUMEN'!H66 -> 0 | AC8: Tasaciones PN
A9: 4
A10: 5
A11: 6
A12: 7
A13: 8
A14: 9
A15: 10
A16: 11
A17: 12
A18: 13
A19: 14
A20: 15
... A105: 100

Sheet Aux_TipoBien
A1: Codigo | B1: Nombre
A2: 0001 | B2: CENTRIFUGA
A3: 0002 | B3: CALDERA
A4: 0003 | B4: PRENSA
A5: 0004 | B5: VAPORIZADOR
A6: 0005 | B6: SOLDADORA
A7: 0006 | B7: CARGADOR FRONTA
A8: 0007 | B8: RETROEXCAVADORA
A9: 0008 | B9: MOTONIVELADORA
A10: 0009 | B10: MAQ - EQP INDL
A11: 0010 | B11: PLANTA INDL
A12: 0011 | B12: COMPUTADORA
... A98: 0097 | B98: EQUIPOS MEDICOS

Sheet AuxTipoVia
A1: Codigo | B1: Nombre
A2: AV | B2: AVENIDA AV.
A3: CL | B3: CALLE CAL.
A4: JR | B4: JIRON JR.
A5: MZ | B5: MANZANA BL.
A6: PJ | B6: PASAJE PSJ.
A7: PZ | B7: PLAZA - PLAZUELA PZA.
A8: AL | B8: ALAMEDA ALM.
A9: BA | B9: BAJADA BAJ.
A10: CA | B10: CARRETERA CAR.
A11: GA | B11: GALERIA GAL.
A12: MA | B12: MALECON MLC.
... A19: SR | B19: SUB RAMAL SBR.

Sheet AuxUbigeo
A1: Codigo | B1: DEPARTAMENTO | D1: Codigo | E1: Codigo | F1: PROVINCIA | H1: Codigo | I1: Codigo | J1: Codigo | K1: DISTRITO
A2: 01 | B2: AMAZONAS | D2: 01 | E2: 01 | F2: CHACHAPOYAS | H2: 01 | I2: 01 | J2: 01 | K2: CHACHAPOYAS
A3: 02 | B3: ANCASH | D3: 01 | E3: 02 | F3: BAGUA | H3: 01 | I3: 01 | J3: 02 | K3: ASUNCION
A4: 03 | B4: APURIMAC | D4: 01 | E4: 03 | F4: BONGARA | H4: 01 | I4: 01 | J4: 03 | K4: BALSAS
A5: 04 | B5: AREQUIPA | D5: 01 | E5: 04 | F5: CONDORCANQUI | H5: 01 | I5: 01 | J5: 04 | K5: CHETO
A6: 05 | B6: AYACUCHO | D6: 01 | E6: 05 | F6: LUYA | H6: 01 | I6: 01 | J6: 05 | K6: CHILIQUIN
A7: 06 | B7: CAJAMARCA | D7: 01 | E7: 06 | F7: RODRIGUEZ DE MENDOZA | H7: 01 | I7: 01 | J7: 06 | K7: CHUQUIBAMBA
A8: 07 | B8: CALLAO | D8: 01 | E8: 07 | F8: UTCUBAMBA | H8: 01 | I8: 01 | J8: 07 | K8: GRANADA
A9: 08 | B9: CUSCO | D9: 02 | E9: 01 | F9: HUARAZ | H9: 01 | I9: 01 | J9: 08 | K9: HUANCAS
A10: 09 | B10: HUANCAVELICA | D10: 02 | E10: 02 | F10: AIJA | H10: 01 | I10: 01 | J10: 09 | K10: LA JALCA
A11: 10 | B11: HUANUCO | D11: 02 | E11: 03 | F11: ANTONIO RAYMONDI | H11: 01 | I11: 01 | J11: 10 | K11: LEIMEBAMBA
A12: 11 | B12: ICA | D12: 02 | E12: 04 | F12: ASUNCION | H12: 01 | I12: 01 | J12: 11 | K12: LEVANTO
... A26: 25 | B26: UCAYALI | D26: 02 | E26: 18 | F26: SANTA | H26: 01 | I26: 02 | J26: 04 | K26: EL PARCO
D27: 02 | E27: 19 | F27: SIHUAS | H27: 01 | I27: 02 | J27: 05 | K27: IMAZA
D28: 02 | E28: 20 | F28: YUNGAY | H28: 01 | I28: 03 | J28: 01 | K28: JUMBILLA
D29: 03 | E29: 01 | F29: ABANCAY | H29: 01 | I29: 03 | J29: 02 | K29: CHISQUILLA
D30: 03 | E30: 02 | F30: ANDAHUAYLAS | H30: 01 | I30: 03 | J30: 03 | K30: CHURUJA
D31: 03 | E31: 03 | F31: ANTABAMBA | H31: 01 | I31: 03 | J31: 04 | K31: COROSHA
D32: 03 | E32: 04 | F32: AYMARAES | H32: 01 | I32: 03 | J32: 05 | K32: CUISPES
D33: 03 | E33: 05 | F33: COTABAMBAS | H33: 01 | I33: 03 | J33: 06 | K33: FLORIDA
D34: 03 | E34: 06 | F34: CHINCHEROS | H34: 01 | I34: 03 | J34: 07 | K34: JAZAN
D35: 03 | E35: 07 | F35: GRAU | H35: 01 | I35: 03 | J35: 08 | K35: RECTA
D36: 04 | E36: 01 | F36: AREQUIPA | H36: 01 | I36: 03 | J36: 09 | K36: SAN CARLOS
D37: 04 | E37: 02 | F37: CAMANA | H37: 01 | I37: 03 | J37: 10 | K37: SHIPASBAMBA
D38: 04 | E38: 03 | F38: CARAVELI | H38: 01 | I38: 03 | J38: 11 | K38: VALERA
... D196: 25 | E196: 04 | F196: PURUS | H196: 02 | I196: 14 | J196: 08 | K196: SAN CRISTOBAL DE RAJAN
H197: 02 | I197: 14 | J197: 09 | K197: SAN PEDRO
H198: 02 | I198: 14 | J198: 10 | K198: SANTIAGO DE CHILCAS
H199: 02 | I199: 15 | J199: 01 | K199: CABANA
H200: 02 | I200: 15 | J200: 02 | K200: BOLOGNESI
H201: 02 | I201: 15 | J201: 03 | K201: CONCHUCOS
H202: 02 | I202: 15 | J202: 04 | K202: HUACASCHUQUE
H203: 02 | I203: 15 | J203: 05 | K203: HUANDOVAL
H204: 02 | I204: 15 | J204: 06 | K204: LACABAMBA
H205: 02 | I205: 15 | J205: 07 | K205: LLAPO
H206: 02 | I206: 15 | J206: 08 | K206: PALLASCA
H207: 02 | I207: 15 | J207: 09 | K207: PAMPAS
H208: 02 | I208: 15 | J208: 10 | K208: SANTA ROSA
... H1834: 20 | I1834: 01 | J1834: 15 | K1834: 26 DE OCTUBRE
